Workbook

Sheet START HERE
A1: Cells contained in this worksheet may contain cells with dropdown lists as well as autopopulated formulas.
A2: HECVAT™ Solution Provider Response - Start Here | F2: ='Auto Responses'!$A$36 -> Version 4.04
A3: Date Completed | C3: 45933
A4: Instructions for Solution Providers
A5: =HLOOKUP($A$4,'Auto Responses'!$D$2:$D$8,2,0)&"" -> 1. Complete the "Start Here" tab and review the "Required Questions" guidance to find the other sections are required for your product or service.
A6: =HLOOKUP($A$4,'Auto Responses'!$D$2:$D$8,3,0)&"" -> 2. Complete the "Organization" tab and the applicable questions in each of the next 5 tabs (Product through Privacy) that apply, based on your answers to the "Required Questions."
A7: =HLOOKUP($A$4,'Auto Responses'!$D$2:$D$8,4,0)&"" -> 3. Guidance in column E may change based on your answers to prompt details in "Additional Information." If leaving an answer blank, you must also state why in "Additional Information".
A8: =HLOOKUP($A$4,'Auto Responses'!$D$2:$D$8,5,0)&"" -> 4. DO NOT complete any fields in the "Evaluation" sheets or the "Analyst Notes" column.
A9: =HLOOKUP($A$4,'Auto Responses'!$D$2:$D$8,6,0)&"" -> 5. Return the completed file to institutions.
A10: =HLOOKUP($A$4,'Auto Responses'!$D$2:$D$8,7,0)&"" -> * Denotes critical questions. Critical questions are those deemed most important to institutions by higher education volunteers.
A11: =HLOOKUP($A$4,'Auto Responses'!$D$2:$D$9,8,0)&"" -> For full instructions, please visit educause.edu/HECVAT
A12: =VLOOKUP(LEFT($A13,4),'Auto Responses'!$N$4:$O$38,2,0)&"" -> General Information
A13: GNRL-01 | B13: =VLOOKUP($A13,Questions!$A$2:$X$333,2,0)&"" -> Solution Provider Name | C13: Coursedog
A14: GNRL-02 | B14: =VLOOKUP($A14,Questions!$A$2:$X$333,2,0)&"" -> Solution Name | C14: Coursedog
A15: GNRL-03 | B15: =VLOOKUP($A15,Questions!$A$2:$X$333,2,0)&"" -> Solution Description | C15: Coursedog is a SaaS platform designed to streamline curriculum, catalog, and scheduling management for higher education institutions, offering intuitive tools, insightful analytics, and seamless integration without requiring IT involvement.
A16: GNRL-04 | B16: =VLOOKUP($A16,Questions!$A$2:$X$333,2,0)&"" -> Solution Provider Contact Name
A17: GNRL-05 | B17: =VLOOKUP($A17,Questions!$A$2:$X$333,2,0)&"" -> Solution Provider Contact Title
A18: GNRL-06 | B18: =VLOOKUP($A18,Questions!$A$2:$X$333,2,0)&"" -> Solution Provider Contact Email | C18: contracts@coursedog.com
A19: GNRL-07 | B19: =VLOOKUP($A19,Questions!$A$2:$X$333,2,0)&"" -> Solution Provider Contact Phone Number | C19: (913) 565-2513
A20: GNRL-08 | B20: =VLOOKUP($A20,Questions!$A$2:$X$333,2,0)&"" -> Country of Company Headquarters | C20: United States
A21: GNRL-09 | B21: =VLOOKUP($A21,Questions!$A$2:$X$333,2,0)&"" -> Employee Work Locations (all) | C21: New York, various remote locations
A22: =VLOOKUP(LEFT($A23,4),'Auto Responses'!$N$4:$O$38,2,0)&"" -> Company Information | C22: Answer | D22: Additional Information | E22: Guidance | F22: Analyst Notes
A23: COMP-01 | B23: =VLOOKUP($A23,Questions!$A$2:$X$333,2,0)&"" -> Do you have a dedicated software and system development team(s) (e.g., customer support, implementation, product management, etc.)?* | C23: Yes | D23: Coursedog has a dedicated teams including Customer Success, Product Management, Customer Support, and Engineering. | E23: =IF($C23="Yes",VLOOKUP($A23,Questions!$A$2:$X$333,17,0)&"",IF($C23="No",VLOOKUP($A23,Questions!$A$2:$X$333,16,0)&"",VLOOKUP($A23,Questions!$A$2:$X$333,15,0)&"")) -> Describe the structure and size of your software and system development teams. (e.g., customer support, implementation, product management, etc.). | F23: =VLOOKUP($A23,'Institution Evaluation'!$A$56:$F$346,6,0)&""
A24: COMP-02 | B24: =VLOOKUP($A24,Questions!$A$2:$X$333,2,0)&"" -> Describe your organization’s business background and ownership structure, including all parent and subsidiary relationships. | D24: Coursedog, a leading Academic Operations Platform for higher education, has received a $90 million strategic growth investment from JMI Equity (“JMI”), a growth equity firm focused on investing in leading software companies. A three-time Forbes Top 500 Startup Employer, Coursedog is the leading Academic Operations Platform for Higher Education institutions. Coursedog was founded by Forbes 30 Under 30 members Justin Wenig and Nicholas Diao in 2018. JMI Equity is a growth equity firm focused on investing in leading software companies. For over three decades, JMI has partnered with exceptional founders, entrepreneurs, and management teams at high-growth software companies to provide flexible capital, industry expertise, and operational support to build businesses of enduring value. To date, JMI has invested in over 180 software businesses in North America and Europe and completed over 115 exits. Today, the Firm’s portfolio of industry-leading cloud software companies represents $8 billion in combined revenue, $65 billion in aggregate enterprise value, and over 34,000 jobs. | F24: =VLOOKUP($A24,'Institution Evaluation'!$A$56:$F$346,6,0)&""
A25: COMP-03 | B25: =VLOOKUP($A25,Questions!$A$2:$X$333,2,0)&"" -> Have you operated without unplanned disruptions to this solution in the past 12 months? | C25: No | E25: =IF($C25="Yes",VLOOKUP($A25,Questions!$A$2:$X$333,17,0)&"",IF($C25="No",VLOOKUP($A25,Questions!$A$2:$X$333,16,0)&"",VLOOKUP($A25,Questions!$A$2:$X$333,15,0)&"")) -> Provide a detailed summary of the unplanned disruption. | F25: =VLOOKUP($A25,'Institution Evaluation'!$A$56:$F$346,6,0)&""
A26: COMP-04 | B26: =VLOOKUP($A26,Questions!$A$2:$X$333,2,0)&"" -> Do you have a dedicated information security staff or office? | C26: Yes | D26: Roughly half of Coursedog is dedicated to R&D. This includes a Product Management and engineering teams. The Engineering team is led by a CTO and has a full time security officer. Each Engineer adheres to best practices set forth by the organization. Coursedog leverages external third parties for vulnerability scans and hosting (i.e. AWS). | E26: =IF($C26="Yes",VLOOKUP($A26,Questions!$A$2:$X$333,17,0)&"",IF($C26="No",VLOOKUP($A26,Questions!$A$2:$X$333,16,0)&"",VLOOKUP($A26,Questions!$A$2:$X$333,15,0)&"")) -> Describe your information security office, including size, talents, resources, etc. | F26: =VLOOKUP($A26,'Institution Evaluation'!$A$56:$F$346,6,0)&""
A27: COMP-05 | B27: =VLOOKUP($A27,Questions!$A$2:$X$333,2,0)&"" -> Use this area to share information about your environment that will assist those who are assessing your company's data security program. | D27: See our Coursedog Security Overview | F27: =VLOOKUP($A27,'Institution Evaluation'!$A$56:$F$346,6,0)&"" | G27: End Table Data
A28: =VLOOKUP(LEFT($A29,4),'Auto Responses'!$N$4:$O$38,2,0)&"" -> Required Questions | C28: Answer | D28: Additional Information | E28: Guidance | F28: Analyst Notes
A29: REQU-01 | B29: =VLOOKUP($A29,Questions!$A$2:$X$333,2,0)&"" -> Are you offering either a product or platform, as opposed to only offering a service | C29: Yes | D29: Coursedog is a SaaS platform designed to streamline curriculum, catalog, and scheduling management for higher education institutions, offering intuitive tools, insightful analytics, and seamless integration without requiring IT involvement. | E29: =IF($C29="Yes",VLOOKUP($A29,Questions!$A$2:$X$333,17,0)&"",IF($C29="No",VLOOKUP($A29,Questions!$A$2:$X$333,16,0)&"",VLOOKUP($A29,Questions!$A$2:$X$333,15,0)&"")) -> DO complete the Product and Infrastructure worksheets | F29: =VLOOKUP($A29,'Institution Evaluation'!$A$56:$F$346,6,0)&""
A30: REQU-02 | B30: =VLOOKUP($A30,Questions!$A$2:$X$333,2,0)&"" -> Does your product or service have an interface? | C30: Yes | D30: Coursedog provides a UI for all of its products with the platform | E30: =IF($C30="Yes",VLOOKUP($A30,Questions!$A$2:$X$333,17,0)&"",IF($C30="No",VLOOKUP($A30,Questions!$A$2:$X$333,16,0)&"",VLOOKUP($A30,Questions!$A$2:$X$333,15,0)&"")) -> DO complete the IT Accessibility worksheet. | F30: =VLOOKUP($A30,'Institution Evaluation'!$A$56:$F$346,6,0)&""
A31: REQU-03 | B31: =VLOOKUP($A31,Questions!$A$2:$X$333,2,0)&"" -> Are you providing consulting services? | C31: Yes | D31: Coursedog's professional services team, led by a project manager/subject matter expert, can work with your team for intensive business process consulting. | E31: =IF($C31="Yes",VLOOKUP($A31,Questions!$A$2:$X$333,17,0)&"",IF($C31="No",VLOOKUP($A31,Questions!$A$2:$X$333,16,0)&"",VLOOKUP($A31,Questions!$A$2:$X$333,15,0)&"")) -> DO complete the Consulting section in the Case-Specific worksheet | F31: =VLOOKUP($A31,'Institution Evaluation'!$A$56:$F$346,6,0)&""
A32: REQU-04 | B32: =VLOOKUP($A32,Questions!$A$2:$X$333,2,0)&"" -> Does your solution have AI features, or are there plans to implement AI features in the next 12 months? | C32: Yes | D32: Coursedog has implemented AI features including OpenAI integration for chat completions and embeddings, AI Hub product for controlling AI operations, merge error solutions with AI-powered recommendations, and an agentic chat assistant called "Cassie". | E32: =IF($C32="Yes",VLOOKUP($A32,Questions!$A$2:$X$333,17,0)&"",IF($C32="No",VLOOKUP($A32,Questions!$A$2:$X$333,16,0)&"",VLOOKUP($A32,Questions!$A$2:$X$333,15,0)&"")) -> DO complete the Artificial Intelligence (AI) worksheet | F32: =VLOOKUP($A32,'Institution Evaluation'!$A$56:$F$346,6,0)&""
A33: REQU-05 | B33: =VLOOKUP($A33,Questions!$A$2:$X$333,2,0)&"" -> Does your solution process protected health information (PHI) or any data covered by the Health Insurance Portability and Accountability Act (HIPAA)? | C33: No | E33: =IF($C33="Yes",VLOOKUP($A33,Questions!$A$2:$X$333,17,0)&"",IF($C33="No",VLOOKUP($A33,Questions!$A$2:$X$333,16,0)&"",VLOOKUP($A33,Questions!$A$2:$X$333,15,0)&"")) -> DO NOT complete the HIPAA section in the Case-Specific worksheet | F33: =VLOOKUP($A33,'Institution Evaluation'!$A$56:$F$346,6,0)&""
A34: REQU-06 | B34: =VLOOKUP($A34,Questions!$A$2:$X$333,2,0)&"" -> Is the solution designed to process, store, or transmit credit card information? | C34: No | E34: =IF($C34="Yes",VLOOKUP($A34,Questions!$A$2:$X$333,17,0)&"",IF($C34="No",VLOOKUP($A34,Questions!$A$2:$X$333,16,0)&"",VLOOKUP($A34,Questions!$A$2:$X$333,15,0)&"")) -> DO NOT complete the PCI-DSS section in the Case-Specific worksheet | F34: =VLOOKUP($A34,'Institution Evaluation'!$A$56:$F$346,6,0)&""
A35: REQU-07 | B35: =VLOOKUP($A35,Questions!$A$2:$X$333,2,0)&"" -> Does operating your solution require the institution to operate a physical or virtual appliance in their own environment or to provide inbound firewall exceptions to allow your employees to remotely administer systems in the institution's environment? | C35: No | E35: =IF($C35="Yes",VLOOKUP($A35,Questions!$A$2:$X$333,17,0)&"",IF($C35="No",VLOOKUP($A35,Questions!$A$2:$X$333,16,0)&"",VLOOKUP($A35,Questions!$A$2:$X$333,15,0)&"")) -> DO NOT complete the On-Prem section in the Case-Specific worksheet | F35: =VLOOKUP($A35,'Institution Evaluation'!$A$56:$F$346,6,0)&""
A36: REQU-08 | B36: =VLOOKUP($A36,Questions!$A$2:$X$333,2,0)&"" -> Does your solution have access to personal or institutional data? | C36: No | E36: =IF($C36="Yes",VLOOKUP($A36,Questions!$A$2:$X$333,17,0)&"",IF($C36="No",VLOOKUP($A36,Questions!$A$2:$X$333,16,0)&"",VLOOKUP($A36,Questions!$A$2:$X$333,15,0)&"")) -> DO NOT complete the Privacy tab | F36: =VLOOKUP($A36,'Institution Evaluation'!$A$56:$F$346,6,0)&"" | G36: End Table Data
A37: Note: The "Organization" tab is required for ALL products and services.
A38: Copyright © 2025 EDUCAUSE

Sheet Organization
A1: Cells contained in this worksheet may contain cells with dropdown lists as well as autopopulated formulas.
A2: HECVAT Solution Provider Response - Organization | F2: ='Auto Responses'!$A$36 -> Version 4.04
A3: Date Completed | C3: ='START HERE'!$C$3 -> 45933
A4: Instructions for Solution Providers
A5: =HLOOKUP($A$4,'Auto Responses'!$D$2:$D$8,2,0)&"" -> 1. Complete the "Start Here" tab and review the "Required Questions" guidance to find the other sections are required for your product or service.
A6: =HLOOKUP($A$4,'Auto Responses'!$D$2:$D$8,3,0)&"" -> 2. Complete the "Organization" tab and the applicable questions in each of the next 5 tabs (Product through Privacy) that apply, based on your answers to the "Required Questions."
A7: =HLOOKUP($A$4,'Auto Responses'!$D$2:$D$8,4,0)&"" -> 3. Guidance in column E may change based on your answers to prompt details in "Additional Information." If leaving an answer blank, you must also state why in "Additional Information".
A8: =HLOOKUP($A$4,'Auto Responses'!$D$2:$D$8,5,0)&"" -> 4. DO NOT complete any fields in the "Evaluation" sheets or the "Analyst Notes" column.
A9: =HLOOKUP($A$4,'Auto Responses'!$D$2:$D$8,6,0)&"" -> 5. Return the completed file to institutions.
A10: =HLOOKUP($A$4,'Auto Responses'!$D$2:$D$8,7,0)&"" -> * Denotes critical questions. Critical questions are those deemed most important to institutions by higher education volunteers.
A11: =HLOOKUP($A$4,'Auto Responses'!$D$2:$D$9,8,0)&"" -> For full instructions, please visit educause.edu/HECVAT
A12: =VLOOKUP(LEFT($A13,4),'Auto Responses'!$N$4:$O$38,2,0)&"" -> General Information | C12: Answer
A13: GNRL-01 | B13: =VLOOKUP($A13,Questions!$A$2:$X$333,2,0)&"" -> Solution Provider Name | C13: =VLOOKUP($A13,'START HERE'!$A$13:$C$21,3,0)&"" -> Coursedog
A14: GNRL-02 | B14: =VLOOKUP($A14,Questions!$A$2:$X$333,2,0)&"" -> Solution Name | C14: =VLOOKUP($A14,'START HERE'!$A$13:$C$21,3,0)&"" -> Coursedog
A15: GNRL-03 | B15: =VLOOKUP($A15,Questions!$A$2:$X$333,2,0)&"" -> Solution Description | C15: =VLOOKUP($A15,'START HERE'!$A$13:$C$21,3,0)&"" -> Coursedog is a SaaS platform designed to streamline curriculum, catalog, and scheduling management for higher education institutions, offering intuitive tools, insightful analytics, and seamless integration without requiring IT involvement.
A16: GNRL-04 | B16: =VLOOKUP($A16,Questions!$A$2:$X$333,2,0)&"" -> Solution Provider Contact Name | C16: =VLOOKUP($A16,'START HERE'!$A$13:$C$21,3,0)&""
A17: GNRL-05 | B17: =VLOOKUP($A17,Questions!$A$2:$X$333,2,0)&"" -> Solution Provider Contact Title | C17: =VLOOKUP($A17,'START HERE'!$A$13:$C$21,3,0)&""
A18: GNRL-06 | B18: =VLOOKUP($A18,Questions!$A$2:$X$333,2,0)&"" -> Solution Provider Contact Email | C18: =VLOOKUP($A18,'START HERE'!$A$13:$C$21,3,0)&"" -> contracts@coursedog.com
A19: GNRL-07 | B19: =VLOOKUP($A19,Questions!$A$2:$X$333,2,0)&"" -> Solution Provider Contact Phone Number | C19: =VLOOKUP($A19,'START HERE'!$A$13:$C$21,3,0)&"" -> (913) 565-2513
A20: GNRL-08 | B20: =VLOOKUP($A20,Questions!$A$2:$X$333,2,0)&"" -> Country of Company Headquarters | C20: =VLOOKUP($A20,'START HERE'!$A$13:$C$21,3,0)&"" -> United States
A21: =VLOOKUP(LEFT($A22,4),'Auto Responses'!$N$4:$O$38,2,0)&"" -> Documentation | C21: Answer | D21: Additional Information | E21: Guidance | F21: Analyst Notes
A22: DOCU-01 | B22: =VLOOKUP($A22,Questions!$A$2:$X$333,2,0) -> Do you have a well-documented business continuity plan (BCP), with a clear owner, that is tested annually?* | C22: Yes | D22: See our Coursedog Business Continutity and AWS disaster recovery procedure | F22: =VLOOKUP($A22,'Institution Evaluation'!$A$56:$F$346,6,0)&""
A23: DOCU-02 | B23: =VLOOKUP($A23,Questions!$A$2:$X$333,2,0) -> Do you have a well-documented disaster recovery plan (DRP), with a clear owner, that is tested annually?* | C23: Yes | D23: See AWS disaster recovery procedure | E23: =IF($C23="Yes",VLOOKUP($A23,Questions!$A$2:$X$333,17,0)&"",IF($C23="No",VLOOKUP($A23,Questions!$A$2:$X$333,16,0)&"",VLOOKUP($A23,Questions!$A$2:$X$333,15,0)&"")) | F23: =VLOOKUP($A23,'Institution Evaluation'!$A$56:$F$346,6,0)&""
A24: DOCU-03 | B24: =VLOOKUP($A24,Questions!$A$2:$X$333,2,0) -> Have you undergone a SSAE 18/SOC 2 audit? | C24: No | D24: SOCII compliance has been deferred to a later date. This decision is based on the fact that Coursedog does not store or process any personally identifiable information (PII), and none of our 300+ current customers require SOCII compliance at this time. For your reference, you can review details about SOCII and related compliance frameworks as they apply to our infrastructure provider, AWS, here. | E24: =IF($C24="Yes",VLOOKUP($A24,Questions!$A$2:$X$333,17,0)&"",IF($C24="No",VLOOKUP($A24,Questions!$A$2:$X$333,16,0)&"",VLOOKUP($A24,Questions!$A$2:$X$333,15,0)&"")) -> Describe any plans to undergo a SSAE 18 audit. | F24: =VLOOKUP($A24,'Institution Evaluation'!$A$56:$F$346,6,0)&""
A25: DOCU-04 | B25: =VLOOKUP($A25,Questions!$A$2:$X$333,2,0) -> Do you conform with a specific industry standard security framework (e.g., NIST Cybersecurity Framework, CIS Controls, ISO 27001, etc.)? | C25: No | D25: Coursedog has not obtained NIST SP 800-171 or CMMC Level 2 compliance certifications. However, Coursedog follows industry best practices for data security. Coursedog is in the process of obtaining the official ISO27001 certification. | E25: =IF($C25="Yes",VLOOKUP($A25,Questions!$A$2:$X$333,17,0)&"",IF($C25="No",VLOOKUP($A25,Questions!$A$2:$X$333,16,0)&"",VLOOKUP($A25,Questions!$A$2:$X$333,15,0)&"")) -> Describe any plans to conform to an industry standard security framework. | F25: =VLOOKUP($A25,'Institution Evaluation'!$A$56:$F$346,6,0)&""
A26: DOCU-05 | B26: =VLOOKUP($A26,Questions!$A$2:$X$333,2,0) -> Can you provide overall system and/or application architecture diagrams, including a full description of the data flow for all components of the system? | C26: Yes | D26: See our Coursedog Application Architecture for more detailed information. | E26: =IF($C26="Yes",VLOOKUP($A26,Questions!$A$2:$X$333,17,0)&"",IF($C26="No",VLOOKUP($A26,Questions!$A$2:$X$333,16,0)&"",VLOOKUP($A26,Questions!$A$2:$X$333,15,0)&"")) -> Provide your diagrams (or a valid link to it) upon submission. | F26: =VLOOKUP($A26,'Institution Evaluation'!$A$56:$F$346,6,0)&""
A27: DOCU-06 | B27: =VLOOKUP($A27,Questions!$A$2:$X$333,2,0) -> Does your organization have a data privacy policy? | C27: Yes | D27: See our Privacy Policy | E27: =IF($C27="Yes",VLOOKUP($A27,Questions!$A$2:$X$333,17,0)&"",IF($C27="No",VLOOKUP($A27,Questions!$A$2:$X$333,16,0)&"",VLOOKUP($A27,Questions!$A$2:$X$333,15,0)&"")) -> Provide your data privacy document (or a valid link to it) upon submission. | F27: =VLOOKUP($A27,'Institution Evaluation'!$A$56:$F$346,6,0)&""
A28: DOCU-07 | B28: =VLOOKUP($A28,Questions!$A$2:$X$333,2,0) -> Do you have a documented, and currently implemented, employee onboarding and offboarding policy? | C28: Yes | D28: The Coursedog onboarding document contains sensitive information and therefore is not available publically. | E28: =IF($C28="Yes",VLOOKUP($A28,Questions!$A$2:$X$333,17,0)&"",IF($C28="No",VLOOKUP($A28,Questions!$A$2:$X$333,16,0)&"",VLOOKUP($A28,Questions!$A$2:$X$333,15,0)&"")) -> Provide a reference to your employee onboarding and offboarding policy and supporting documentation or submit it along with this fully populated HECVAT. | F28: =VLOOKUP($A28,'Institution Evaluation'!$A$56:$F$346,6,0)&"" | G28: End Table Data
A29: =VLOOKUP(LEFT($A30,4),'Auto Responses'!$N$4:$O$38,2,0)&"" -> Assessment of Third Parties | C29: Answer | D29: Additional Information | E29: Guidance | F29: Analyst Notes
A30: THRD-01 | B30: =VLOOKUP($A30,Questions!$A$2:$X$333,2,0) -> Do you perform security assessments of third-party companies with which you share data (e.g., hosting providers, cloud services, PaaS, IaaS, SaaS)?* | C30: Yes | D30: Coursedog assess third party vendors based on data security (use of encryption and data security during processing transmission and storage, and data recoverable procedures) and network security (review of network architecture and security configurations, Anti-virus controls, penetration testing, security monitoring capabilities). | F30: =VLOOKUP($A30,'Institution Evaluation'!$A$56:$F$346,6,0)&""
A31: THRD-02 | B31: =VLOOKUP($A31,Questions!$A$2:$X$333,2,0) -> Do you have contractual language in place with third parties governing access to institutional data?* | C31: Yes | D31: Coursedog assess third party vendors based on data security (use of encryption and data security during processing transmission and storage, and data recoverable procedures) and network security (review of network architecture and security configurations, Anti-virus controls, penetration testing, security monitoring capabilities). | F31: =VLOOKUP($A31,'Institution Evaluation'!$A$56:$F$346,6,0)&""
A32: THRD-03 | B32: =VLOOKUP($A32,Questions!$A$2:$X$333,2,0) -> Do the contracts in place with these third parties address liability in the event of a data breach?* | C32: Yes | D32: For each of these vendors, we use their standard SaaS agreements and each of them have guardrails in place the address liabiliity in case of a data breach. | F32: =VLOOKUP($A32,'Institution Evaluation'!$A$56:$F$346,6,0)&""
A33: THRD-04 | B33: =VLOOKUP($A33,Questions!$A$2:$X$333,2,0) -> Do you have an implemented third-party management strategy?* | C33: Yes | D33: See Coursedog Architecture for more information. | E33: =IF($C33="Yes",VLOOKUP($A33,Questions!$A$2:$X$333,17,0)&"",IF($C33="No",VLOOKUP($A33,Questions!$A$2:$X$333,16,0)&"",VLOOKUP($A33,Questions!$A$2:$X$333,15,0)&"")) -> Provide additional information that may help analysts better understand your environment and how it relates to third-party solutions. | F33: =VLOOKUP($A33,'Institution Evaluation'!$A$56:$F$346,6,0)&""
A34: THRD-05 | B34: =VLOOKUP($A34,Questions!$A$2:$X$333,2,0) -> Do you have a process and implemented procedures for managing your hardware supply chain (e.g., telecommunications equipment, export licensing, computing devices)? | C34: Yes | D34: See our security overview for more information. | E34: =IF($C34="Yes",VLOOKUP($A34,Questions!$A$2:$X$333,17,0)&"",IF($C34="No",VLOOKUP($A34,Questions!$A$2:$X$333,16,0)&"",VLOOKUP($A34,Questions!$A$2:$X$333,15,0)&"")) -> State what countries and/or regions this process is compliant with. | F34: =VLOOKUP($A34,'Institution Evaluation'!$A$56:$F$346,6,0)&"" | G34: End Table Data
A35: =VLOOKUP(LEFT($A36,4),'Auto Responses'!$N$4:$O$38,2,0)&"" -> Change Management | C35: Answer | D35: Additional Information | E35: Guidance | F35: Analyst Notes
A36: CHNG-01 | B36: =VLOOKUP($A36,Questions!$A$2:$X$333,2,0) -> Will the institution be notified of major changes to your environment that could impact the institution's security posture?* | C36: Yes | D36: Institutions will be notified within 24 hours | E36: =IF($C36="Yes",VLOOKUP($A36,Questions!$A$2:$X$333,17,0)&"",IF($C36="No",VLOOKUP($A36,Questions!$A$2:$X$333,16,0)&"",VLOOKUP($A36,Questions!$A$2:$X$333,15,0)&"")) -> State how and when the institution will be notified of major changes to your environment. | F36: =VLOOKUP($A36,'Institution Evaluation'!$A$56:$F$346,6,0)&""
A37: CHNG-02 | B37: =VLOOKUP($A37,Questions!$A$2:$X$333,2,0) -> Does the system support client customizations from one release to another?* | C37: Yes | D37: Coursedog is a software as a service (SaaS) solution and therefore all usrs operate within the same version. See answer to CHNG-04 for more details on feature specific items. | E37: =IF($C37="Yes",VLOOKUP($A37,Questions!$A$2:$X$333,17,0)&"",IF($C37="No",VLOOKUP($A37,Questions!$A$2:$X$333,16,0)&"",VLOOKUP($A37,Questions!$A$2:$X$333,15,0)&"")) -> Describe or provide reference to your solution support strategy in regard to maintaining client customizations from one release to another. | F37: =VLOOKUP($A37,'Institution Evaluation'!$A$56:$F$346,6,0)&""
A38: CHNG-03 | B38: =VLOOKUP($A38,Questions!$A$2:$X$333,2,0) -> Do you have an implemented system configuration management process (e.g.,secure "gold" images, etc.)?* | C38: Yes | D38: AWS | E38: =IF($C38="Yes",VLOOKUP($A38,Questions!$A$2:$X$333,17,0)&"",IF($C38="No",VLOOKUP($A38,Questions!$A$2:$X$333,16,0)&"",VLOOKUP($A38,Questions!$A$2:$X$333,15,0)&"")) -> Summarize your implemented system configuration management precess. | F38: =VLOOKUP($A38,'Institution Evaluation'!$A$56:$F$346,6,0)&""
A39: CHNG-04 | B39: =VLOOKUP($A39,Questions!$A$2:$X$333,2,0) -> Do you have a documented change management process? | C39: Yes | D39: Coursedog communicates all platform wide updates. (See release notes) All features (e.g. integration changes) are behind a feature toggle and therefore can opted out. Coursedog recommends you disucuss specific situations with your dedicated Customer Success Manager (CSM). | E39: =IF($C39="Yes",VLOOKUP($A39,Questions!$A$2:$X$333,17,0)&"",IF($C39="No",VLOOKUP($A39,Questions!$A$2:$X$333,16,0)&"",VLOOKUP($A39,Questions!$A$2:$X$333,15,0)&"")) -> Summarize your current change management process. | F39: =VLOOKUP($A39,'Institution Evaluation'!$A$56:$F$346,6,0)&""
A40: CHNG-05 | B40: =VLOOKUP($A40,Questions!$A$2:$X$333,2,0) -> Does your change management process minimally include authorization, impact analysis, testing, and validation before moving changes to production? | C40: Yes | D40: Our change management process includes impact analysis, authorization by leadership, testing in staging, and validation before moving to production. Learn More about Change Management | E40: =IF($C40="Yes",VLOOKUP($A40,Questions!$A$2:$X$333,17,0)&"",IF($C40="No",VLOOKUP($A40,Questions!$A$2:$X$333,16,0)&"",VLOOKUP($A40,Questions!$A$2:$X$333,15,0)&"")) -> Indicate all procedures that are implemented in your change management process. (a) An impact analysis of the upgrade is performed. (b) The change is appropriately authorized. (c) Changes are made first in a test environment. (d) The ability to implement the upgrades/changes in the production environment is limited to appropriate IT personnel. | F40: =VLOOKUP($A40,'Institution Evaluation'!$A$56:$F$346,6,0)&""
A41: CHNG-06 | B41: =VLOOKUP($A41,Questions!$A$2:$X$333,2,0) -> Does your change management process verify that all required third-party libraries and dependencies are still supported with each major change? | C41: No | D41: N/A | E41: =IF($C41="Yes",VLOOKUP($A41,Questions!$A$2:$X$333,17,0)&"",IF($C41="No",VLOOKUP($A41,Questions!$A$2:$X$333,16,0)&"",VLOOKUP($A41,Questions!$A$2:$X$333,15,0)&"")) -> Please describe any plans to implement third-party library dependancy tracking. | F41: =VLOOKUP($A41,'Institution Evaluation'!$A$56:$F$346,6,0)&""
A42: CHNG-07 | B42: =VLOOKUP($A42,Questions!$A$2:$X$333,2,0) -> Do you have policy and procedure, currently implemented, managing how critical patches are applied to all systems and applications? | C42: Yes | D42: The majority of our applicaiton and infastructre is automatically maintained and updated by AWS without any downtime. Application specific patches are reviewed by our head Application Engineer and foldeded into our production environment after it is fully tested and validated in our staging instance. | E42: =IF($C42="Yes",VLOOKUP($A42,Questions!$A$2:$X$333,17,0)&"",IF($C42="No",VLOOKUP($A42,Questions!$A$2:$X$333,16,0)&"",VLOOKUP($A42,Questions!$A$2:$X$333,15,0)&"")) -> Summarize the policy and procedure(s) managing how critical patches are applied to systems and applications. | F42: =VLOOKUP($A42,'Institution Evaluation'!$A$56:$F$346,6,0)&""
A43: CHNG-08 | B43: =VLOOKUP($A43,Questions!$A$2:$X$333,2,0) -> Have you implemented policies and procedures that guide how security risks are mitigated until patches can be applied? | C43: Yes | D43: The Coursedog head Application Engineer will make these decisions on a case by case basis. Coursedog always has the ability to roll back versions due to our cloud based architecture. See our response to CHNG-14. | E43: =IF($C43="Yes",VLOOKUP($A43,Questions!$A$2:$X$333,17,0)&"",IF($C43="No",VLOOKUP($A43,Questions!$A$2:$X$333,16,0)&"",VLOOKUP($A43,Questions!$A$2:$X$333,15,0)&"")) -> Summarize the policy and procedure(s) guiding risk mitigation practices before critical patches can be applied. | F43: =VLOOKUP($A43,'Institution Evaluation'!$A$56:$F$346,6,0)&""
A44: CHNG-09 | B44: =VLOOKUP($A44,Questions!$A$2:$X$333,2,0) -> Do clients have the option to not participate in or postpone an upgrade to a new release? | C44: Yes | D44: Coursedog communicates all non-breaking platform wide updates. All breaking features are behind a feature toggle and therefore can opted out. Coursedog recommends you disucuss specific situations with your dedicated Customer Success Manager (CSM). | E44: =IF($C44="Yes",VLOOKUP($A44,Questions!$A$2:$X$333,17,0)&"",IF($C44="No",VLOOKUP($A44,Questions!$A$2:$X$333,16,0)&"",VLOOKUP($A44,Questions!$A$2:$X$333,15,0)&"")) -> Provide reference the the process/procedure to manage releases. | F44: =VLOOKUP($A44,'Institution Evaluation'!$A$56:$F$346,6,0)&""
A45: CHNG-10 | B45: =VLOOKUP($A45,Questions!$A$2:$X$333,2,0) -> Do you have a fully implemented solution support strategy that defines how many concurrent versions you support? | C45: Yes | D45: Coursedog is a software as a service (SaaS) solution and therefore all users operate within the same version. See answer to CHNG-09 for more details on feature specific items. | F45: =VLOOKUP($A45,'Institution Evaluation'!$A$56:$F$346,6,0)&""
A46: CHNG-11 | B46: =VLOOKUP($A46,Questions!$A$2:$X$333,2,0) -> Do you have a release schedule for product updates? | C46: Yes | D46: Coursedog communicates all platform wide updates. (See release notes) All features (e.g. integration changes) are behind a feature toggle and therefore can opted out. Coursedog recommends you disucuss specific situations with your dedicated Customer Success Manager (CSM). | E46: =IF($C46="Yes",VLOOKUP($A46,Questions!$A$2:$X$333,17,0)&"",IF($C46="No",VLOOKUP($A46,Questions!$A$2:$X$333,16,0)&"",VLOOKUP($A46,Questions!$A$2:$X$333,15,0)&"")) -> Provide a reference to this solution's release schedule. | F46: =VLOOKUP($A46,'Institution Evaluation'!$A$56:$F$346,6,0)&""
A47: CHNG-12 | B47: =VLOOKUP($A47,Questions!$A$2:$X$333,2,0) -> Do you have a technology roadmap, for at least the next two years, for enhancements and bug fixes for the solution being assessed? | C47: Yes | D47: Coursedog maintains a roadmap for each product up to a year out. Coursedog is happy to share the roadmap with current customers. | E47: =IF($C47="Yes",VLOOKUP($A47,Questions!$A$2:$X$333,17,0)&"",IF($C47="No",VLOOKUP($A47,Questions!$A$2:$X$333,16,0)&"",VLOOKUP($A47,Questions!$A$2:$X$333,15,0)&"")) -> Provide a reference to your technology roadmap. | F47: =VLOOKUP($A47,'Institution Evaluation'!$A$56:$F$346,6,0)&""
A48: CHNG-13 | B48: =VLOOKUP($A48,Questions!$A$2:$X$333,2,0) -> Can solution updates be completed without institutional involvement (i.e., technically or organizationally)? | C48: Yes | D48: Coursedog communicates all platform wide updates. (See release notes) All features (e.g. integration changes) are behind a feature toggle and therefore can opted out. Coursedog recommends you disucuss specific situations with your dedicated Customer Success Manager (CSM). | E48: =IF($C48="Yes",VLOOKUP($A48,Questions!$A$2:$X$333,17,0)&"",IF($C48="No",VLOOKUP($A48,Questions!$A$2:$X$333,16,0)&"",VLOOKUP($A48,Questions!$A$2:$X$333,15,0)&"")) | F48: =VLOOKUP($A48,'Institution Evaluation'!$A$56:$F$346,6,0)&""
A49: CHNG-14 | B49: =VLOOKUP($A49,Questions!$A$2:$X$333,2,0) -> Are upgrades or system changes installed during off-peak hours or in a manner that does not impact the customer? | C49: Yes | D49: Coursedogs utilizes rolling deployments via AWS Elastic Beanstalk so we can deploy updates without zero downtime. The application has multiple servers live at any single moment in time, so when we apply updates, one server is taken out of commission while all user access is automatically delegated to the other servers. This process is replicated until all servers have been updated - and during this process users will experience no downtime. This ensures our application is always available for end users. | E49: =IF($C49="Yes",VLOOKUP($A49,Questions!$A$2:$X$333,17,0)&"",IF($C49="No",VLOOKUP($A49,Questions!$A$2:$X$333,16,0)&"",VLOOKUP($A49,Questions!$A$2:$X$333,15,0)&"")) -> Define current off-peak hours, including time zones as necessary. | F49: =VLOOKUP($A49,'Institution Evaluation'!$A$56:$F$346,6,0)&""
A50: CHNG-15 | B50: =VLOOKUP($A50,Questions!$A$2:$X$333,2,0) -> Do procedures exist to provide that emergency changes are documented and authorized (including after-the-fact approval)? | C50: Yes | D50: All emergency changes must go through a peer review process that is ultimately signed off on by our CTO. | E50: =IF($C50="Yes",VLOOKUP($A50,Questions!$A$2:$X$333,17,0)&"",IF($C50="No",VLOOKUP($A50,Questions!$A$2:$X$333,16,0)&"",VLOOKUP($A50,Questions!$A$2:$X$333,15,0)&"")) -> Summarize implemented procedures ensuring that emergency changes are documented and authorized. | F50: =VLOOKUP($A50,'Institution Evaluation'!$A$56:$F$346,6,0)&""
A51: CHNG-16 | B51: =VLOOKUP($A51,Questions!$A$2:$X$333,2,0) -> Do you have a systems management and configuration strategy that encompasses servers, appliances, cloud services, applications, and mobile devices (company and employee owned)? | C51: Yes | D51: AWS / Not Relevant | E51: =IF($C51="Yes",VLOOKUP($A51,Questions!$A$2:$X$333,17,0)&"",IF($C51="No",VLOOKUP($A51,Questions!$A$2:$X$333,16,0)&"",VLOOKUP($A51,Questions!$A$2:$X$333,15,0)&"")) -> Summarize your systems management and configuration strategy. | F51: =VLOOKUP($A51,'Institution Evaluation'!$A$56:$F$346,6,0)&"" | G51: End Table Data
A52: =VLOOKUP(LEFT($A53,4),'Auto Responses'!$N$4:$O$38,2,0)&"" -> Policies, Processes, and Procedures | C52: Answer | D52: Additional Information | E52: Guidance | F52: Analyst Notes
A53: PPPR-01 | B53: =VLOOKUP($A53,Questions!$A$2:$X$333,2,0) -> Do you have a documented patch management process?* | C53: Yes | D53: Available up request | E53: =IF($C53="Yes",VLOOKUP($A53,Questions!$A$2:$X$333,17,0)&"",IF($C53="No",VLOOKUP($A53,Questions!$A$2:$X$333,16,0)&"",VLOOKUP($A53,Questions!$A$2:$X$333,15,0)&"")) | F53: =VLOOKUP($A53,'Institution Evaluation'!$A$56:$F$346,6,0)&""
A54: PPPR-02 | B54: =VLOOKUP($A54,Questions!$A$2:$X$333,2,0) -> Can your organization comply with institutional policies on privacy and data protection with regard to users of institutional systems, if required?* | C54: No | D54: Coursedog followes industry standard security policies and is willing to discuss the specific policy. | E54: =IF($C54="Yes",VLOOKUP($A54,Questions!$A$2:$X$333,17,0)&"",IF($C54="No",VLOOKUP($A54,Questions!$A$2:$X$333,16,0)&"",VLOOKUP($A54,Questions!$A$2:$X$333,15,0)&"")) -> Summarize why you will not comply with the institution's IT policy with regards to user privacy and data protection. | F54: =VLOOKUP($A54,'Institution Evaluation'!$A$56:$F$346,6,0)&""
A55: PPPR-03 | B55: =VLOOKUP($A55,Questions!$A$2:$X$333,2,0) -> Is your company subject to the institution's geographic region's laws and regulations?* | C55: Yes | E55: =IF($C55="Yes",VLOOKUP($A55,Questions!$A$2:$X$333,17,0)&"",IF($C55="No",VLOOKUP($A55,Questions!$A$2:$X$333,16,0)&"",VLOOKUP($A55,Questions!$A$2:$X$333,15,0)&"")) | F55: =VLOOKUP($A55,'Institution Evaluation'!$A$56:$F$346,6,0)&""
A56: PPPR-04 | B56: =VLOOKUP($A56,Questions!$A$2:$X$333,2,0) -> Can you accommodate encryption requirements using open standards? | C56: Yes | D56: See our Coursedog Security Overview | E56: =IF($C56="Yes",VLOOKUP($A56,Questions!$A$2:$X$333,17,0)&"",IF($C56="No",VLOOKUP($A56,Questions!$A$2:$X$333,16,0)&"",VLOOKUP($A56,Questions!$A$2:$X$333,15,0)&"")) | F56: =VLOOKUP($A56,'Institution Evaluation'!$A$56:$F$346,6,0)&""
A57: PPPR-05 | B57: =VLOOKUP($A57,Questions!$A$2:$X$333,2,0) -> Do you have a documented systems development life cycle (SDLC)? | C57: Yes | D57: Process is Requirement Gathering and Analysis, Design, Development using Atom and Git, Testing using Jest, Cypress, and CircleCi, Deployment using AWS Elastic beanstalk, Maintenance using AWS cloudwatch, AWS Elsastic beanstalk, and AWS S3 | E57: =IF($C57="Yes",VLOOKUP($A57,Questions!$A$2:$X$333,17,0)&"",IF($C57="No",VLOOKUP($A57,Questions!$A$2:$X$333,16,0)&"",VLOOKUP($A57,Questions!$A$2:$X$333,15,0)&"")) -> Briefly summarize your SDLC or provide a link or attachment. | F57: =VLOOKUP($A57,'Institution Evaluation'!$A$56:$F$346,6,0)&""
A58: PPPR-06 | B58: =VLOOKUP($A58,Questions!$A$2:$X$333,2,0) -> Do you perform background screenings or multi-state background checks on all employees prior to their first day of work? | C58: Yes | D58: Coursedog uses Checkr for all employee screening | E58: =IF($C58="Yes",VLOOKUP($A58,Questions!$A$2:$X$333,17,0)&"",IF($C58="No",VLOOKUP($A58,Questions!$A$2:$X$333,16,0)&"",VLOOKUP($A58,Questions!$A$2:$X$333,15,0)&"")) -> Summarize your background check practices. | F58: =VLOOKUP($A58,'Institution Evaluation'!$A$56:$F$346,6,0)&""
A59: PPPR-07 | B59: =VLOOKUP($A59,Questions!$A$2:$X$333,2,0) -> Do you require new employees to fill out agreements and review policies? | C59: Yes | D59: All Coursedog employees must review and acknowledge applicable security policies | E59: =IF($C59="Yes",VLOOKUP($A59,Questions!$A$2:$X$333,17,0)&"",IF($C59="No",VLOOKUP($A59,Questions!$A$2:$X$333,16,0)&"",VLOOKUP($A59,Questions!$A$2:$X$333,15,0)&"")) -> Summarize the required agreements and reviewed policies. | F59: =VLOOKUP($A59,'Institution Evaluation'!$A$56:$F$346,6,0)&""
A60: PPPR-08 | B60: =VLOOKUP($A60,Questions!$A$2:$X$333,2,0) -> Do you have a documented information security policy? | C60: Yes | D60: See our Coursedog Security Overview | E60: =IF($C60="Yes",VLOOKUP($A60,Questions!$A$2:$X$333,17,0)&"",IF($C60="No",VLOOKUP($A60,Questions!$A$2:$X$333,16,0)&"",VLOOKUP($A60,Questions!$A$2:$X$333,15,0)&"")) -> Provide a reference to your information security policy or submit documentation with this fully populated HECVAT. | F60: =VLOOKUP($A60,'Institution Evaluation'!$A$56:$F$346,6,0)&""
A61: PPPR-09 | B61: =VLOOKUP($A61,Questions!$A$2:$X$333,2,0) -> Are information security principles designed into the product lifecycle? | C61: Yes | D61: See OWASP | E61: =IF($C61="Yes",VLOOKUP($A61,Questions!$A$2:$X$333,17,0)&"",IF($C61="No",VLOOKUP($A61,Questions!$A$2:$X$333,16,0)&"",VLOOKUP($A61,Questions!$A$2:$X$333,15,0)&"")) -> Summarize the information security principles designed into the product lifecycle. | F61: =VLOOKUP($A61,'Institution Evaluation'!$A$56:$F$346,6,0)&""
A62: PPPR-10 | B62: =VLOOKUP($A62,Questions!$A$2:$X$333,2,0) -> Will you comply with applicable breach notification laws? | C62: Yes | D62: in SLA | E62: =IF($C62="Yes",VLOOKUP($A62,Questions!$A$2:$X$333,17,0)&"",IF($C62="No",VLOOKUP($A62,Questions!$A$2:$X$333,16,0)&"",VLOOKUP($A62,Questions!$A$2:$X$333,15,0)&"")) -> State how quickly the institution will be notified of a data breach or security incident. | F62: =VLOOKUP($A62,'Institution Evaluation'!$A$56:$F$346,6,0)&""
A63: PPPR-11 | B63: =VLOOKUP($A63,Questions!$A$2:$X$333,2,0) -> Do you have an information security awareness program? | C63: Yes | D63: Once annually and during onboarding | E63: =IF($C63="Yes",VLOOKUP($A63,Questions!$A$2:$X$333,17,0)&"",IF($C63="No",VLOOKUP($A63,Questions!$A$2:$X$333,16,0)&"",VLOOKUP($A63,Questions!$A$2:$X$333,15,0)&"")) -> Summarize your information security awareness program. | F63: =VLOOKUP($A63,'Institution Evaluation'!$A$56:$F$346,6,0)&""
A64: PPPR-12 | B64: =VLOOKUP($A64,Questions!$A$2:$X$333,2,0) -> Is security awareness training mandatory for all employees? | C64: Yes | D64: Once annually and during onboarding | E64: =IF($C64="Yes",VLOOKUP($A64,Questions!$A$2:$X$333,17,0)&"",IF($C64="No",VLOOKUP($A64,Questions!$A$2:$X$333,16,0)&"",VLOOKUP($A64,Questions!$A$2:$X$333,15,0)&"")) -> Summarize your security awareness training content and state how frequently employees are required to undergo security awareness training. | F64: =VLOOKUP($A64,'Institution Evaluation'!$A$56:$F$346,6,0)&""
A65: PPPR-13 | B65: =VLOOKUP($A65,Questions!$A$2:$X$333,2,0) -> Do you have process and procedure(s) documented, and currently followed, that require a review and update of the access list(s) for privileged accounts? | C65: Yes | D65: Access updates / lists can be manged via Attributes in the configuration of Single Sign On for all account types. | E65: =IF($C65="Yes",VLOOKUP($A65,Questions!$A$2:$X$333,17,0)&"",IF($C65="No",VLOOKUP($A65,Questions!$A$2:$X$333,16,0)&"",VLOOKUP($A65,Questions!$A$2:$X$333,15,0)&"")) -> Provide a brief summary and the implement review interval. | F65: =VLOOKUP($A65,'Institution Evaluation'!$A$56:$F$346,6,0)&""
A66: PPPR-14 | B66: =VLOOKUP($A66,Questions!$A$2:$X$333,2,0) -> Do you have documented, and currently implemented, internal audit processes and procedures? | C66: Yes | D66: See our Coursedog Security Overview | E66: =IF($C66="Yes",VLOOKUP($A66,Questions!$A$2:$X$333,17,0)&"",IF($C66="No",VLOOKUP($A66,Questions!$A$2:$X$333,16,0)&"",VLOOKUP($A66,Questions!$A$2:$X$333,15,0)&"")) -> Summarize your internal audit processes and procedures. | F66: =VLOOKUP($A66,'Institution Evaluation'!$A$56:$F$346,6,0)&""
A67: PPPR-15 | B67: =VLOOKUP($A67,Questions!$A$2:$X$333,2,0) -> Does your organization have physical security controls and policies in place? | C67: Yes | D67: See AWS Controls | E67: =IF($C67="Yes",VLOOKUP($A67,Questions!$A$2:$X$333,17,0)&"",IF($C67="No",VLOOKUP($A67,Questions!$A$2:$X$333,16,0)&"",VLOOKUP($A67,Questions!$A$2:$X$333,15,0)&"")) -> Provide a copy of your physical security controls and policies along with this document (link or attached). | F67: =VLOOKUP($A67,'Institution Evaluation'!$A$56:$F$346,6,0)&"" | G67: End Table Data
A68: Copyright © 2025 EDUCAUSE
A71: =#REF! -> #REF!
A72: =#REF! -> #REF!
A73: =#REF! -> #REF!
A74: =#REF! -> #REF!
A75: =#REF! -> #REF!
A76: =#REF! -> #REF!
A77: =#REF! -> #REF!

Sheet Product
A1: Cells contained in this worksheet may contain cells with dropdown lists as well as autopopulated formulas.
A2: HECVAT Solution Provider Response - Product | F2: ='Auto Responses'!$A$36 -> Version 4.04
A3: Date Completed | C3: ='START HERE'!$C$3 -> 45933
A4: Instructions for Solution Providers
A5: =HLOOKUP($A$4,'Auto Responses'!$D$2:$D$8,2,0)&"" -> 1. Complete the "Start Here" tab and review the "Required Questions" guidance to find the other sections are required for your product or service.
A6: =HLOOKUP($A$4,'Auto Responses'!$D$2:$D$8,3,0)&"" -> 2. Complete the "Organization" tab and the applicable questions in each of the next 5 tabs (Product through Privacy) that apply, based on your answers to the "Required Questions."
A7: =HLOOKUP($A$4,'Auto Responses'!$D$2:$D$8,4,0)&"" -> 3. Guidance in column E may change based on your answers to prompt details in "Additional Information." If leaving an answer blank, you must also state why in "Additional Information".
A8: =HLOOKUP($A$4,'Auto Responses'!$D$2:$D$8,5,0)&"" -> 4. DO NOT complete any fields in the "Evaluation" sheets or the "Analyst Notes" column.
A9: =HLOOKUP($A$4,'Auto Responses'!$D$2:$D$8,6,0)&"" -> 5. Return the completed file to institutions.
A10: =HLOOKUP($A$4,'Auto Responses'!$D$2:$D$8,7,0)&"" -> * Denotes critical questions. Critical questions are those deemed most important to institutions by higher education volunteers.
A11: =HLOOKUP($A$4,'Auto Responses'!$D$2:$D$9,8,0)&"" -> For full instructions, please visit educause.edu/HECVAT
A12: =VLOOKUP(LEFT($A13,4),'Auto Responses'!$N$4:$O$38,2,0)&"" -> General Information | C12: Answer
A13: GNRL-01 | B13: =VLOOKUP($A13,Questions!$A$2:$X$333,2,0)&"" -> Solution Provider Name | C13: =VLOOKUP($A13,'START HERE'!$A$13:$C$21,3,0)&"" -> Coursedog
A14: GNRL-02 | B14: =VLOOKUP($A14,Questions!$A$2:$X$333,2,0)&"" -> Solution Name | C14: =VLOOKUP($A14,'START HERE'!$A$13:$C$21,3,0)&"" -> Coursedog
A15: GNRL-03 | B15: =VLOOKUP($A15,Questions!$A$2:$X$333,2,0)&"" -> Solution Description | C15: =VLOOKUP($A15,'START HERE'!$A$13:$C$21,3,0)&"" -> Coursedog is a SaaS platform designed to streamline curriculum, catalog, and scheduling management for higher education institutions, offering intuitive tools, insightful analytics, and seamless integration without requiring IT involvement.
A16: GNRL-08 | B16: =VLOOKUP($A16,Questions!$A$2:$X$333,2,0)&"" -> Country of Company Headquarters | C16: =VLOOKUP($A16,'START HERE'!$A$13:$C$21,3,0)&"" -> United States
A17: =VLOOKUP(LEFT($A18,4),'Auto Responses'!$N$4:$O$38,2,0)&"" -> Required Questions | C17: Answer | E17: Guidance | F17: Analyst Notes
A18: REQU-01 | B18: =VLOOKUP($A18,Questions!$A$2:$X$333,2,0) -> Are you offering either a product or platform, as opposed to only offering a service | C18: =VLOOKUP($A18,'START HERE'!$A$23:$F$36,3,0)&"" -> Yes | D18: =VLOOKUP($A18,'START HERE'!$A$23:$F$36,4,0)&"" -> Coursedog is a SaaS platform designed to streamline curriculum, catalog, and scheduling management for higher education institutions, offering intuitive tools, insightful analytics, and seamless integration without requiring IT involvement. | E18: =IF($C18="Yes",VLOOKUP($A18,Questions!$A$2:$X$333,17,0)&"",IF($C18="No",VLOOKUP($A18,Questions!$A$2:$X$333,16,0)&"",VLOOKUP($A18,Questions!$A$2:$X$333,15,0)&"")) -> DO complete the Product and Infrastructure worksheets | F18: =VLOOKUP($A18,'Institution Evaluation'!$A$56:$F$346,6,0)&"" | G18: End Table Data
A19: =VLOOKUP(LEFT($A20,4),'Auto Responses'!$N$4:$O$38,2,0)&"" -> Authentication, Authorization, and Account Management | C19: Answer | D19: Additional Information | E19: Guidance | F19: Analyst Notes
A20: AAAI-01 | B20: =VLOOKUP($A20,Questions!$A$2:$X$333,2,0) -> Does your solution support single sign-on (SSO) protocols for user and administrator authentication?* | C20: Yes | D20: Yes, Coursedog supports SSO for authentication and provisioning purposes. Read More about SSO | E20: =IF($C$18="No",'Auto Responses'!$A$3,IF($C20="Yes",VLOOKUP($A20,Questions!$A$2:$X$333,17,0)&"",IF($C20="No",VLOOKUP($A20,Questions!$A$2:$X$333,16,0)&"",VLOOKUP($A20,Questions!$A$2:$X$333,15,0)&""))) -> Describe how strong authentication is enforced (e.g., complex passwords, multifactor tokens, certificates, biometrics, aging requirements, re-use policy). | F20: =VLOOKUP($A20,'Institution Evaluation'!$A$56:$F$346,6,0)&""
A21: AAAI-02 | B21: =VLOOKUP($A21,Questions!$A$2:$X$333,2,0) -> Does your solution support local authentication protocols for user and administrator authentication?* | C21: Yes | D21: See user Authentification documentation for more information. | E21: =IF($C$18="No",'Auto Responses'!$A$3,IF($C21="Yes",VLOOKUP($A21,Questions!$A$2:$X$333,17,0)&"",IF($C21="No",VLOOKUP($A21,Questions!$A$2:$X$333,16,0)&"",VLOOKUP($A21,Questions!$A$2:$X$333,15,0)&""))) -> Provide a detailed description of your local authentication mode practices. | F21: =VLOOKUP($A21,'Institution Evaluation'!$A$56:$F$346,6,0)&""
A22: AAAI-03 | B22: =VLOOKUP($A22,Questions!$A$2:$X$333,2,0) -> Can you enforce password/passphrase complexity requirements (provided by the institution)?* | C22: Yes | D22: Coursedog recommends you use single sign on (SSO) for all admin access to Coursedog. That said, Coursedog has password aging on our near term roadmap. | E22: =IF($C$18="No",'Auto Responses'!$A$3,IF($C22="Yes",VLOOKUP($A22,Questions!$A$2:$X$333,17,0)&"",IF($C22="No",VLOOKUP($A22,Questions!$A$2:$X$333,16,0)&"",VLOOKUP($A22,Questions!$A$2:$X$333,15,0)&""))) -> Describe how password/passphrase complexity requirements are implemented in the product. | F22: =VLOOKUP($A22,'Institution Evaluation'!$A$56:$F$346,6,0)&""
A23: AAAI-04 | B23: =VLOOKUP($A23,Questions!$A$2:$X$333,2,0) -> Does the system have password complexity or length limitations and/or restrictions?* | C23: Yes | D23: Coursedog recommends you use single sign on (SSO) for all admin access to Coursedog. That said, Coursedog has password aging on our near term roadmap. | E23: =IF($C$18="No",'Auto Responses'!$A$3,IF($C23="Yes",VLOOKUP($A23,Questions!$A$2:$X$333,17,0)&"",IF($C23="No",VLOOKUP($A23,Questions!$A$2:$X$333,16,0)&"",VLOOKUP($A23,Questions!$A$2:$X$333,15,0)&""))) -> Describe these limitations and/or restrictions and state what lengths and complexities are supported. | F23: =VLOOKUP($A23,'Institution Evaluation'!$A$56:$F$346,6,0)&""
A24: AAAI-05 | B24: =VLOOKUP($A24,Questions!$A$2:$X$333,2,0) -> Do you have documented password/passphrase reset procedures that are currently implemented in the system and/or customer support?* | C24: Yes | D24: Coursedog reccomends using Single Sign On (SSO) for authentication. However, users can reset their passwords by following the steps on the sign-in page or through "Account Settings" if they know their current password. Read More about Resetting Passwords | E24: =IF($C$18="No",'Auto Responses'!$A$3,IF($C24="Yes",VLOOKUP($A24,Questions!$A$2:$X$333,17,0)&"",IF($C24="No",VLOOKUP($A24,Questions!$A$2:$X$333,16,0)&"",VLOOKUP($A24,Questions!$A$2:$X$333,15,0)&""))) -> Describe your documented password/passphrase reset procedures that are currently implemented in the system and/or customer support. | F24: =VLOOKUP($A24,'Institution Evaluation'!$A$56:$F$346,6,0)&""
A25: AAAI-06 | B25: =VLOOKUP($A25,Questions!$A$2:$X$333,2,0) -> Does your organization participate in InCommon or another eduGAIN-affiliated trust federation?* | C25: Yes | D25: Coursedog supports SAML and CAS for single sign on (SSO) | E25: =IF($C$18="No",'Auto Responses'!$A$3,IF($C25="Yes",VLOOKUP($A25,Questions!$A$2:$X$333,17,0)&"",IF($C25="No",VLOOKUP($A25,Questions!$A$2:$X$333,16,0)&"",VLOOKUP($A25,Questions!$A$2:$X$333,15,0)&""))) -> List the entity IDs registered in the Additional Information column. | F25: =VLOOKUP($A25,'Institution Evaluation'!$A$56:$F$346,6,0)&""
A26: AAAI-07 | B26: =VLOOKUP($A26,Questions!$A$2:$X$333,2,0) -> Are there any passwords/passphrases hard-coded into your systems or solutions?* | C26: No | E26: =IF($C$18="No",'Auto Responses'!$A$3,IF($C26="Yes",VLOOKUP($A26,Questions!$A$2:$X$333,17,0)&"",IF($C26="No",VLOOKUP($A26,Questions!$A$2:$X$333,16,0)&"",VLOOKUP($A26,Questions!$A$2:$X$333,15,0)&""))) | F26: =VLOOKUP($A26,'Institution Evaluation'!$A$56:$F$346,6,0)&""
A27: AAAI-08 | B27: =VLOOKUP($A27,Questions!$A$2:$X$333,2,0) -> Are you storing any passwords in plaintext?* | C27: No | E27: =IF($C$18="No",'Auto Responses'!$A$3,IF($C27="Yes",VLOOKUP($A27,Questions!$A$2:$X$333,17,0)&"",IF($C27="No",VLOOKUP($A27,Questions!$A$2:$X$333,16,0)&"",VLOOKUP($A27,Questions!$A$2:$X$333,15,0)&""))) | F27: =VLOOKUP($A27,'Institution Evaluation'!$A$56:$F$346,6,0)&""
A28: AAAI-09 | B28: =VLOOKUP($A28,Questions!$A$2:$X$333,2,0) -> Are audit logs available that include AT LEAST all of the following: login, logout, actions performed, and source IP address?* | C28: Yes | D28: All user activity is logged. Most of the activity accessible in our admin panel by select administrators (see RBAC answer). | E28: =IF($C$18="No",'Auto Responses'!$A$3,IF($C28="Yes",VLOOKUP($A28,Questions!$A$2:$X$333,17,0)&"",IF($C28="No",VLOOKUP($A28,Questions!$A$2:$X$333,16,0)&"",VLOOKUP($A28,Questions!$A$2:$X$333,15,0)&""))) | F28: =VLOOKUP($A28,'Institution Evaluation'!$A$56:$F$346,6,0)&""
A29: AAAI-10 | B29: =VLOOKUP($A29,Questions!$A$2:$X$333,2,0) -> Describe or provide a reference to the (a) system capability to log security/authorization changes, as well as user and administrator security events (i.e., physical or electronic), such as login failures, access denied, changes accepted; and (b) all requirements necessary to implement logging and monitoring on the system. Include (c) information about SIEM/log collector usage.* | C29: All logs for security changes and user security are implemented and stored via AWS: https://docs.aws.amazon.com/elasticloadbalancing/latest/classic/access-log-collection.html https://docs.aws.amazon.com/organizations/latest/userguide/orgs_monitoring.html#orgs_cloudtrail-integration | E29: =IF($C$18="No",'Auto Responses'!$A$3,IF($C29="Yes",VLOOKUP($A29,Questions!$A$2:$X$333,17,0)&"",IF($C29="No",VLOOKUP($A29,Questions!$A$2:$X$333,16,0)&"",VLOOKUP($A29,Questions!$A$2:$X$333,15,0)&""))) -> Ensure that all elements of AAAI-10 are clearly stated in your response. | F29: =VLOOKUP($A29,'Institution Evaluation'!$A$56:$F$346,6,0)&""
A30: AAAI-11 | B30: =VLOOKUP($A30,Questions!$A$2:$X$333,2,0) -> Can you provide the institution documentation regarding the retention period for those logs, how logs are protected, and whether they are accessible to the customer (and if so, how)?* | C30: Yes | D30: Coursedog maintains Activity Logs indefinitely. | E30: =IF($C$18="No",'Auto Responses'!$A$3,IF($C30="Yes",VLOOKUP($A30,Questions!$A$2:$X$333,17,0)&"",IF($C30="No",VLOOKUP($A30,Questions!$A$2:$X$333,16,0)&"",VLOOKUP($A30,Questions!$A$2:$X$333,15,0)&""))) | F30: =VLOOKUP($A30,'Institution Evaluation'!$A$56:$F$346,6,0)&""
A31: AAAI-12 | B31: =VLOOKUP($A31,Questions!$A$2:$X$333,2,0) -> Does your application support integration with other authentication and authorization systems? | C31: Yes | D31: Coursedog supports Active Directory though single sign on (SSO) | E31: =IF($C$18="No",'Auto Responses'!$A$3,IF($C31="Yes",VLOOKUP($A31,Questions!$A$2:$X$333,17,0)&"",IF($C31="No",VLOOKUP($A31,Questions!$A$2:$X$333,16,0)&"",VLOOKUP($A31,Questions!$A$2:$X$333,15,0)&""))) -> List which systems and versions supported (such as Active Directory, Kerberos, or other LDAP compatible directory) in Additional Info. | F31: =VLOOKUP($A31,'Institution Evaluation'!$A$56:$F$346,6,0)&""
A32: AAAI-13 | B32: =VLOOKUP($A32,Questions!$A$2:$X$333,2,0) -> Do you allow the customer to specify attribute mappings for any needed information beyond a user identifier? (e.g., Reference eduPerson, ePPA/ePPN/ePE) | C32: Yes | E32: =IF($C$18="No",'Auto Responses'!$A$3,IF($C32="Yes",VLOOKUP($A32,Questions!$A$2:$X$333,17,0)&"",IF($C32="No",VLOOKUP($A32,Questions!$A$2:$X$333,16,0)&"",VLOOKUP($A32,Questions!$A$2:$X$333,15,0)&""))) | F32: =VLOOKUP($A32,'Institution Evaluation'!$A$56:$F$346,6,0)&""
A33: AAAI-14 | B33: =VLOOKUP($A33,Questions!$A$2:$X$333,2,0) -> Does your application support directory integration for user accounts? | C33: Yes | D33: Coursedog supports user creation and role assignments via SSO, which can be integrated with directory services. Learn More about SSO Integration | E33: =IF($C$18="No",'Auto Responses'!$A$3,IF($C33="Yes",VLOOKUP($A33,Questions!$A$2:$X$333,17,0)&"",IF($C33="No",VLOOKUP($A33,Questions!$A$2:$X$333,16,0)&"",VLOOKUP($A33,Questions!$A$2:$X$333,15,0)&""))) -> Describe all authentication services supported by the system. | F33: =VLOOKUP($A33,'Institution Evaluation'!$A$56:$F$346,6,0)&""
A34: AAAI-15 | B34: =VLOOKUP($A34,Questions!$A$2:$X$333,2,0) -> Does your solution support any of the following web SSO standards: SAML2 (with redirect flow), OIDC, CAS, or other? | C34: Yes | D34: Coursedog supports SAML and CAS for single sign on (SSO) | E34: =IF($C$18="No",'Auto Responses'!$A$3,IF($C34="Yes",VLOOKUP($A34,Questions!$A$2:$X$333,17,0)&"",IF($C34="No",VLOOKUP($A34,Questions!$A$2:$X$333,16,0)&"",VLOOKUP($A34,Questions!$A$2:$X$333,15,0)&""))) -> State the web SSO standards supported by your solution and provide additional details about your support, including framework(s) in use, how information is exchanged securely, etc. | F34: =VLOOKUP($A34,'Institution Evaluation'!$A$56:$F$346,6,0)&""
A35: AAAI-16 | B35: =VLOOKUP($A35,Questions!$A$2:$X$333,2,0) -> Do you support differentiation between email address and user identifier? | C35: Yes | E35: =IF($C$18="No",'Auto Responses'!$A$3,IF($C35="Yes",VLOOKUP($A35,Questions!$A$2:$X$333,17,0)&"",IF($C35="No",VLOOKUP($A35,Questions!$A$2:$X$333,16,0)&"",VLOOKUP($A35,Questions!$A$2:$X$333,15,0)&""))) | F35: =VLOOKUP($A35,'Institution Evaluation'!$A$56:$F$346,6,0)&""
A36: AAAI-17 | B36: =VLOOKUP($A36,Questions!$A$2:$X$333,2,0) -> If the institution does not use SSO, does your application and/or user frontend/portal support multifactor authentication (e.g., Duo, Google Authenticator, OTP, etc.)? | C36: No | D36: Coursedog recommends you use single sign on (SSO) to leverage any 2FA at your institution for all admin access to Coursedog. | E36: =IF($C$18="No",'Auto Responses'!$A$3,IF($C$20="No",'Auto Responses'!$A$28,IF($C36="Yes",VLOOKUP($A36,Questions!$A$2:$X$333,17,0)&"",IF($C36="No",VLOOKUP($A36,Questions!$A$2:$X$333,16,0)&"",VLOOKUP($A36,Questions!$A$2:$X$333,15,0)&"")))) -> Describe any plans to support multifactor authentication in your application. | F36: =VLOOKUP($A36,'Institution Evaluation'!$A$56:$F$346,6,0)&""
A37: AAAI-18 | B37: =VLOOKUP($A37,Questions!$A$2:$X$333,2,0) -> Does your application automatically lock the session or log out an account after a period of inactivity? | C37: Yes | D37: If you are inactive for more than 24 hours, you will automatically be logged out of Coursedog. Read More about Logging Out | E37: =IF($C$18="No",'Auto Responses'!$A$3,IF($C37="Yes",VLOOKUP($A37,Questions!$A$2:$X$333,17,0)&"",IF($C37="No",VLOOKUP($A37,Questions!$A$2:$X$333,16,0)&"",VLOOKUP($A37,Questions!$A$2:$X$333,15,0)&""))) -> Describe the default behavior of this capability. | F37: =VLOOKUP($A37,'Institution Evaluation'!$A$56:$F$346,6,0)&"" | G37: End Table Data
A38: =VLOOKUP(LEFT($A39,4),'Auto Responses'!$N$4:$O$38,2,0)&"" -> Data | C38: Answer | D38: Additional Information | E38: Guidance | F38: Analyst Notes
A39: DATA-01 | B39: =VLOOKUP($A39,Questions!$A$2:$X$333,2,0) -> Will the institution's data be stored on any devices (database servers, file servers, SAN, NAS, etc.) configured with non-RFC 1918/4193 (i.e., publicly routable) IP addresses?* | C39: No | E39: =IF($C$18="No",'Auto Responses'!$A$3,IF($C39="Yes",VLOOKUP($A39,Questions!$A$2:$X$333,17,0)&"",IF($C39="No",VLOOKUP($A39,Questions!$A$2:$X$333,16,0)&"",VLOOKUP($A39,Questions!$A$2:$X$333,15,0)&""))) | F39: =VLOOKUP($A39,'Institution Evaluation'!$A$56:$F$346,6,0)&""
A40: DATA-02 | B40: =VLOOKUP($A40,Questions!$A$2:$X$333,2,0) -> Is the transport of sensitive data encrypted using security protocols/algorithms (e.g., system-to-client)?* | C40: Yes | D40: See our security overview for more information. | E40: =IF($C$18="No",'Auto Responses'!$A$3,IF($C40="Yes",VLOOKUP($A40,Questions!$A$2:$X$333,17,0)&"",IF($C40="No",VLOOKUP($A40,Questions!$A$2:$X$333,16,0)&"",VLOOKUP($A40,Questions!$A$2:$X$333,15,0)&""))) -> Summarize your transport encryption strategy. | F40: =VLOOKUP($A40,'Institution Evaluation'!$A$56:$F$346,6,0)&""
A41: DATA-03 | B41: =VLOOKUP($A41,Questions!$A$2:$X$333,2,0) -> Is the storage of sensitive data encrypted using security protocols/algorithms (e.g., disk encryption, at-rest, files, and within a running database)?* | C41: Yes | D41: See our security overview for more information. | E41: =IF($C$18="No",'Auto Responses'!$A$3,IF($C41="Yes",VLOOKUP($A41,Questions!$A$2:$X$333,17,0)&"",IF($C41="No",VLOOKUP($A41,Questions!$A$2:$X$333,16,0)&"",VLOOKUP($A41,Questions!$A$2:$X$333,15,0)&""))) -> Summarize your data encryption strategy and state what encryption options are available. | F41: =VLOOKUP($A41,'Institution Evaluation'!$A$56:$F$346,6,0)&""
A42: DATA-04 | B42: =VLOOKUP($A42,Questions!$A$2:$X$333,2,0) -> Do all cryptographic modules in use in your solution conform to the Federal Information Processing Standards (FIPS PUB 140-2 or 140-3)?* | C42: Yes | D42: Coursedog is a schedule and curriculum planning tool and therefore does not store any sensitive data (e.g. FERPA, PII, credit cards, etc.). That said, Coursedog follows best practices such as FIPS PUB 140-3. See our security overview for more information. | E42: =IF($C$18="No",'Auto Responses'!$A$3,IF($C42="Yes",VLOOKUP($A42,Questions!$A$2:$X$333,17,0)&"",IF($C42="No",VLOOKUP($A42,Questions!$A$2:$X$333,16,0)&"",VLOOKUP($A42,Questions!$A$2:$X$333,15,0)&""))) -> Provide reference to FIPS 140-3 validation certificates. | F42: =VLOOKUP($A42,'Institution Evaluation'!$A$56:$F$346,6,0)&""
A43: DATA-05 | B43: =VLOOKUP($A43,Questions!$A$2:$X$333,2,0) -> Will the institution's data be available within the system for a period of time at the completion of this contract?* | C43: Yes | D43: All relevant data structures can be returned upon request for an agreed upon time period upon contract completion | E43: =IF($C$18="No",'Auto Responses'!$A$3,IF($C43="Yes",VLOOKUP($A43,Questions!$A$2:$X$333,17,0)&"",IF($C43="No",VLOOKUP($A43,Questions!$A$2:$X$333,16,0)&"",VLOOKUP($A43,Questions!$A$2:$X$333,15,0)&""))) -> State the length of time that the institution's data will be available in the system at the completion of the contract. | F43: =VLOOKUP($A43,'Institution Evaluation'!$A$56:$F$346,6,0)&""
A44: DATA-06 | B44: =VLOOKUP($A44,Questions!$A$2:$X$333,2,0) -> Are these rights retained even through a provider acquisition or bankruptcy event?* | C44: Yes | D44: It is Coursedog's intention, although there is no contract behind this. | E44: =IF($C$18="No",'Auto Responses'!$A$3,IF($C44="Yes",VLOOKUP($A44,Questions!$A$2:$X$333,17,0)&"",IF($C44="No",VLOOKUP($A44,Questions!$A$2:$X$333,16,0)&"",VLOOKUP($A44,Questions!$A$2:$X$333,15,0)&""))) -> Provide references, as needed. | F44: =VLOOKUP($A44,'Institution Evaluation'!$A$56:$F$346,6,0)&""
A45: DATA-07 | B45: =VLOOKUP($A45,Questions!$A$2:$X$333,2,0) -> Do backups containing the institution's data ever leave the institution's data zone either physically or via network routing?* | C45: Yes | D45: See AWS backup documentation | E45: =IF($C$18="No",'Auto Responses'!$A$3,IF($C45="Yes",VLOOKUP($A45,Questions!$A$2:$X$333,17,0)&"",IF($C45="No",VLOOKUP($A45,Questions!$A$2:$X$333,16,0)&"",VLOOKUP($A45,Questions!$A$2:$X$333,15,0)&""))) -> Summarize why backups containing the institution's data leave the institution's data zone. | F45: =VLOOKUP($A45,'Institution Evaluation'!$A$56:$F$346,6,0)&""
A46: DATA-08 | B46: =VLOOKUP($A46,Questions!$A$2:$X$333,2,0) -> Is media used for long-term retention of business data and archival purposes stored in a secure, environmentally protected area?* | C46: Yes | D46: Included in our SLA | E46: =IF($C$18="No",'Auto Responses'!$A$3,IF($C46="Yes",VLOOKUP($A46,Questions!$A$2:$X$333,17,0)&"",IF($C46="No",VLOOKUP($A46,Questions!$A$2:$X$333,16,0)&"",VLOOKUP($A46,Questions!$A$2:$X$333,15,0)&""))) -> Provide a general summary of your archival environment. | F46: =VLOOKUP($A46,'Institution Evaluation'!$A$56:$F$346,6,0)&""
A47: DATA-09 | B47: =VLOOKUP($A47,Questions!$A$2:$X$333,2,0) -> At the completion of this contract, will data be returned to the institution and/or deleted from all your systems and archives? | C47: Yes | D47: All relevant data structures can be returned upon request and removed from the DB | E47: =IF($C$18="No",'Auto Responses'!$A$3,IF($C47="Yes",VLOOKUP($A47,Questions!$A$2:$X$333,17,0)&"",IF($C47="No",VLOOKUP($A47,Questions!$A$2:$X$333,16,0)&"",VLOOKUP($A47,Questions!$A$2:$X$333,15,0)&""))) -> State the length of time that the institution's data will be available in the system at the completion of the contract. | F47: =VLOOKUP($A47,'Institution Evaluation'!$A$56:$F$346,6,0)&""
A48: DATA-10 | B48: =VLOOKUP($A48,Questions!$A$2:$X$333,2,0) -> Can the institution extract a full or partial backup of data? | C48: Yes | D48: See data backup policy | E48: =IF($C$18="No",'Auto Responses'!$A$3,IF($C48="Yes",VLOOKUP($A48,Questions!$A$2:$X$333,17,0)&"",IF($C48="No",VLOOKUP($A48,Questions!$A$2:$X$333,16,0)&"",VLOOKUP($A48,Questions!$A$2:$X$333,15,0)&""))) -> Provide a general summary of how full and partial backups of data can be extracted. | F48: =VLOOKUP($A48,'Institution Evaluation'!$A$56:$F$346,6,0)&""
A49: DATA-11 | B49: =VLOOKUP($A49,Questions!$A$2:$X$333,2,0) -> Do current backups include all operating system software, utilities, security software, application software, and data files necessary for recovery? | C49: Yes | D49: See AWS backup documentation | E49: =IF($C$18="No",'Auto Responses'!$A$3,IF($C49="Yes",VLOOKUP($A49,Questions!$A$2:$X$333,17,0)&"",IF($C49="No",VLOOKUP($A49,Questions!$A$2:$X$333,16,0)&"",VLOOKUP($A49,Questions!$A$2:$X$333,15,0)&""))) -> Decribe your overall strategy to accomplish these elements. | F49: =VLOOKUP($A49,'Institution Evaluation'!$A$56:$F$346,6,0)&""
A50: DATA-12 | B50: =VLOOKUP($A50,Questions!$A$2:$X$333,2,0) -> Are you performing off-site backups (i.e., digitally moved off site)? | C50: Yes | D50: See AWS backup documentation | E50: =IF($C$18="No",'Auto Responses'!$A$3,IF($C50="Yes",VLOOKUP($A50,Questions!$A$2:$X$333,17,0)&"",IF($C50="No",VLOOKUP($A50,Questions!$A$2:$X$333,16,0)&"",VLOOKUP($A50,Questions!$A$2:$X$333,15,0)&""))) -> Summarize your off-site backup strategy. | F50: =VLOOKUP($A50,'Institution Evaluation'!$A$56:$F$346,6,0)&""
A51: DATA-13 | B51: =VLOOKUP($A51,Questions!$A$2:$X$333,2,0) -> Are physical backups taken off-site (i.e., physically moved off site)? | C51: Yes | D51: See AWS backup documentation | E51: =IF($C$18="No",'Auto Responses'!$A$3,IF($C51="Yes",VLOOKUP($A51,Questions!$A$2:$X$333,17,0)&"",IF($C51="No",VLOOKUP($A51,Questions!$A$2:$X$333,16,0)&"",VLOOKUP($A51,Questions!$A$2:$X$333,15,0)&""))) -> Provide the distance (in miles) between the primary and off-site locations. | F51: =VLOOKUP($A51,'Institution Evaluation'!$A$56:$F$346,6,0)&""
... A54: DATA-16 | B54: =VLOOKUP($A54,Questions!$A$2:$X$333,2,0) -> Does the process described in DATA-15 adhere to DoD 5220.22-M and/or NIST SP 800-88 standards? | C54: Yes | D54: See AWS backup documentation | E54: =IF($C$18="No",'Auto Responses'!$A$3,IF($C54="Yes",VLOOKUP($A54,Questions!$A$2:$X$333,17,0)&"",IF($C54="No",VLOOKUP($A54,Questions!$A$2:$X$333,16,0)&"",VLOOKUP($A54,Questions!$A$2:$X$333,15,0)&""))) | F54: =VLOOKUP($A54,'Institution Evaluation'!$A$56:$F$346,6,0)&""
A55: DATA-17 | B55: =VLOOKUP($A55,Questions!$A$2:$X$333,2,0) -> Does your staff (or third party) have access to institutional data (e.g., financial, PHI, or other sensitive information) through any means? | C55: No | E55: =IF($C$18="No",'Auto Responses'!$A$3,IF($C55="Yes",VLOOKUP($A55,Questions!$A$2:$X$333,17,0)&"",IF($C55="No",VLOOKUP($A55,Questions!$A$2:$X$333,16,0)&"",VLOOKUP($A55,Questions!$A$2:$X$333,15,0)&""))) | F55: =VLOOKUP($A55,'Institution Evaluation'!$A$56:$F$346,6,0)&""
A56: DATA-18 | B56: =VLOOKUP($A56,Questions!$A$2:$X$333,2,0) -> Do you have a documented and currently implemented strategy for securing employee workstations when they work remotely (i.e., not in a trusted computing environment)? | C56: Yes | D56: See our security overview and privacy policy for more information. | E56: =IF($C$18="No",'Auto Responses'!$A$3,IF($C56="Yes",VLOOKUP($A56,Questions!$A$2:$X$333,17,0)&"",IF($C56="No",VLOOKUP($A56,Questions!$A$2:$X$333,16,0)&"",VLOOKUP($A56,Questions!$A$2:$X$333,15,0)&""))) -> Provide a detailed summary outlining the security controls implemented to protect the institution's data. | F56: =VLOOKUP($A56,'Institution Evaluation'!$A$56:$F$346,6,0)&""
A57: DATA-19 | B57: =VLOOKUP($A57,Questions!$A$2:$X$333,2,0) -> Does the environment provide for dedicated single-tenant capabilities? If not, describe how your solution or environment separates data from different customers (e.g., logically, physically, single tenancy, multi-tenancy). | C57: Yes | D57: Coursedog is fully hosted and each client has their own dedicated instance. Databases are hosted separately via MongoDb Atlas - which itself is in an AWS VPC. We also utilize a multi-tenant database architecture, so each client is on their own database. The application and databases are hosted by AWS VPC in the US. See AWS security details. | E57: =IF($C$18="No",'Auto Responses'!$A$3,IF($C57="Yes",VLOOKUP($A57,Questions!$A$2:$X$333,17,0)&"",IF($C57="No",VLOOKUP($A57,Questions!$A$2:$X$333,16,0)&"",VLOOKUP($A57,Questions!$A$2:$X$333,15,0)&""))) -> Describe or provide a reference to how institution data is separated from that of other customers. | F57: =VLOOKUP($A57,'Institution Evaluation'!$A$56:$F$346,6,0)&""
A58: DATA-20 | B58: =VLOOKUP($A58,Questions!$A$2:$X$333,2,0) -> Are ownership rights to all data, inputs, outputs, and metadata retained by the institution? | C58: Yes | D58: See SLA | E58: =IF($C$18="No",'Auto Responses'!$A$3,IF($C58="Yes",VLOOKUP($A58,Questions!$A$2:$X$333,17,0)&"",IF($C58="No",VLOOKUP($A58,Questions!$A$2:$X$333,16,0)&"",VLOOKUP($A58,Questions!$A$2:$X$333,15,0)&""))) -> Provide reference to your data ownership documention. | F58: =VLOOKUP($A58,'Institution Evaluation'!$A$56:$F$346,6,0)&""
A59: DATA-21 | B59: =VLOOKUP($A59,Questions!$A$2:$X$333,2,0) -> In the event of imminent bankruptcy, closing of business, or retirement of service, will you provide 90 days for customers to get their data out of the system and migrate applications? | C59: Yes | D59: Coursedog will strive to provide a clean handoff in the event of a closure | E59: =IF($C$18="No",'Auto Responses'!$A$3,IF($C59="Yes",VLOOKUP($A59,Questions!$A$2:$X$333,17,0)&"",IF($C59="No",VLOOKUP($A59,Questions!$A$2:$X$333,16,0)&"",VLOOKUP($A59,Questions!$A$2:$X$333,15,0)&""))) -> State how the institution will be notified of imminent termination. | F59: =VLOOKUP($A59,'Institution Evaluation'!$A$56:$F$346,6,0)&""
A60: DATA-22 | B60: =VLOOKUP($A60,Questions!$A$2:$X$333,2,0) -> Are involatile backup copies made according to predefined schedules and securely stored and protected? | C60: Yes | D60: Nightly backups are made and securely stored in AWS S3. See the backup policy | E60: =IF($C$18="No",'Auto Responses'!$A$3,IF($C60="Yes",VLOOKUP($A60,Questions!$A$2:$X$333,17,0)&"",IF($C60="No",VLOOKUP($A60,Questions!$A$2:$X$333,16,0)&"",VLOOKUP($A60,Questions!$A$2:$X$333,15,0)&""))) -> If your strategy uses different processes for services and data, ensure that all strategies are clearly stated and supported. | F60: =VLOOKUP($A60,'Institution Evaluation'!$A$56:$F$346,6,0)&""
A61: DATA-23 | B61: =VLOOKUP($A61,Questions!$A$2:$X$333,2,0) -> Do you have a cryptographic key management process (generation, exchange, storage, safeguards, use, vetting, and replacement) that is documented and currently implemented, for all system components (e.g., database, system, web, etc.)? | C61: Yes | D61: See AWS backup documentation | E61: =IF($C$18="No",'Auto Responses'!$A$3,IF($C61="Yes",VLOOKUP($A61,Questions!$A$2:$X$333,17,0)&"",IF($C61="No",VLOOKUP($A61,Questions!$A$2:$X$333,16,0)&"",VLOOKUP($A61,Questions!$A$2:$X$333,15,0)&""))) | F61: =VLOOKUP($A61,'Institution Evaluation'!$A$56:$F$346,6,0)&"" | G61: End Table Data
A62: Copyright © 2025 EDUCAUSE
A66: =#REF! -> #REF!
A67: =#REF! -> #REF!
A68: =#REF! -> #REF!
A69: =#REF! -> #REF!
A70: =#REF! -> #REF!
A71: =#REF! -> #REF!
A72: =#REF! -> #REF!

Sheet Infrastructure
A1: Cells contained in this worksheet may contain cells with dropdown lists as well as autopopulated formulas.
A2: HECVAT Solution Provider Response - Infrastructure | F2: ='Auto Responses'!$A$36 -> Version 4.04
A3: Date Completed | C3: ='START HERE'!$C$3 -> 45933
A4: Instructions for Solution Providers
A5: =HLOOKUP($A$4,'Auto Responses'!$D$2:$D$8,2,0)&"" -> 1. Complete the "Start Here" tab and review the "Required Questions" guidance to find the other sections are required for your product or service.
A6: =HLOOKUP($A$4,'Auto Responses'!$D$2:$D$8,3,0)&"" -> 2. Complete the "Organization" tab and the applicable questions in each of the next 5 tabs (Product through Privacy) that apply, based on your answers to the "Required Questions."
A7: =HLOOKUP($A$4,'Auto Responses'!$D$2:$D$8,4,0)&"" -> 3. Guidance in column E may change based on your answers to prompt details in "Additional Information." If leaving an answer blank, you must also state why in "Additional Information".
A8: =HLOOKUP($A$4,'Auto Responses'!$D$2:$D$8,5,0)&"" -> 4. DO NOT complete any fields in the "Evaluation" sheets or the "Analyst Notes" column.
A9: =HLOOKUP($A$4,'Auto Responses'!$D$2:$D$8,6,0)&"" -> 5. Return the completed file to institutions.
A10: =HLOOKUP($A$4,'Auto Responses'!$D$2:$D$8,7,0)&"" -> * Denotes critical questions. Critical questions are those deemed most important to institutions by higher education volunteers.
A11: =HLOOKUP($A$4,'Auto Responses'!$D$2:$D$9,8,0)&"" -> For full instructions, please visit educause.edu/HECVAT
A12: =VLOOKUP(LEFT($A13,4),'Auto Responses'!$N$4:$O$38,2,0)&"" -> General Information | C12: Answer
A13: GNRL-01 | B13: =VLOOKUP($A13,Questions!$A$2:$X$333,2,0)&"" -> Solution Provider Name | C13: =VLOOKUP($A13,'START HERE'!$A$13:$C$21,3,0)&"" -> Coursedog
A14: GNRL-02 | B14: =VLOOKUP($A14,Questions!$A$2:$X$333,2,0)&"" -> Solution Name | C14: =VLOOKUP($A14,'START HERE'!$A$13:$C$21,3,0)&"" -> Coursedog
A15: GNRL-03 | B15: =VLOOKUP($A15,Questions!$A$2:$X$333,2,0)&"" -> Solution Description | C15: =VLOOKUP($A15,'START HERE'!$A$13:$C$21,3,0)&"" -> Coursedog is a SaaS platform designed to streamline curriculum, catalog, and scheduling management for higher education institutions, offering intuitive tools, insightful analytics, and seamless integration without requiring IT involvement.
A16: GNRL-08 | B16: =VLOOKUP($A16,Questions!$A$2:$X$333,2,0)&"" -> Country of Company Headquarters | C16: =VLOOKUP($A16,'START HERE'!$A$13:$C$21,3,0)&"" -> United States
A17: =VLOOKUP(LEFT($A18,4),'Auto Responses'!$N$4:$O$38,2,0)&"" -> Required Questions | C17: Answer | E17: Guidance | F17: Analyst Notes
A18: REQU-01 | B18: =VLOOKUP($A18,Questions!$A$2:$X$333,2,0) -> Are you offering either a product or platform, as opposed to only offering a service | C18: =VLOOKUP($A18,'START HERE'!$A$23:$F$36,3,0)&"" -> Yes | D18: =VLOOKUP($A18,'START HERE'!$A$23:$F$36,4,0)&"" -> Coursedog is a SaaS platform designed to streamline curriculum, catalog, and scheduling management for higher education institutions, offering intuitive tools, insightful analytics, and seamless integration without requiring IT involvement. | E18: =IF($C18="Yes",VLOOKUP($A18,Questions!$A$2:$X$333,17,0)&"",IF($C18="No",VLOOKUP($A18,Questions!$A$2:$X$333,16,0)&"",VLOOKUP($A18,Questions!$A$2:$X$333,15,0)&"")) -> DO complete the Product and Infrastructure worksheets | F18: =VLOOKUP($A18,'Institution Evaluation'!$A$56:$F$346,6,0)&"" | G18: End Table Data
A19: =VLOOKUP(LEFT($A20,4),'Auto Responses'!$N$4:$O$38,2,0)&"" -> Application/Service Security | C19: Answer | D19: Additional Information | E19: Guidance | F19: Analyst Notes
A20: APPL-01 | B20: =VLOOKUP($A20,Questions!$A$2:$X$333,2,0) -> Are access controls for institutional accounts based on structured rules, such as role-based access control (RBAC), attribute-based access control (ABAC), or policy-based access control (PBAC)?* | C20: Yes | D20: Coursedog supports role-based access control (RBAC). You can create, manage, and remove permissions for various roles. Products come pre-loaded with a set of roles, but you can also create custom roles and set different permissions for each role. Permissions can be set on a product-wide level, with additional role-based permissions available on the field-level. | E20: =IF($C$18="No",'Auto Responses'!$A$3,IF($C20="Yes",VLOOKUP($A20,Questions!$A$2:$X$333,17,0)&"",IF($C20="No",VLOOKUP($A20,Questions!$A$2:$X$333,16,0)&"",VLOOKUP($A20,Questions!$A$2:$X$333,15,0)&""))) -> Describe available roles. | F20: =VLOOKUP($A20,'Institution Evaluation'!$A$56:$F$346,6,0)&""
A21: APPL-02 | B21: =VLOOKUP($A21,Questions!$A$2:$X$333,2,0) -> Are you using a web application firewall (WAF)?* | C21: Yes | D21: See AWS firewall documentation | E21: =IF($C$18="No",'Auto Responses'!$A$3,IF($C21="Yes",VLOOKUP($A21,Questions!$A$2:$X$333,17,0)&"",IF($C21="No",VLOOKUP($A21,Questions!$A$2:$X$333,16,0)&"",VLOOKUP($A21,Questions!$A$2:$X$333,15,0)&""))) -> Describe the currently implemented WAF. | F21: =VLOOKUP($A21,'Institution Evaluation'!$A$56:$F$346,6,0)&""
A22: APPL-03 | B22: =VLOOKUP($A22,Questions!$A$2:$X$333,2,0) -> Are only currently supported operating system(s), software, and libraries leveraged by the system(s)/application(s) that will have access to institution's data?* | C22: Yes | D22: See Coursedog application and infastructure archutecture documents | F22: =VLOOKUP($A22,'Institution Evaluation'!$A$56:$F$346,6,0)&""
A23: APPL-04 | B23: =VLOOKUP($A23,Questions!$A$2:$X$333,2,0) -> Does your application require access to location or GPS data? | C23: No | D23: Can be leveraged but not required. See our support article for more information | E23: =IF($C$18="No",'Auto Responses'!$A$3,IF($C23="Yes",VLOOKUP($A23,Questions!$A$2:$X$333,17,0)&"",IF($C23="No",VLOOKUP($A23,Questions!$A$2:$X$333,16,0)&"",VLOOKUP($A23,Questions!$A$2:$X$333,15,0)&""))) -> Please indicate any future plans that would require access to this data | F23: =VLOOKUP($A23,'Institution Evaluation'!$A$56:$F$346,6,0)&""
A24: APPL-05 | B24: =VLOOKUP($A24,Questions!$A$2:$X$333,2,0) -> Does your application provide separation of duties between security administration, system administration, and standard user functions?* | C24: Yes | D24: https://aws.amazon.com/security/ | F24: =VLOOKUP($A24,'Institution Evaluation'!$A$56:$F$346,6,0)&""
A25: APPL-06 | B25: =VLOOKUP($A25,Questions!$A$2:$X$333,2,0) -> Do you subject your code to static code analysis and/or static application security testing prior to release?* | C25: Yes | D25: Eslint | E25: =IF($C$18="No",'Auto Responses'!$A$3,IF($C25="Yes",VLOOKUP($A25,Questions!$A$2:$X$333,17,0)&"",IF($C25="No",VLOOKUP($A25,Questions!$A$2:$X$333,16,0)&"",VLOOKUP($A25,Questions!$A$2:$X$333,15,0)&""))) -> Provide a list of all tools utilized during static code analysis or static application security testing. | F25: =VLOOKUP($A25,'Institution Evaluation'!$A$56:$F$346,6,0)&""
A26: APPL-07 | B26: =VLOOKUP($A26,Questions!$A$2:$X$333,2,0) -> Do you have software testing processes (dynamic or static) that are established and followed?* | C26: Yes | D26: Coursedog practices a two week agile development process with test driven deployment (TDD). Developers build the specification to the test and push changes to a QA system where it is thoroughly tested. Updates are then moved to a staging environment where they can be tested by active implementations before they are pushed to production, where they are gated behind role based access control and admins can opt into using the functionality. We provide change logs to end users and admins when new functionality is deployed. Any end user is able to provide feedback through our public bug tracking tool if a bug is found in the production. | E26: =IF($C$18="No",'Auto Responses'!$A$3,IF($C26="Yes",VLOOKUP($A26,Questions!$A$2:$X$333,17,0)&"",IF($C26="No",VLOOKUP($A26,Questions!$A$2:$X$333,16,0)&"",VLOOKUP($A26,Questions!$A$2:$X$333,15,0)&""))) -> Describe testing processes, including but not limited to, development of test plans, personnel involved in the testing process, and authorized individual accountable for approval and certification of test results. | F26: =VLOOKUP($A26,'Institution Evaluation'!$A$56:$F$346,6,0)&""
A27: APPL-08 | B27: =VLOOKUP($A27,Questions!$A$2:$X$333,2,0) -> Are access controls for staff within your organization based on structured rules, such as RBAC, ABAC, or PBAC? | C27: Yes | D27: Coursedog supports role-based access control (RBAC) for staff within the organization. You can create, manage, and remove permissions for various roles, allowing for structured access control based on roles. | E27: =IF($C$18="No",'Auto Responses'!$A$3,IF($C27="Yes",VLOOKUP($A27,Questions!$A$2:$X$333,17,0)&"",IF($C27="No",VLOOKUP($A27,Questions!$A$2:$X$333,16,0)&"",VLOOKUP($A27,Questions!$A$2:$X$333,15,0)&""))) | F27: =VLOOKUP($A27,'Institution Evaluation'!$A$56:$F$346,6,0)&""
A28: APPL-09 | B28: =VLOOKUP($A28,Questions!$A$2:$X$333,2,0) -> Does the system provide data input validation and error messages? | C28: Yes | D28: See our support article explaining our error handling in more detail. | E28: =IF($C$18="No",'Auto Responses'!$A$3,IF($C28="Yes",VLOOKUP($A28,Questions!$A$2:$X$333,17,0)&"",IF($C28="No",VLOOKUP($A28,Questions!$A$2:$X$333,16,0)&"",VLOOKUP($A28,Questions!$A$2:$X$333,15,0)&""))) -> Describe how your system(s) provide data input validation and error messages. | F28: =VLOOKUP($A28,'Institution Evaluation'!$A$56:$F$346,6,0)&""
A29: APPL-10 | B29: =VLOOKUP($A29,Questions!$A$2:$X$333,2,0) -> Do you have a process and implemented procedures for managing your software supply chain (e.g., libraries, repositories, frameworks, etc.) | C29: Yes | D29: See Coursedog - Configuration Management Policy | E29: =IF($C$18="No",'Auto Responses'!$A$3,IF($C29="Yes",VLOOKUP($A29,Questions!$A$2:$X$333,17,0)&"",IF($C29="No",VLOOKUP($A29,Questions!$A$2:$X$333,16,0)&"",VLOOKUP($A29,Questions!$A$2:$X$333,15,0)&""))) -> Provide supporting documentation of your processes. | F29: =VLOOKUP($A29,'Institution Evaluation'!$A$56:$F$346,6,0)&""
A30: APPL-11 | B30: =VLOOKUP($A30,Questions!$A$2:$X$333,2,0) -> Have your developers been trained in secure coding techniques? | C30: Yes | D30: See OWASP | E30: =IF($C$18="No",'Auto Responses'!$A$3,IF($C30="Yes",VLOOKUP($A30,Questions!$A$2:$X$333,17,0)&"",IF($C30="No",VLOOKUP($A30,Questions!$A$2:$X$333,16,0)&"",VLOOKUP($A30,Questions!$A$2:$X$333,15,0)&""))) -> Summarize your secure coding training. | F30: =VLOOKUP($A30,'Institution Evaluation'!$A$56:$F$346,6,0)&""
A31: APPL-12 | B31: =VLOOKUP($A31,Questions!$A$2:$X$333,2,0) -> Was your application developed using secure coding techniques? | C31: Yes | D31: See OWASP | E31: =IF($C$18="No",'Auto Responses'!$A$3,IF($C31="Yes",VLOOKUP($A31,Questions!$A$2:$X$333,17,0)&"",IF($C31="No",VLOOKUP($A31,Questions!$A$2:$X$333,16,0)&"",VLOOKUP($A31,Questions!$A$2:$X$333,15,0)&""))) -> Summarize your secure coding practices. | F31: =VLOOKUP($A31,'Institution Evaluation'!$A$56:$F$346,6,0)&""
A32: APPL-13 | B32: =VLOOKUP($A32,Questions!$A$2:$X$333,2,0) -> If mobile, is the application available from a trusted source (e.g., App Store, Google Play Store)? | C32: N/A | E32: =IF($C$18="No",'Auto Responses'!$A$3,IF($C32="Yes",VLOOKUP($A32,Questions!$A$2:$X$333,17,0)&"",IF($C32="No",VLOOKUP($A32,Questions!$A$2:$X$333,16,0)&"",VLOOKUP($A32,Questions!$A$2:$X$333,15,0)&""))) -> Select N/A if there is no mobile version of your app. | F32: =VLOOKUP($A32,'Institution Evaluation'!$A$56:$F$346,6,0)&""
A33: APPL-14 | B33: =VLOOKUP($A33,Questions!$A$2:$X$333,2,0) -> Do you have a fully implemented policy or procedure that details how your employees obtain administrator access to institutional instance of the application? | C33: Yes | D33: Access to the Admin Dashboard is limited to Coursedog users with administrator permissions and the internal Coursedog team. This ensures that only authorized personnel can manage settings such as Single Sign On (SSO), integration settings, and user activity monitoring. Read More about the Admin Dashboard | E33: =IF($C$18="No",'Auto Responses'!$A$3,IF($C33="Yes",VLOOKUP($A33,Questions!$A$2:$X$333,17,0)&"",IF($C33="No",VLOOKUP($A33,Questions!$A$2:$X$333,16,0)&"",VLOOKUP($A33,Questions!$A$2:$X$333,15,0)&""))) -> Describe or provide a reference that details how administrator access is handled (e.g., provisioning, principle of least privilege, deprovisioning, etc.). | F33: =VLOOKUP($A33,'Institution Evaluation'!$A$56:$F$346,6,0)&"" | G33: End Table Data
A34: =VLOOKUP(LEFT($A35,4),'Auto Responses'!$N$4:$O$38,2,0)&"" -> Datacenter | C34: Answer | D34: Additional Information | E34: Guidance | F34: Analyst Notes
A35: DCTR-01 | B35: =VLOOKUP($A35,Questions!$A$2:$X$333,2,0) -> Select your hosting option. | C35: AWS | E35: =IF(OR($C35="",$C35="Other"),VLOOKUP($A35,Questions!$A$2:$X$333,15,0),"")&"" | F35: =VLOOKUP($A35,'Institution Evaluation'!$A$56:$F$346,6,0)&""
A36: DCTR-02 | B36: =VLOOKUP($A36,Questions!$A$2:$X$333,2,0) -> Is a SOC 2 Type 2 report available for the hosting environment? | C36: Yes | D36: See AWS SOC documentation | E36: =IF($C$35="","",IF(OR($C$35='Auto Responses'!$J$20,$C$35='Auto Responses'!$J$21,$C$35='Auto Responses'!$J$22),'Auto Responses'!$A$26,IF($C36="Yes",VLOOKUP($A36,Questions!$A$2:$X$333,17,0)&"",IF($C36="No",VLOOKUP($A36,Questions!$A$2:$X$333,16,0)&"",VLOOKUP($A36,Questions!$A$2:$X$333,15,0)&"")))) -> Based on the response to DCTR-01, this question does not apply to this product or service. | F36: =VLOOKUP($A36,'Institution Evaluation'!$A$56:$F$346,6,0)&""
A37: DCTR-03 | B37: =VLOOKUP($A37,Questions!$A$2:$X$333,2,0) -> Are you generally able to accommodate storing each institution's data within its geographic region? | C37: Yes | D37: See AWS overview | E37: =IF($C$35="","",IF($C37="Yes",VLOOKUP($A37,Questions!$A$2:$X$333,17,0)&"",IF($C37="No",VLOOKUP($A37,Questions!$A$2:$X$333,16,0)&"",VLOOKUP($A37,Questions!$A$2:$X$333,15,0)&""))) | F37: =VLOOKUP($A37,'Institution Evaluation'!$A$56:$F$346,6,0)&""
A38: DCTR-04 | B38: =VLOOKUP($A38,Questions!$A$2:$X$333,2,0) -> Are the data centers staffed 24 hours a day, seven days a week (i.e., 24 x 7 x 365)? | C38: Yes | D38: See AWS Controls | E38: =IF($C$35="","",IF(OR($C$35='Auto Responses'!$J$20,$C$35='Auto Responses'!$J$21,$C$35='Auto Responses'!$J$22),'Auto Responses'!$A$26,IF($C38="Yes",VLOOKUP($A38,Questions!$A$2:$X$333,17,0)&"",IF($C38="No",VLOOKUP($A38,Questions!$A$2:$X$333,16,0)&"",VLOOKUP($A38,Questions!$A$2:$X$333,15,0)&"")))) -> Based on the response to DCTR-01, this question does not apply to this product or service. | F38: =VLOOKUP($A38,'Institution Evaluation'!$A$56:$F$346,6,0)&""
A39: DCTR-05 | B39: =VLOOKUP($A39,Questions!$A$2:$X$333,2,0) -> Are your servers separated from other companies via a physical barrier, such as a cage or hard walls? | C39: Yes | D39: See AWS overview | E39: =IF($C$35="","",IF(OR($C$35='Auto Responses'!$J$17,$C$35='Auto Responses'!$J$19,$C$35='Auto Responses'!$J$20,$C$35='Auto Responses'!$J$21,$C$35='Auto Responses'!$J$22),'Auto Responses'!$A$26,IF($C39="Yes",VLOOKUP($A39,Questions!$A$2:$X$333,17,0)&"",IF($C39="No",VLOOKUP($A39,Questions!$A$2:$X$333,16,0)&"",VLOOKUP($A39,Questions!$A$2:$X$333,15,0)&"")))) -> Based on the response to DCTR-01, this question does not apply to this product or service. | F39: =VLOOKUP($A39,'Institution Evaluation'!$A$56:$F$346,6,0)&""
A40: DCTR-06 | B40: =VLOOKUP($A40,Questions!$A$2:$X$333,2,0) -> Does a physical barrier fully enclose the physical space, preventing unauthorized physical contact with any of your devices?* | C40: Yes | D40: See AWS overview | E40: =IF($C$35="","",IF(OR($C$35='Auto Responses'!$J$19,$C$35='Auto Responses'!$J$20,$C$35='Auto Responses'!$J$21,$C$35='Auto Responses'!$J$22),'Auto Responses'!$A$26,IF($C40="Yes",VLOOKUP($A40,Questions!$A$2:$X$333,17,0)&"",IF($C40="No",VLOOKUP($A40,Questions!$A$2:$X$333,16,0)&"",VLOOKUP($A40,Questions!$A$2:$X$333,15,0)&"")))) -> Based on the response to DCTR-01, this question does not apply to this product or service. | F40: =VLOOKUP($A40,'Institution Evaluation'!$A$56:$F$346,6,0)&""
A41: DCTR-07 | B41: =VLOOKUP($A41,Questions!$A$2:$X$333,2,0) -> Are your primary and secondary data centers geographically diverse? | C41: Yes | D41: Primary data center is in Ohio, secondary data center is in N. Virginia | E41: =IF($C$35="","",IF($C41="Yes",VLOOKUP($A41,Questions!$A$2:$X$333,17,0)&"",IF($C41="No",VLOOKUP($A41,Questions!$A$2:$X$333,16,0)&"",VLOOKUP($A41,Questions!$A$2:$X$333,15,0)&""))) -> State your primary and secondary data center locations. For cloud infrastructures, state the primary and secondary zones. | F41: =VLOOKUP($A41,'Institution Evaluation'!$A$56:$F$346,6,0)&""
A42: DCTR-08 | B42: =VLOOKUP($A42,Questions!$A$2:$X$333,2,0) -> Is the service hosted in a high-availability environment? | C42: Yes | D42: See AWS disaster recovery procedure | E42: =IF($C$35="","",IF($C42="Yes",VLOOKUP($A42,Questions!$A$2:$X$333,17,0)&"",IF($C42="No",VLOOKUP($A42,Questions!$A$2:$X$333,16,0)&"",VLOOKUP($A42,Questions!$A$2:$X$333,15,0)&""))) -> Provide a summary to support your response selection. | F42: =VLOOKUP($A42,'Institution Evaluation'!$A$56:$F$346,6,0)&""
A43: DCTR-09 | B43: =VLOOKUP($A43,Questions!$A$2:$X$333,2,0) -> Is redundant power available for all data centers where institutional data will reside? | C43: Yes | D43: See AWS disaster recovery procedure | E43: =IF($C$35="","",IF(OR($C$35='Auto Responses'!$J$20,$C$35='Auto Responses'!$J$21,$C$35='Auto Responses'!$J$22),'Auto Responses'!$A$26,IF($C43="Yes",VLOOKUP($A43,Questions!$A$2:$X$333,17,0)&"",IF($C43="No",VLOOKUP($A43,Questions!$A$2:$X$333,16,0)&"",VLOOKUP($A43,Questions!$A$2:$X$333,15,0)&"")))) -> Based on the response to DCTR-01, this question does not apply to this product or service. | F43: =VLOOKUP($A43,'Institution Evaluation'!$A$56:$F$346,6,0)&""
A44: DCTR-10 | B44: =VLOOKUP($A44,Questions!$A$2:$X$333,2,0) -> Are redundant power strategies tested?* | C44: Yes | D44: See AWS disaster recovery procedure | E44: =IF($C$35="","",IF(OR($C$35='Auto Responses'!$J$20,$C$35='Auto Responses'!$J$21,$C$35='Auto Responses'!$J$22),'Auto Responses'!$A$26,IF($C44="Yes",VLOOKUP($A44,Questions!$A$2:$X$333,17,0)&"",IF($C44="No",VLOOKUP($A44,Questions!$A$2:$X$333,16,0)&"",VLOOKUP($A44,Questions!$A$2:$X$333,15,0)&"")))) -> Based on the response to DCTR-01, this question does not apply to this product or service. | F44: =VLOOKUP($A44,'Institution Evaluation'!$A$56:$F$346,6,0)&""
A45: DCTR-11 | B45: =VLOOKUP($A45,Questions!$A$2:$X$333,2,0) -> Does the center where the data will reside have cooling and fire-suppression systems that are active and regularly tested? | C45: Yes | D45: See AWS disaster recovery procedure | E45: =IF($C$35="","",IF(OR($C$35='Auto Responses'!$J$19,$C$35='Auto Responses'!$J$20,$C$35='Auto Responses'!$J$21,$C$35='Auto Responses'!$J$22,$C$35='Auto Responses'!$J$23),'Auto Responses'!$A$26,IF($C45="Yes",VLOOKUP($A45,Questions!$A$2:$X$333,17,0)&"",IF($C45="No",VLOOKUP($A45,Questions!$A$2:$X$333,16,0)&"",VLOOKUP($A45,Questions!$A$2:$X$333,15,0)&"")))) -> Based on the response to DCTR-01, this question does not apply to this product or service. | F45: =VLOOKUP($A45,'Institution Evaluation'!$A$56:$F$346,6,0)&""
A46: DCTR-12 | B46: =VLOOKUP($A46,Questions!$A$2:$X$333,2,0) -> Do you have Internet Service Provider (ISP) redundancy? | C46: Yes | D46: See AWS disaster recovery procedure | E46: =IF($C$35="","",IF(OR($C$35='Auto Responses'!$J$20,$C$35='Auto Responses'!$J$21,$C$35='Auto Responses'!$J$22),'Auto Responses'!$A$26,IF($C46="Yes",VLOOKUP($A46,Questions!$A$2:$X$333,17,0)&"",IF($C46="No",VLOOKUP($A46,Questions!$A$2:$X$333,16,0)&"",VLOOKUP($A46,Questions!$A$2:$X$333,15,0)&"")))) -> Based on the response to DCTR-01, this question does not apply to this product or service. | F46: =VLOOKUP($A46,'Institution Evaluation'!$A$56:$F$346,6,0)&""
A47: DCTR-13 | B47: =VLOOKUP($A47,Questions!$A$2:$X$333,2,0) -> Does every data center where the institution's data will reside have multiple telephone company or network provider entrances to the facility? | C47: Yes | D47: See AWS disaster recovery procedure | F47: =VLOOKUP($A47,'Institution Evaluation'!$A$56:$F$346,6,0)&""
A48: DCTR-14 | B48: =VLOOKUP($A48,Questions!$A$2:$X$333,2,0) -> Do you require multifactor authentication for all administrative accounts in your environment? | C48: No | D48: MFA can be leveraged via the configuration of Single Sign On | E48: =IF($C$35="","",IF($C48="Yes",VLOOKUP($A48,Questions!$A$2:$X$333,17,0)&"",IF($C48="No",VLOOKUP($A48,Questions!$A$2:$X$333,16,0)&"",VLOOKUP($A48,Questions!$A$2:$X$333,15,0)&""))) -> Describe plans to implement MFA. | F48: =VLOOKUP($A48,'Institution Evaluation'!$A$56:$F$346,6,0)&""
A49: DCTR-15 | B49: =VLOOKUP($A49,Questions!$A$2:$X$333,2,0) -> Are you using your cloud provider's available hardening tools or pre-hardened images? | C49: Yes | D49: Coursedog uses industry-best tools for infrastructure monitoring and a variety of metrics to detect cyber threats like DDoS attacks. We also employ AWS technologies such as WAF, Shield, and Macie for added protection against anomalies and attacks. Learn More about Coursedog Security | E49: =IF($C$35="","",IF(OR($C$35='Auto Responses'!$J$17,$C$35='Auto Responses'!$J$18),'Auto Responses'!$A$26,IF($C49="Yes",VLOOKUP($A49,Questions!$A$2:$X$333,17,0)&"",IF($C49="No",VLOOKUP($A49,Questions!$A$2:$X$333,16,0)&"",VLOOKUP($A49,Questions!$A$2:$X$333,15,0)&"")))) | F49: =VLOOKUP($A49,'Institution Evaluation'!$A$56:$F$346,6,0)&""
A50: DCTR-16 | B50: =VLOOKUP($A50,Questions!$A$2:$X$333,2,0) -> Does your cloud solution provider have access to your encryption keys? | C50: No | E50: =IF($C$35="","",IF(OR($C$35='Auto Responses'!$J$17,$C$35='Auto Responses'!$J$18),'Auto Responses'!$A$26,IF($C50="Yes",VLOOKUP($A50,Questions!$A$2:$X$333,17,0)&"",IF($C50="No",VLOOKUP($A50,Questions!$A$2:$X$333,16,0)&"",VLOOKUP($A50,Questions!$A$2:$X$333,15,0)&"")))) | F50: =VLOOKUP($A50,'Institution Evaluation'!$A$56:$F$346,6,0)&""
A51: =VLOOKUP(LEFT($A52,4),'Auto Responses'!$N$4:$O$38,2,0)&"" -> Firewalls, IDS, IPS, and Networking | C51: Answer | D51: Additional Information | E51: Guidance | F51: Analyst Notes
A52: FIDP-01 | B52: =VLOOKUP($A52,Questions!$A$2:$X$333,2,0) -> Are you utilizing a stateful packet inspection (SPI) firewall?* | C52: Yes | D52: See AWS firewall documentation | E52: =IF($C$18="No",'Auto Responses'!$A$3,IF($C52="Yes",VLOOKUP($A52,Questions!$A$2:$X$333,17,0)&"",IF($C52="No",VLOOKUP($A52,Questions!$A$2:$X$333,16,0)&"",VLOOKUP($A52,Questions!$A$2:$X$333,15,0)&""))) -> Describe the currently implemented SPI firewall. | F52: =VLOOKUP($A52,'Institution Evaluation'!$A$56:$F$346,6,0)&""
A53: FIDP-02 | B53: =VLOOKUP($A53,Questions!$A$2:$X$333,2,0) -> Do you have a documented policy for firewall change requests?* | C53: Yes | D53: All changes must recieve approval from all engineering managers and system architects. Additionally, should be presented to AWS techical team for review. | E53: =IF($C$18="No",'Auto Responses'!$A$3,IF($C53="Yes",VLOOKUP($A53,Questions!$A$2:$X$333,17,0)&"",IF($C53="No",VLOOKUP($A53,Questions!$A$2:$X$333,16,0)&"",VLOOKUP($A53,Questions!$A$2:$X$333,15,0)&""))) -> Describe your documented firewall change request policy. | F53: =VLOOKUP($A53,'Institution Evaluation'!$A$56:$F$346,6,0)&""
A54: FIDP-03 | B54: =VLOOKUP($A54,Questions!$A$2:$X$333,2,0) -> Have you implemented an intrusion detection system (network-based)?* | C54: Yes | D54: Coursedog uses AWS Guard​Duty, AWS Shield, AWS IDS | E54: =IF($C$18="No",'Auto Responses'!$A$3,IF($C54="Yes",VLOOKUP($A54,Questions!$A$2:$X$333,17,0)&"",IF($C54="No",VLOOKUP($A54,Questions!$A$2:$X$333,16,0)&"",VLOOKUP($A54,Questions!$A$2:$X$333,15,0)&""))) -> Describe the currently implemented IDS. | F54: =VLOOKUP($A54,'Institution Evaluation'!$A$56:$F$346,6,0)&""
A55: FIDP-04 | B55: =VLOOKUP($A55,Questions!$A$2:$X$333,2,0) -> Do you employ host-based intrusion detection?* | C55: Yes | D55: Coursedog uses AWS Guard​Duty, AWS Shield, AWS IDS | E55: =IF($C$18="No",'Auto Responses'!$A$3,IF($C55="Yes",VLOOKUP($A55,Questions!$A$2:$X$333,17,0)&"",IF($C55="No",VLOOKUP($A55,Questions!$A$2:$X$333,16,0)&"",VLOOKUP($A55,Questions!$A$2:$X$333,15,0)&""))) -> Describe the currently implemented host-based IDS solution(s). | F55: =VLOOKUP($A55,'Institution Evaluation'!$A$56:$F$346,6,0)&""
A56: FIDP-05 | B56: =VLOOKUP($A56,Questions!$A$2:$X$333,2,0) -> Are audit logs available for all changes to the network, firewall, IDS, and IPS systems?* | C56: Yes | D56: Logged via AWS Cloudtrail | E56: =IF($C$18="No",'Auto Responses'!$A$3,IF($C56="Yes",VLOOKUP($A56,Questions!$A$2:$X$333,17,0)&"",IF($C56="No",VLOOKUP($A56,Questions!$A$2:$X$333,16,0)&"",VLOOKUP($A56,Questions!$A$2:$X$333,15,0)&""))) -> Describe your current network systems logging strategy. | F56: =VLOOKUP($A56,'Institution Evaluation'!$A$56:$F$346,6,0)&""
A57: FIDP-06 | B57: =VLOOKUP($A57,Questions!$A$2:$X$333,2,0) -> Is authority for firewall change approval documented? Please list approver names or titles in Additional Info. | C57: Yes | D57: Coursedog uses AWS Guard​Duty, AWS Shield, AWS IDS | F57: =VLOOKUP($A57,'Institution Evaluation'!$A$56:$F$346,6,0)&""
A58: FIDP-07 | B58: =VLOOKUP($A58,Questions!$A$2:$X$333,2,0) -> Have you implemented an intrusion prevention system (network-based)? | C58: Yes | D58: Coursedog uses AWS Guard​Duty, AWS Shield, AWS IDS | E58: =IF($C$18="No",'Auto Responses'!$A$3,IF($C58="Yes",VLOOKUP($A58,Questions!$A$2:$X$333,17,0)&"",IF($C58="No",VLOOKUP($A58,Questions!$A$2:$X$333,16,0)&"",VLOOKUP($A58,Questions!$A$2:$X$333,15,0)&""))) -> Describe the currently implemented IPS. | F58: =VLOOKUP($A58,'Institution Evaluation'!$A$56:$F$346,6,0)&""
A59: FIDP-08 | B59: =VLOOKUP($A59,Questions!$A$2:$X$333,2,0) -> Do you employ host-based intrusion prevention? | C59: Yes | D59: Coursedog uses AWS Guard​Duty, AWS Shield, AWS IDS | E59: =IF($C$18="No",'Auto Responses'!$A$3,IF($C59="Yes",VLOOKUP($A59,Questions!$A$2:$X$333,17,0)&"",IF($C59="No",VLOOKUP($A59,Questions!$A$2:$X$333,16,0)&"",VLOOKUP($A59,Questions!$A$2:$X$333,15,0)&""))) -> Describe the currently implemented host-based IPS solution(s). | F59: =VLOOKUP($A59,'Institution Evaluation'!$A$56:$F$346,6,0)&""
A60: FIDP-09 | B60: =VLOOKUP($A60,Questions!$A$2:$X$333,2,0) -> Are you employing any next-generation persistent threat (NGPT) monitoring? | C60: Yes | D60: Coursedog uses AWS Guard​Duty, AWS Shield, AWS IDS | E60: =IF($C$18="No",'Auto Responses'!$A$3,IF($C60="Yes",VLOOKUP($A60,Questions!$A$2:$X$333,17,0)&"",IF($C60="No",VLOOKUP($A60,Questions!$A$2:$X$333,16,0)&"",VLOOKUP($A60,Questions!$A$2:$X$333,15,0)&""))) -> Describe your NGPT monitoring strategy. | F60: =VLOOKUP($A60,'Institution Evaluation'!$A$56:$F$346,6,0)&""
A61: FIDP-10 | B61: =VLOOKUP($A61,Questions!$A$2:$X$333,2,0) -> Is intrusion monitoring performed internally or by a third-party service? | C61: Yes | D61: Coursedog uses AWS Guard​Duty, AWS Shield, AWS IDS | E61: =IF($C$18="No",'Auto Responses'!$A$3,IF($C61="Yes",VLOOKUP($A61,Questions!$A$2:$X$333,17,0)&"",IF($C61="No",VLOOKUP($A61,Questions!$A$2:$X$333,16,0)&"",VLOOKUP($A61,Questions!$A$2:$X$333,15,0)&""))) | F61: =VLOOKUP($A61,'Institution Evaluation'!$A$56:$F$346,6,0)&""
A62: FIDP-11 | B62: =VLOOKUP($A62,Questions!$A$2:$X$333,2,0) -> Do you monitor for intrusions on a 24 x 7 x 365 basis? | C62: Yes | D62: Coursedog uses AWS Guard​Duty, AWS Shield, AWS IDS | E62: =IF($C$18="No",'Auto Responses'!$A$3,IF($C62="Yes",VLOOKUP($A62,Questions!$A$2:$X$333,17,0)&"",IF($C62="No",VLOOKUP($A62,Questions!$A$2:$X$333,16,0)&"",VLOOKUP($A62,Questions!$A$2:$X$333,15,0)&""))) -> Provide a brief summary of this activity. | F62: =VLOOKUP($A62,'Institution Evaluation'!$A$56:$F$346,6,0)&"" | G62: End Table Data
A63: =VLOOKUP(LEFT($A64,4),'Auto Responses'!$N$4:$O$38,2,0)&"" -> Incident Handling | C63: Answer | D63: Additional Information | E63: Guidance | F63: Analyst Notes
A64: HFIH-01 | B64: =VLOOKUP($A64,Questions!$A$2:$X$333,2,0) -> Do you have a formal incident response plan? | C64: Yes | D64: Available up request | E64: =IF($C$18="No",'Auto Responses'!$A$3,IF($C64="Yes",VLOOKUP($A64,Questions!$A$2:$X$333,17,0)&"",IF($C64="No",VLOOKUP($A64,Questions!$A$2:$X$333,16,0)&"",VLOOKUP($A64,Questions!$A$2:$X$333,15,0)&""))) -> Summarize or provide a link to your formal incident response plan. | F64: =VLOOKUP($A64,'Institution Evaluation'!$A$56:$F$346,6,0)&""
A65: HFIH-02 | B65: =VLOOKUP($A65,Questions!$A$2:$X$333,2,0) -> Do you either have an internal incident response team or retain an external team? | C65: Yes | D65: See incident response process. | E65: =IF($C$18="No",'Auto Responses'!$A$3,IF($C65="Yes",VLOOKUP($A65,Questions!$A$2:$X$333,17,0)&"",IF($C65="No",VLOOKUP($A65,Questions!$A$2:$X$333,16,0)&"",VLOOKUP($A65,Questions!$A$2:$X$333,15,0)&""))) -> Summarize your incident response and reporting processes. | F65: =VLOOKUP($A65,'Institution Evaluation'!$A$56:$F$346,6,0)&""
A66: HFIH-03 | B66: =VLOOKUP($A66,Questions!$A$2:$X$333,2,0) -> Do you have the capability to respond to incidents on a 24 x 7 x 365 basis? | C66: Yes | D66: See AWS Controls | E66: =IF($C$18="No",'Auto Responses'!$A$3,IF($C66="Yes",VLOOKUP($A66,Questions!$A$2:$X$333,17,0)&"",IF($C66="No",VLOOKUP($A66,Questions!$A$2:$X$333,16,0)&"",VLOOKUP($A66,Questions!$A$2:$X$333,15,0)&""))) -> Summarize your internal approach or reference your third-party contractor. | F66: =VLOOKUP($A66,'Institution Evaluation'!$A$56:$F$346,6,0)&""
A67: HFIH-04 | B67: =VLOOKUP($A67,Questions!$A$2:$X$333,2,0) -> Do you carry cyber-risk insurance to protect against unforeseen service outages, data that is lost or stolen, and security incidents? | C67: Yes | D67: Coursedog is happy to provide certificate of insurance upon request; we have $2M limit w/ $5M additional umbrella coverage | E67: =IF($C$18="No",'Auto Responses'!$A$3,IF($C67="Yes",VLOOKUP($A67,Questions!$A$2:$X$333,17,0)&"",IF($C67="No",VLOOKUP($A67,Questions!$A$2:$X$333,16,0)&"",VLOOKUP($A67,Questions!$A$2:$X$333,15,0)&""))) -> Describe the coverage in place for this solution. | F67: =VLOOKUP($A67,'Institution Evaluation'!$A$56:$F$346,6,0)&"" | G67: End Table Data
A68: =VLOOKUP(LEFT($A69,4),'Auto Responses'!$N$4:$O$38,2,0)&"" -> Vulnerability Management | C68: Answer | D68: Additional Information | E68: Guidance | F68: Analyst Notes
A69: VULN-01 | B69: =VLOOKUP($A69,Questions!$A$2:$X$333,2,0) -> Are your systems and applications scanned with an authenticated user account for vulnerabilities (that are remediated) prior to new releases?* | C69: Yes | D69: Updates are thoroughly tested in a QA system before being moved to a staging environment and then to production. This process ensures that any vulnerabilities are addressed before the new releases. | E69: =IF($C$18="No",'Auto Responses'!$A$3,IF($C69="Yes",VLOOKUP($A69,Questions!$A$2:$X$333,17,0)&"",IF($C69="No",VLOOKUP($A69,Questions!$A$2:$X$333,16,0)&"",VLOOKUP($A69,Questions!$A$2:$X$333,15,0)&""))) -> Provide a brief description. | F69: =VLOOKUP($A69,'Institution Evaluation'!$A$56:$F$346,6,0)&""
A70: VULN-02 | B70: =VLOOKUP($A70,Questions!$A$2:$X$333,2,0) -> Will you provide results of application and system vulnerability scans to the institution?* | C70: Yes | D70: Available upon request | E70: =IF($C$18="No",'Auto Responses'!$A$3,IF($C70="Yes",VLOOKUP($A70,Questions!$A$2:$X$333,17,0)&"",IF($C70="No",VLOOKUP($A70,Questions!$A$2:$X$333,16,0)&"",VLOOKUP($A70,Questions!$A$2:$X$333,15,0)&""))) -> Provide a reference to security scan documentation. | F70: =VLOOKUP($A70,'Institution Evaluation'!$A$56:$F$346,6,0)&""
A71: VULN-03 | B71: =VLOOKUP($A71,Questions!$A$2:$X$333,2,0) -> Will you allow the institution to perform its own vulnerability testing and/or scanning of your systems and/or application, provided that testing is performed at a mutually agreed upon time and date?* | C71: Yes | D71: Coursedog prefers to avoid undue load on the system and is more than happy to provide documentation to satisfy the requirement. | E71: =IF($C$18="No",'Auto Responses'!$A$3,IF($C71="Yes",VLOOKUP($A71,Questions!$A$2:$X$333,17,0)&"",IF($C71="No",VLOOKUP($A71,Questions!$A$2:$X$333,16,0)&"",VLOOKUP($A71,Questions!$A$2:$X$333,15,0)&""))) -> Provide reference to the process or procedure to set up security testing times and scopes. | F71: =VLOOKUP($A71,'Institution Evaluation'!$A$56:$F$346,6,0)&""
A72: VULN-04 | B72: =VLOOKUP($A72,Questions!$A$2:$X$333,2,0) -> Have your systems and applications had a third-party security assessment completed in the last year? | C72: Yes | D72: An external audit of our application from a trusted third party is conducted annually. | E72: =IF($C$18="No",'Auto Responses'!$A$3,IF($C72="Yes",VLOOKUP($A72,Questions!$A$2:$X$333,17,0)&"",IF($C72="No",VLOOKUP($A72,Questions!$A$2:$X$333,16,0)&"",VLOOKUP($A72,Questions!$A$2:$X$333,15,0)&""))) -> Provide the results with this document (link or attached), if possible. State the date of the last completed third-party security assessment. | F72: =VLOOKUP($A72,'Institution Evaluation'!$A$56:$F$346,6,0)&""
A73: VULN-05 | B73: =VLOOKUP($A73,Questions!$A$2:$X$333,2,0) -> Do you regularly scan for common web application security vulnerabilities (e.g., SQL injection, XSS, XSRF, etc.)? | C73: Yes | D73: Where possible, defenses against attacks are incorporated directly into the design. For example, use of MongoDB maintains a separation of the data in the query from the query itself, making an SQL injection type attack fundamentally impossible. Our use of a REST API is beneficial because session state information is not stored on the server, mitigating state-based attacks. Coursedog's web-based design is an important reason why our solutions can be fundamentally more secure than our competitors. Coursedog never requires clients to install custom software to access our products. By running in the browser sandbox, our software by default runs with extremely limited privileges unlike an installed executable. Modern browser sandboxes have been tried and tested for many years and are used by millions of people to protect their computers from malicious actors while on the web. In a web browser sandbox Coursedog cannot access confidential local files or install viruses or keyloggers on Customer's machines, even if the system were compromised. This design isolates the Coursedog system from the rest of our Customers' networks. | F73: =VLOOKUP($A73,'Institution Evaluation'!$A$56:$F$346,6,0)&""
A74: VULN-06 | B74: =VLOOKUP($A74,Questions!$A$2:$X$333,2,0) -> Are your systems and applications regularly scanned externally for vulnerabilities? | C74: Yes | D74: See AWS Penetration Testing | E74: =IF($C$18="No",'Auto Responses'!$A$3,IF($C74="Yes",VLOOKUP($A74,Questions!$A$2:$X$333,17,0)&"",IF($C74="No",VLOOKUP($A74,Questions!$A$2:$X$333,16,0)&"",VLOOKUP($A74,Questions!$A$2:$X$333,15,0)&""))) -> Decribe your external application vulnerability scanning strategy. | F74: =VLOOKUP($A74,'Institution Evaluation'!$A$56:$F$346,6,0)&"" | G74: End Table Data
A75: Copyright © 2025 EDUCAUSE
A78: =#REF! -> #REF!
A79: =#REF! -> #REF!
A80: =#REF! -> #REF!
A81: =#REF! -> #REF!
A82: =#REF! -> #REF!
A83: =#REF! -> #REF!
A84: =#REF! -> #REF!

Sheet IT Accessibility
A1: Cells contained in this worksheet may contain cells with dropdown lists as well as autopopulated formulas.
A2: HECVAT Solution Provider Response - IT Accessibility | F2: ='Auto Responses'!$A$36 -> Version 4.04
A3: Date Completed | C3: ='START HERE'!$C$3 -> 45933
A4: Instructions for Solution Providers
A5: =HLOOKUP($A$4,'Auto Responses'!$D$2:$D$8,2,0)&"" -> 1. Complete the "Start Here" tab and review the "Required Questions" guidance to find the other sections are required for your product or service.
A6: =HLOOKUP($A$4,'Auto Responses'!$D$2:$D$8,3,0)&"" -> 2. Complete the "Organization" tab and the applicable questions in each of the next 5 tabs (Product through Privacy) that apply, based on your answers to the "Required Questions."
A7: =HLOOKUP($A$4,'Auto Responses'!$D$2:$D$8,4,0)&"" -> 3. Guidance in column E may change based on your answers to prompt details in "Additional Information." If leaving an answer blank, you must also state why in "Additional Information".
A8: =HLOOKUP($A$4,'Auto Responses'!$D$2:$D$8,5,0)&"" -> 4. DO NOT complete any fields in the "Evaluation" sheets or the "Analyst Notes" column.
A9: =HLOOKUP($A$4,'Auto Responses'!$D$2:$D$8,6,0)&"" -> 5. Return the completed file to institutions.
A10: =HLOOKUP($A$4,'Auto Responses'!$D$2:$D$8,7,0)&"" -> * Denotes critical questions. Critical questions are those deemed most important to institutions by higher education volunteers.
A11: =HLOOKUP($A$4,'Auto Responses'!$D$2:$D$9,8,0)&"" -> For full instructions, please visit educause.edu/HECVAT
A12: =VLOOKUP(LEFT($A13,4),'Auto Responses'!$N$4:$O$38,2,0)&"" -> General Information | C12: Answer
A13: GNRL-01 | B13: =VLOOKUP($A13,Questions!$A$2:$X$333,2,0)&"" -> Solution Provider Name | C13: =VLOOKUP($A13,'START HERE'!$A$13:$C$21,3,0)&"" -> Coursedog
A14: GNRL-02 | B14: =VLOOKUP($A14,Questions!$A$2:$X$333,2,0)&"" -> Solution Name | C14: =VLOOKUP($A14,'START HERE'!$A$13:$C$21,3,0)&"" -> Coursedog
A15: GNRL-03 | B15: =VLOOKUP($A15,Questions!$A$2:$X$333,2,0)&"" -> Solution Description | C15: =VLOOKUP($A15,'START HERE'!$A$13:$C$21,3,0)&"" -> Coursedog is a SaaS platform designed to streamline curriculum, catalog, and scheduling management for higher education institutions, offering intuitive tools, insightful analytics, and seamless integration without requiring IT involvement.
A16: GNRL-08 | B16: =VLOOKUP($A16,Questions!$A$2:$X$333,2,0)&"" -> Country of Company Headquarters | C16: =VLOOKUP($A16,'START HERE'!$A$13:$C$21,3,0)&"" -> United States
A17: =VLOOKUP(LEFT($A18,4),'Auto Responses'!$N$4:$O$38,2,0)&"" -> Required Questions | C17: Answer | E17: Guidance | F17: Analyst Notes
A18: REQU-02 | B18: =VLOOKUP($A18,Questions!$A$2:$X$333,2,0) -> Does your product or service have an interface? | C18: =VLOOKUP($A18,'START HERE'!$A$23:$F$36,3,0)&"" -> Yes | D18: =VLOOKUP($A18,'START HERE'!$A$23:$F$36,4,0)&"" -> Coursedog provides a UI for all of its products with the platform | E18: =IF($C18="Yes",VLOOKUP($A18,Questions!$A$2:$X$333,17,0)&"",IF($C18="No",VLOOKUP($A18,Questions!$A$2:$X$333,16,0)&"",VLOOKUP($A18,Questions!$A$2:$X$333,15,0)&"")) -> DO complete the IT Accessibility worksheet. | F18: =VLOOKUP($A18,'Institution Evaluation'!$A$56:$F$346,6,0)&"" | G18: End Table Data
A19: =VLOOKUP(LEFT($A20,4),'Auto Responses'!$N$4:$O$38,2,0)&"" -> IT Accessibility | C19: Answer | D19: Additional Information | E19: Guidance | F19: Analyst Notes
A20: ITAC-01 | B20: =VLOOKUP($A20,Questions!$A$2:$X$333,2,0) -> Solution Provider Accessibility Contact Name | C20: Daniel Lipkin | F20: =VLOOKUP($A20,'Institution Evaluation'!$A$56:$F$346,6,0)&""
A21: ITAC-02 | B21: =VLOOKUP($A21,Questions!$A$2:$X$333,2,0) -> Solution Provider Accessibility Contact Title | C21: CTO | F21: =VLOOKUP($A21,'Institution Evaluation'!$A$56:$F$346,6,0)&""
A22: ITAC-03 | B22: =VLOOKUP($A22,Questions!$A$2:$X$333,2,0) -> Solution Provider Accessibility Contact Email | C22: dlipkin@coursedog.com | F22: =VLOOKUP($A22,'Institution Evaluation'!$A$56:$F$346,6,0)&""
A23: ITAC-04 | B23: =VLOOKUP($A23,Questions!$A$2:$X$333,2,0) -> Solution Provider Accessibility Contact Phone Number | C23: 310-980-2495 | F23: =VLOOKUP($A23,'Institution Evaluation'!$A$56:$F$346,6,0)&""
A24: ITAC-05 | B24: =VLOOKUP($A24,Questions!$A$2:$X$333,2,0) -> Web Link to Accessibility Statement or VPAT | C24: https://coursedog.my.site.com/support/s/article/CoursedogApplicationAccessibility67fda79f83ed9 | E24: =IF($C$18="No",'Auto Responses'!$A$4,IF($C24="Yes",VLOOKUP($A24,Questions!$A$2:$X$333,17,0)&"",IF($C24="No",VLOOKUP($A24,Questions!$A$2:$X$333,16,0)&"",VLOOKUP($A24,Questions!$A$2:$X$333,15,0)&""))) -> VPAT can also be added as an attachment | F24: =VLOOKUP($A24,'Institution Evaluation'!$A$56:$F$346,6,0)&""
A25: ITAC-06 | B25: =VLOOKUP($A25,Questions!$A$2:$X$333,2,0) -> Has a VPAT or ACR been created or updated for the solution and version under consideration within the past 12 months?* | C25: Yes | D25: https://coursedog.my.site.com/support/s/article/CoursedogApplicationAccessibility67fda79f83ed9 | E25: =IF($C$18="No",'Auto Responses'!$A$4,IF($C25="Yes",VLOOKUP($A25,Questions!$A$2:$X$333,17,0)&"",IF($C25="No",VLOOKUP($A25,Questions!$A$2:$X$333,16,0)&"",VLOOKUP($A25,Questions!$A$2:$X$333,15,0)&""))) -> State the date the VPAT was completed. Include this VPAT in your submission and/or link to its web location. | F25: =VLOOKUP($A25,'Institution Evaluation'!$A$56:$F$346,6,0)&""
A26: ITAC-07 | B26: =VLOOKUP($A26,Questions!$A$2:$X$333,2,0) -> Will your company agree to meet your stated accessibility standard or WCAG 2.1 AA as part of your contractual agreement for the solution?* | C26: Yes | D26: https://coursedog.my.site.com/support/s/article/CoursedogApplicationAccessibility67fda79f83ed9 | E26: =IF($C$18="No",'Auto Responses'!$A$4,IF($C26="Yes",VLOOKUP($A26,Questions!$A$2:$X$333,17,0)&"",IF($C26="No",VLOOKUP($A26,Questions!$A$2:$X$333,16,0)&"",VLOOKUP($A26,Questions!$A$2:$X$333,15,0)&""))) | F26: =VLOOKUP($A26,'Institution Evaluation'!$A$56:$F$346,6,0)&""
A27: ITAC-08 | B27: =VLOOKUP($A27,Questions!$A$2:$X$333,2,0) -> Does the solution substantially conform to WCAG 2.1 AA?* | C27: Yes | D27: https://coursedog.my.site.com/support/s/article/CoursedogApplicationAccessibility67fda79f83ed9 | E27: =IF($C$18="No",'Auto Responses'!$A$4,IF($C27="Yes",VLOOKUP($A27,Questions!$A$2:$X$333,17,0)&"",IF($C27="No",VLOOKUP($A27,Questions!$A$2:$X$333,16,0)&"",VLOOKUP($A27,Questions!$A$2:$X$333,15,0)&""))) | F27: =VLOOKUP($A27,'Institution Evaluation'!$A$56:$F$346,6,0)&""
A28: ITAC-09 | B28: =VLOOKUP($A28,Questions!$A$2:$X$333,2,0) -> Do you have a documented and implemented process for reporting and tracking accessibility issues?* | C28: Yes | D28: Coursedog has a documented and implemented process for reporting and tracking accessibility issues. Users can report accessibility issues by submitting a Feature Request or through the dedicated Customer Success Manager (CSM). These issues are re-evaluated internally and added to the engineering backlog if they impact site accessibility. | E28: =IF($C$18="No",'Auto Responses'!$A$4,IF($C28="Yes",VLOOKUP($A28,Questions!$A$2:$X$333,17,0)&"",IF($C28="No",VLOOKUP($A28,Questions!$A$2:$X$333,16,0)&"",VLOOKUP($A28,Questions!$A$2:$X$333,15,0)&""))) -> Describe the process and any recent examples of fixes as a result of the process. | F28: =VLOOKUP($A28,'Institution Evaluation'!$A$56:$F$346,6,0)&""
A29: ITAC-10 | B29: =VLOOKUP($A29,Questions!$A$2:$X$333,2,0) -> Do you have documentation to support the accessibility features of your solution? | C29: Yes | D29: Accessibility is a key aspect of the Coursedog user experience. As such Coursedog has a full time UX designer that reviews all changes for usability and accessibility. Coursedog prioritizes WCAG 2.1 A-level compliance for public facing pages. See our accessability documentation for more information inclusing a VPAT. | E29: =IF($C$18="No",'Auto Responses'!$A$4,IF($C29="Yes",VLOOKUP($A29,Questions!$A$2:$X$333,17,0)&"",IF($C29="No",VLOOKUP($A29,Questions!$A$2:$X$333,16,0)&"",VLOOKUP($A29,Questions!$A$2:$X$333,15,0)&""))) -> Provide examples with links where possible. | F29: =VLOOKUP($A29,'Institution Evaluation'!$A$56:$F$346,6,0)&""
A30: ITAC-11 | B30: =VLOOKUP($A30,Questions!$A$2:$X$333,2,0) -> Has a third-party expert conducted an audit of the most recent version of your solution? | C30: Yes | D30: Coursedog conducts regular penetration tests with a third-party vendor for risk assessment, which includes weekly scans and reports on vulnerabilities. Results are kept private for security purposes. | E30: =IF($C$18="No",'Auto Responses'!$A$4,IF($C30="Yes",VLOOKUP($A30,Questions!$A$2:$X$333,17,0)&"",IF($C30="No",VLOOKUP($A30,Questions!$A$2:$X$333,16,0)&"",VLOOKUP($A30,Questions!$A$2:$X$333,15,0)&""))) -> State when the audit was conducted and by whom. Include the results in your submission and/or link to its web location. | F30: =VLOOKUP($A30,'Institution Evaluation'!$A$56:$F$346,6,0)&""
A31: ITAC-12 | B31: =VLOOKUP($A31,Questions!$A$2:$X$333,2,0) -> Do you have a documented and implemented process for verifying accessibility conformance? | C31: Yes | D31: Accessibility is a key aspect of the Coursedog user experience. As such Coursedog has a full time UX designer that reviews all changes for usability and accessibility. Coursedog prioritizes WCAG 2.1 A-level compliance for public facing pages. See our accessability documentation for more information inclusing a VPAT. | E31: =IF($C$18="No",'Auto Responses'!$A$4,IF($C31="Yes",VLOOKUP($A31,Questions!$A$2:$X$333,17,0)&"",IF($C31="No",VLOOKUP($A31,Questions!$A$2:$X$333,16,0)&"",VLOOKUP($A31,Questions!$A$2:$X$333,15,0)&""))) -> Describe your processes and methodologies for validating accessibility conformance. | F31: =VLOOKUP($A31,'Institution Evaluation'!$A$56:$F$346,6,0)&""
A32: ITAC-13 | B32: =VLOOKUP($A32,Questions!$A$2:$X$333,2,0) -> Have you adopted a technical or legal standard of conformance for the solution? | C32: Yes | D32: Coursedog prioritizes WCAG 2.1 A-level compliance for public facing pages. See our accessability documentation for more information inclusing a VPAT. | E32: =IF($C$18="No",'Auto Responses'!$A$4,IF($C32="Yes",VLOOKUP($A32,Questions!$A$2:$X$333,17,0)&"",IF($C32="No",VLOOKUP($A32,Questions!$A$2:$X$333,16,0)&"",VLOOKUP($A32,Questions!$A$2:$X$333,15,0)&""))) -> Indicate which primary standards and all additional standards the solution meets. | F32: =VLOOKUP($A32,'Institution Evaluation'!$A$56:$F$346,6,0)&""
A33: ITAC-14 | B33: =VLOOKUP($A33,Questions!$A$2:$X$333,2,0) -> Can you provide a current, detailed accessibility roadmap with delivery timelines? | C33: Yes | D33: See example Roadmap | E33: =IF($C$18="No",'Auto Responses'!$A$4,IF($C33="Yes",VLOOKUP($A33,Questions!$A$2:$X$333,17,0)&"",IF($C33="No",VLOOKUP($A33,Questions!$A$2:$X$333,16,0)&"",VLOOKUP($A33,Questions!$A$2:$X$333,15,0)&""))) -> Comment on how far into the future the roadmap extends. Provide evidence (including links) of having delivered upon the accessibility roadmap in the past. | F33: =VLOOKUP($A33,'Institution Evaluation'!$A$56:$F$346,6,0)&""
A34: ITAC-15 | B34: =VLOOKUP($A34,Questions!$A$2:$X$333,2,0) -> Do you expect your staff to maintain a current skill set in IT accessibility? | C34: Yes | D34: Coursedog maintains a current skill set in IT accessibility. Coursedog has a full-time UX designer dedicated to reviewing all changes for usability and accessibility. Each customer facing team member is aware of the basics of accessability requirements and the process to submit updates as they arise. | E34: =IF($C$18="No",'Auto Responses'!$A$4,IF($C34="Yes",VLOOKUP($A34,Questions!$A$2:$X$333,17,0)&"",IF($C34="No",VLOOKUP($A34,Questions!$A$2:$X$333,16,0)&"",VLOOKUP($A34,Questions!$A$2:$X$333,15,0)&""))) -> Provide any further relevant information about how expertise is maintained; include any accessibility certifications staff may hold (e.g., IAAP WAS <https://www.accessibilityassociation.org/certifications> or DHS Trusted Tester <https://section508.gov/test/trusted-tester>). | F34: =VLOOKUP($A34,'Institution Evaluation'!$A$56:$F$346,6,0)&""
A35: ITAC-16 | B35: =VLOOKUP($A35,Questions!$A$2:$X$333,2,0) -> Do you have documented processes and procedures for implementing accessibility into your development lifecycle? | C35: Yes | D35: Coursedog has documented processes and procedures for implementing accessibility into the development lifecycle. Accessibility-related changes are tested by a full-time UX designer using various screen readers across different browsers. Coursedog also runs third party scans to ensure changes meet specifications, and these changes follow the standard testing process. | E35: =IF($C$18="No",'Auto Responses'!$A$4,IF($C35="Yes",VLOOKUP($A35,Questions!$A$2:$X$333,17,0)&"",IF($C35="No",VLOOKUP($A35,Questions!$A$2:$X$333,16,0)&"",VLOOKUP($A35,Questions!$A$2:$X$333,15,0)&""))) -> Provide further details in Additional Information. | F35: =VLOOKUP($A35,'Institution Evaluation'!$A$56:$F$346,6,0)&""
A36: ITAC-17 | B36: =VLOOKUP($A36,Questions!$A$2:$X$333,2,0) -> Can all functions of the application or service be performed using only the keyboard? | C36: Yes | D36: Coursedog supports keyboards across the entire public-facing sites such as the Catalog. By presenting content in a meaningful order, separating navigation menus from content, and following industry standards when coding HTML, we ensure it works seamlessly. However, due to the vast number of interactive elements available on the internal configuration screens, it might be difficult to use keyboards effectively in some parts of the internal application. | E36: =IF($C$18="No",'Auto Responses'!$A$4,IF($C36="Yes",VLOOKUP($A36,Questions!$A$2:$X$333,17,0)&"",IF($C36="No",VLOOKUP($A36,Questions!$A$2:$X$333,16,0)&"",VLOOKUP($A36,Questions!$A$2:$X$333,15,0)&""))) -> State when and on which platform this was verified. | F36: =VLOOKUP($A36,'Institution Evaluation'!$A$56:$F$346,6,0)&""
A37: ITAC-18 | B37: =VLOOKUP($A37,Questions!$A$2:$X$333,2,0) -> Does your product rely on activating a special "accessibility mode," a "lite version," or using an alternate interface (including “overlay” or AI-based alternates) for accessibility purposes? | C37: No | E37: =IF($C$18="No",'Auto Responses'!$A$4,IF($C37="Yes",VLOOKUP($A37,Questions!$A$2:$X$333,17,0)&"",IF($C37="No",VLOOKUP($A37,Questions!$A$2:$X$333,16,0)&"",VLOOKUP($A37,Questions!$A$2:$X$333,15,0)&""))) | F37: =VLOOKUP($A37,'Institution Evaluation'!$A$56:$F$346,6,0)&"" | G37: End Table Data
A38: Copyright © 2025 EDUCAUSE
A41: =#REF! -> #REF!
A42: =#REF! -> #REF!
A43: =#REF! -> #REF!
A44: =#REF! -> #REF!
A45: =#REF! -> #REF!
A46: =#REF! -> #REF!
A47: =#REF! -> #REF!

Sheet Case-Specific
A1: Cells contained in this worksheet may contain cells with dropdown lists as well as autopopulated formulas.
A2: HECVAT Solution Provider Response - Case-Specific Questions | F2: ='Auto Responses'!$A$36 -> Version 4.04
A3: Date Completed | C3: ='START HERE'!$C$3 -> 45933
A4: Instructions for Solution Providers
A5: =HLOOKUP($A$4,'Auto Responses'!$D$2:$D$8,2,0)&"" -> 1. Complete the "Start Here" tab and review the "Required Questions" guidance to find the other sections are required for your product or service.
A6: =HLOOKUP($A$4,'Auto Responses'!$D$2:$D$8,3,0)&"" -> 2. Complete the "Organization" tab and the applicable questions in each of the next 5 tabs (Product through Privacy) that apply, based on your answers to the "Required Questions."
A7: =HLOOKUP($A$4,'Auto Responses'!$D$2:$D$8,4,0)&"" -> 3. Guidance in column E may change based on your answers to prompt details in "Additional Information." If leaving an answer blank, you must also state why in "Additional Information".
A8: =HLOOKUP($A$4,'Auto Responses'!$D$2:$D$8,5,0)&"" -> 4. DO NOT complete any fields in the "Evaluation" sheets or the "Analyst Notes" column.
A9: =HLOOKUP($A$4,'Auto Responses'!$D$2:$D$8,6,0)&"" -> 5. Return the completed file to institutions.
A10: =HLOOKUP($A$4,'Auto Responses'!$D$2:$D$8,7,0)&"" -> * Denotes critical questions. Critical questions are those deemed most important to institutions by higher education volunteers.
A11: =HLOOKUP($A$4,'Auto Responses'!$D$2:$D$9,8,0)&"" -> For full instructions, please visit educause.edu/HECVAT
A12: =VLOOKUP(LEFT($A13,4),'Auto Responses'!$N$4:$O$38,2,0)&"" -> General Information | C12: Answer
A13: GNRL-01 | B13: =VLOOKUP($A13,Questions!$A$2:$X$333,2,0)&"" -> Solution Provider Name | C13: =VLOOKUP($A13,'START HERE'!$A$13:$C$21,3,0)&"" -> Coursedog
A14: GNRL-02 | B14: =VLOOKUP($A14,Questions!$A$2:$X$333,2,0)&"" -> Solution Name | C14: =VLOOKUP($A14,'START HERE'!$A$13:$C$21,3,0)&"" -> Coursedog
A15: GNRL-03 | B15: =VLOOKUP($A15,Questions!$A$2:$X$333,2,0)&"" -> Solution Description | C15: =VLOOKUP($A15,'START HERE'!$A$13:$C$21,3,0)&"" -> Coursedog is a SaaS platform designed to streamline curriculum, catalog, and scheduling management for higher education institutions, offering intuitive tools, insightful analytics, and seamless integration without requiring IT involvement.
A16: GNRL-08 | B16: =VLOOKUP($A16,Questions!$A$2:$X$333,2,0)&"" -> Country of Company Headquarters | C16: =VLOOKUP($A16,'START HERE'!$A$13:$C$21,3,0)&"" -> United States
A17: =VLOOKUP(LEFT($A18,4),'Auto Responses'!$N$4:$O$38,2,0)&"" -> Required Questions | C17: Answer | D17: Additional Information | E17: Guidance | F17: Analyst Notes
A18: REQU-03 | B18: =VLOOKUP($A18,Questions!$A$2:$X$333,2,0) -> Are you providing consulting services? | C18: Yes | D18: Coursedog's professional services team, led by a project manager/subject matter expert, can work with your team for intensive business process consulting. | E18: =IF($C18="Yes",VLOOKUP($A18,Questions!$A$2:$X$333,17,0)&"",IF($C18="No",VLOOKUP($A18,Questions!$A$2:$X$333,16,0)&"",VLOOKUP($A18,Questions!$A$2:$X$333,15,0)&"")) -> DO complete the Consulting section in the Case-Specific worksheet | F18: =VLOOKUP($A18,'Institution Evaluation'!$A$56:$F$346,6,0)&""
A19: REQU-05 | B19: =VLOOKUP($A19,Questions!$A$2:$X$333,2,0) -> Does your solution process protected health information (PHI) or any data covered by the Health Insurance Portability and Accountability Act (HIPAA)? | C19: No | D19: =VLOOKUP($A19,'START HERE'!$A$23:$F$36,4,0)&"" | E19: =IF($C19="Yes",VLOOKUP($A19,Questions!$A$2:$X$333,17,0)&"",IF($C19="No",VLOOKUP($A19,Questions!$A$2:$X$333,16,0)&"",VLOOKUP($A19,Questions!$A$2:$X$333,15,0)&"")) -> DO NOT complete the HIPAA section in the Case-Specific worksheet | F19: =VLOOKUP($A19,'Institution Evaluation'!$A$56:$F$346,6,0)&""
A20: REQU-06 | B20: =VLOOKUP($A20,Questions!$A$2:$X$333,2,0) -> Is the solution designed to process, store, or transmit credit card information? | C20: No | D20: =VLOOKUP($A20,'START HERE'!$A$23:$F$36,4,0)&"" | E20: =IF($C20="Yes",VLOOKUP($A20,Questions!$A$2:$X$333,17,0)&"",IF($C20="No",VLOOKUP($A20,Questions!$A$2:$X$333,16,0)&"",VLOOKUP($A20,Questions!$A$2:$X$333,15,0)&"")) -> DO NOT complete the PCI-DSS section in the Case-Specific worksheet | F20: =VLOOKUP($A20,'Institution Evaluation'!$A$56:$F$346,6,0)&""
A21: REQU-07 | B21: =VLOOKUP($A21,Questions!$A$2:$X$333,2,0) -> Does operating your solution require the institution to operate a physical or virtual appliance in their own environment or to provide inbound firewall exceptions to allow your employees to remotely administer systems in the institution's environment? | C21: No | D21: =VLOOKUP($A21,'START HERE'!$A$23:$F$36,4,0)&"" | E21: =IF($C21="Yes",VLOOKUP($A21,Questions!$A$2:$X$333,17,0)&"",IF($C21="No",VLOOKUP($A21,Questions!$A$2:$X$333,16,0)&"",VLOOKUP($A21,Questions!$A$2:$X$333,15,0)&"")) -> DO NOT complete the On-Prem section in the Case-Specific worksheet | F21: =VLOOKUP($A21,'Institution Evaluation'!$A$56:$F$346,6,0)&"" | G21: End Table Data
A22: =VLOOKUP(LEFT($A23,4),'Auto Responses'!$N$4:$O$38,2,0)&"" -> Consulting Services | C22: Answer | D22: Additional Information | E22: Guidance | F22: Analyst Notes
A23: CONS-01 | B23: =VLOOKUP($A23,Questions!$A$2:$X$333,2,0) -> Will the consultant require access to the institution's network resources?* | C23: No | E23: =IF($C$18="No",'Auto Responses'!$A$5,IF($C23="Yes",VLOOKUP($A23,Questions!$A$2:$X$333,17,0)&"",IF($C23="No",VLOOKUP($A23,Questions!$A$2:$X$333,16,0)&"",VLOOKUP($A23,Questions!$A$2:$X$333,15,0)&""))) | F23: =VLOOKUP($A23,'Institution Evaluation'!$A$56:$F$346,6,0)&""
A24: CONS-02 | B24: =VLOOKUP($A24,Questions!$A$2:$X$333,2,0) -> Has the consultant received training on (sensitive, HIPAA, PCI, etc.) data handling?* | C24: No | E24: =IF($C$18="No",'Auto Responses'!$A$5,IF($C24="Yes",VLOOKUP($A24,Questions!$A$2:$X$333,17,0)&"",IF($C24="No",VLOOKUP($A24,Questions!$A$2:$X$333,16,0)&"",VLOOKUP($A24,Questions!$A$2:$X$333,15,0)&""))) | F24: =VLOOKUP($A24,'Institution Evaluation'!$A$56:$F$346,6,0)&""
A25: CONS-03 | B25: =VLOOKUP($A25,Questions!$A$2:$X$333,2,0) -> Is the data encrypted (at rest) while in the consultant's possession?* | C25: No | D25: All data will be transferred securely through the integration between the two systems. Coursedog will adhere to the institutioon's best practices if they choose to share design collateral and data outside of the integrtation. | E25: =IF($C$18="No",'Auto Responses'!$A$5,IF($C25="Yes",VLOOKUP($A25,Questions!$A$2:$X$333,17,0)&"",IF($C25="No",VLOOKUP($A25,Questions!$A$2:$X$333,16,0)&"",VLOOKUP($A25,Questions!$A$2:$X$333,15,0)&""))) | F25: =VLOOKUP($A25,'Institution Evaluation'!$A$56:$F$346,6,0)&""
A26: CONS-04 | B26: =VLOOKUP($A26,Questions!$A$2:$X$333,2,0) -> Can access be restricted based on source IP address?* | C26: No | E26: =IF($C$18="No",'Auto Responses'!$A$5,IF($C26="Yes",VLOOKUP($A26,Questions!$A$2:$X$333,17,0)&"",IF($C26="No",VLOOKUP($A26,Questions!$A$2:$X$333,16,0)&"",VLOOKUP($A26,Questions!$A$2:$X$333,15,0)&""))) | F26: =VLOOKUP($A26,'Institution Evaluation'!$A$56:$F$346,6,0)&""
A27: CONS-05 | B27: =VLOOKUP($A27,Questions!$A$2:$X$333,2,0) -> Will the consulting take place on-premises? | C27: No | D27: Coursedog typically conducts trainings and consulting remotely. However, there is an option for initial on-site end-user training if desired. On-site training may involve an additional charge to cover the cost of travel and additional resources required. | E27: =IF($C$18="No",'Auto Responses'!$A$5,IF($C27="Yes",VLOOKUP($A27,Questions!$A$2:$X$333,17,0)&"",IF($C27="No",VLOOKUP($A27,Questions!$A$2:$X$333,16,0)&"",VLOOKUP($A27,Questions!$A$2:$X$333,15,0)&""))) | F27: =VLOOKUP($A27,'Institution Evaluation'!$A$56:$F$346,6,0)&""
A28: CONS-06 | B28: =VLOOKUP($A28,Questions!$A$2:$X$333,2,0) -> Will the consultant require access to hardware in the institution's data centers? | C28: No | E28: =IF($C$18="No",'Auto Responses'!$A$5,IF($C28="Yes",VLOOKUP($A28,Questions!$A$2:$X$333,17,0)&"",IF($C28="No",VLOOKUP($A28,Questions!$A$2:$X$333,16,0)&"",VLOOKUP($A28,Questions!$A$2:$X$333,15,0)&""))) | F28: =VLOOKUP($A28,'Institution Evaluation'!$A$56:$F$346,6,0)&""
A29: CONS-07 | B29: =VLOOKUP($A29,Questions!$A$2:$X$333,2,0) -> Will the consultant require an account within the institution's domain (@*.edu)? | C29: No | E29: =IF($C$18="No",'Auto Responses'!$A$5,IF($C29="Yes",VLOOKUP($A29,Questions!$A$2:$X$333,17,0)&"",IF($C29="No",VLOOKUP($A29,Questions!$A$2:$X$333,16,0)&"",VLOOKUP($A29,Questions!$A$2:$X$333,15,0)&""))) | F29: =VLOOKUP($A29,'Institution Evaluation'!$A$56:$F$346,6,0)&""
A30: CONS-08 | B30: =VLOOKUP($A30,Questions!$A$2:$X$333,2,0) -> Will any data be transferred to the consultant's possession? | E30: =IF($C$18="No",'Auto Responses'!$A$5,IF($C30="Yes",VLOOKUP($A30,Questions!$A$2:$X$333,17,0)&"",IF($C30="No",VLOOKUP($A30,Questions!$A$2:$X$333,16,0)&"",VLOOKUP($A30,Questions!$A$2:$X$333,15,0)&""))) | F30: =VLOOKUP($A30,'Institution Evaluation'!$A$56:$F$346,6,0)&""
A31: CONS-09 | B31: =VLOOKUP($A31,Questions!$A$2:$X$333,2,0) -> Will the consultant need remote access to the institution's network or systems? | E31: =IF($C$18="No",'Auto Responses'!$A$5,IF($C31="Yes",VLOOKUP($A31,Questions!$A$2:$X$333,17,0)&"",IF($C31="No",VLOOKUP($A31,Questions!$A$2:$X$333,16,0)&"",VLOOKUP($A31,Questions!$A$2:$X$333,15,0)&""))) | F31: =VLOOKUP($A31,'Institution Evaluation'!$A$56:$F$346,6,0)&"" | G31: End Table Data
A32: =VLOOKUP(LEFT($A33,4),'Auto Responses'!$N$4:$O$38,2,0)&"" -> HIPAA Compliance | C32: Answer | D32: Additional Information | E32: Guidance | F32: Analyst Notes
A33: HIPA-01 | B33: =VLOOKUP($A33,Questions!$A$2:$X$333,2,0) -> Do your workforce members receive regular training related to the Health Insurance Portability and Accountability Act (HIPAA) Privacy and Security Rules and the HITECH Act?* | C33: No | D33: Coursedog does not have or require access to any HIPAA related data. | E33: =IF($C$19="No",'Auto Responses'!$A$7,IF($C33="Yes",VLOOKUP($A33,Questions!$A$2:$X$333,17,0)&"",IF($C33="No",VLOOKUP($A33,Questions!$A$2:$X$333,16,0)&"",VLOOKUP($A33,Questions!$A$2:$X$333,15,0)&""))) -> Based on the response to REQU-05 on the "START HERE" tab, this question does not apply to this product or service. | F33: =VLOOKUP($A33,'Institution Evaluation'!$A$56:$F$346,6,0)&""
A34: HIPA-02 | B34: =VLOOKUP($A34,Questions!$A$2:$X$333,2,0) -> Have you identified areas of risk?* | C34: No | D34: Coursedog does not have or require access to any HIPAA related data. | E34: =IF($C$19="No",'Auto Responses'!$A$7,IF($C34="Yes",VLOOKUP($A34,Questions!$A$2:$X$333,17,0)&"",IF($C34="No",VLOOKUP($A34,Questions!$A$2:$X$333,16,0)&"",VLOOKUP($A34,Questions!$A$2:$X$333,15,0)&""))) -> Based on the response to REQU-05 on the "START HERE" tab, this question does not apply to this product or service. | F34: =VLOOKUP($A34,'Institution Evaluation'!$A$56:$F$346,6,0)&""
A35: HIPA-03 | B35: =VLOOKUP($A35,Questions!$A$2:$X$333,2,0) -> Have the relevant policies/plans been tested?* | C35: No | D35: Coursedog does not have or require access to any HIPAA related data. | E35: =IF($C$19="No",'Auto Responses'!$A$7,IF($C35="Yes",VLOOKUP($A35,Questions!$A$2:$X$333,17,0)&"",IF($C35="No",VLOOKUP($A35,Questions!$A$2:$X$333,16,0)&"",VLOOKUP($A35,Questions!$A$2:$X$333,15,0)&""))) -> Based on the response to REQU-05 on the "START HERE" tab, this question does not apply to this product or service. | F35: =VLOOKUP($A35,'Institution Evaluation'!$A$56:$F$346,6,0)&""
A36: HIPA-04 | B36: =VLOOKUP($A36,Questions!$A$2:$X$333,2,0) -> Have you entered into a Business Associate Agreements with all subcontractors who may have access to protected health information (PHI)?* | C36: No | D36: Coursedog does not have or require access to any HIPAA related data. | E36: =IF($C$19="No",'Auto Responses'!$A$7,IF($C36="Yes",VLOOKUP($A36,Questions!$A$2:$X$333,17,0)&"",IF($C36="No",VLOOKUP($A36,Questions!$A$2:$X$333,16,0)&"",VLOOKUP($A36,Questions!$A$2:$X$333,15,0)&""))) -> Based on the response to REQU-05 on the "START HERE" tab, this question does not apply to this product or service. | F36: =VLOOKUP($A36,'Institution Evaluation'!$A$56:$F$346,6,0)&""
A37: HIPA-05 | B37: =VLOOKUP($A37,Questions!$A$2:$X$333,2,0) -> Do you monitor or receive information regarding changes in HIPAA regulations? | C37: No | D37: Coursedog does not have or require access to any HIPAA related data. | E37: =IF($C$19="No",'Auto Responses'!$A$7,IF($C37="Yes",VLOOKUP($A37,Questions!$A$2:$X$333,17,0)&"",IF($C37="No",VLOOKUP($A37,Questions!$A$2:$X$333,16,0)&"",VLOOKUP($A37,Questions!$A$2:$X$333,15,0)&""))) -> Based on the response to REQU-05 on the "START HERE" tab, this question does not apply to this product or service. | F37: =VLOOKUP($A37,'Institution Evaluation'!$A$56:$F$346,6,0)&""
A38: HIPA-06 | B38: =VLOOKUP($A38,Questions!$A$2:$X$333,2,0) -> Has your organization designated HIPAA Privacy and Security officers as required by the rules? | C38: No | D38: Coursedog does not have or require access to any HIPAA related data. | E38: =IF($C$19="No",'Auto Responses'!$A$7,IF($C38="Yes",VLOOKUP($A38,Questions!$A$2:$X$333,17,0)&"",IF($C38="No",VLOOKUP($A38,Questions!$A$2:$X$333,16,0)&"",VLOOKUP($A38,Questions!$A$2:$X$333,15,0)&""))) -> Based on the response to REQU-05 on the "START HERE" tab, this question does not apply to this product or service. | F38: =VLOOKUP($A38,'Institution Evaluation'!$A$56:$F$346,6,0)&""
A39: HIPA-07 | B39: =VLOOKUP($A39,Questions!$A$2:$X$333,2,0) -> Do you comply with the requirements of the Health Information Technology for Economic and Clinical Health Act (HITECH)? | C39: No | D39: Coursedog does not have or require access to any HIPAA related data. | E39: =IF($C$19="No",'Auto Responses'!$A$7,IF($C39="Yes",VLOOKUP($A39,Questions!$A$2:$X$333,17,0)&"",IF($C39="No",VLOOKUP($A39,Questions!$A$2:$X$333,16,0)&"",VLOOKUP($A39,Questions!$A$2:$X$333,15,0)&""))) -> Based on the response to REQU-05 on the "START HERE" tab, this question does not apply to this product or service. | F39: =VLOOKUP($A39,'Institution Evaluation'!$A$56:$F$346,6,0)&""
A40: HIPA-08 | B40: =VLOOKUP($A40,Questions!$A$2:$X$333,2,0) -> Have you conducted a risk analysis as required under the HIPAA Security Rule? | C40: No | D40: Coursedog does not have or require access to any HIPAA related data. | E40: =IF($C$19="No",'Auto Responses'!$A$7,IF($C40="Yes",VLOOKUP($A40,Questions!$A$2:$X$333,17,0)&"",IF($C40="No",VLOOKUP($A40,Questions!$A$2:$X$333,16,0)&"",VLOOKUP($A40,Questions!$A$2:$X$333,15,0)&""))) -> Based on the response to REQU-05 on the "START HERE" tab, this question does not apply to this product or service. | F40: =VLOOKUP($A40,'Institution Evaluation'!$A$56:$F$346,6,0)&""
A41: HIPA-09 | B41: =VLOOKUP($A41,Questions!$A$2:$X$333,2,0) -> Have you taken actions to mitigate the identified risks? | C41: No | D41: Coursedog does not have or require access to any HIPAA related data. | E41: =IF($C$19="No",'Auto Responses'!$A$7,IF($C41="Yes",VLOOKUP($A41,Questions!$A$2:$X$333,17,0)&"",IF($C41="No",VLOOKUP($A41,Questions!$A$2:$X$333,16,0)&"",VLOOKUP($A41,Questions!$A$2:$X$333,15,0)&""))) -> Based on the response to REQU-05 on the "START HERE" tab, this question does not apply to this product or service. | F41: =VLOOKUP($A41,'Institution Evaluation'!$A$56:$F$346,6,0)&""
A42: HIPA-10 | B42: =VLOOKUP($A42,Questions!$A$2:$X$333,2,0) -> Does your application require user and system administrator password changes at a frequency no greater than 90 days? | C42: No | D42: Coursedog does not have or require access to any HIPAA related data. | E42: =IF($C$19="No",'Auto Responses'!$A$7,IF($C42="Yes",VLOOKUP($A42,Questions!$A$2:$X$333,17,0)&"",IF($C42="No",VLOOKUP($A42,Questions!$A$2:$X$333,16,0)&"",VLOOKUP($A42,Questions!$A$2:$X$333,15,0)&""))) -> Based on the response to REQU-05 on the "START HERE" tab, this question does not apply to this product or service. | F42: =VLOOKUP($A42,'Institution Evaluation'!$A$56:$F$346,6,0)&""
A43: HIPA-11 | B43: =VLOOKUP($A43,Questions!$A$2:$X$333,2,0) -> Does your application require users to set their own password after an administrator reset or on first use of the account? | C43: No | D43: Coursedog does not have or require access to any HIPAA related data. | E43: =IF($C$19="No",'Auto Responses'!$A$7,IF($C43="Yes",VLOOKUP($A43,Questions!$A$2:$X$333,17,0)&"",IF($C43="No",VLOOKUP($A43,Questions!$A$2:$X$333,16,0)&"",VLOOKUP($A43,Questions!$A$2:$X$333,15,0)&""))) -> Based on the response to REQU-05 on the "START HERE" tab, this question does not apply to this product or service. | F43: =VLOOKUP($A43,'Institution Evaluation'!$A$56:$F$346,6,0)&""
A44: HIPA-12 | B44: =VLOOKUP($A44,Questions!$A$2:$X$333,2,0) -> Does your application lock out an account after a number of failed login attempts? | C44: No | D44: Coursedog does not have or require access to any HIPAA related data. | E44: =IF($C$19="No",'Auto Responses'!$A$7,IF($C44="Yes",VLOOKUP($A44,Questions!$A$2:$X$333,17,0)&"",IF($C44="No",VLOOKUP($A44,Questions!$A$2:$X$333,16,0)&"",VLOOKUP($A44,Questions!$A$2:$X$333,15,0)&""))) -> Based on the response to REQU-05 on the "START HERE" tab, this question does not apply to this product or service. | F44: =VLOOKUP($A44,'Institution Evaluation'!$A$56:$F$346,6,0)&""
... A54: HIPA-22 | B54: =VLOOKUP($A54,Questions!$A$2:$X$333,2,0) -> Does the application log administrative activity, such as user account access changes and password changes, including specific user, date/time of changes, and originating IP or device? | C54: No | D54: Coursedog does not have or require access to any HIPAA related data. | E54: =IF($C$19="No",'Auto Responses'!$A$7,IF($C54="Yes",VLOOKUP($A54,Questions!$A$2:$X$333,17,0)&"",IF($C54="No",VLOOKUP($A54,Questions!$A$2:$X$333,16,0)&"",VLOOKUP($A54,Questions!$A$2:$X$333,15,0)&""))) -> Based on the response to REQU-05 on the "START HERE" tab, this question does not apply to this product or service. | F54: =VLOOKUP($A54,'Institution Evaluation'!$A$56:$F$346,6,0)&""
A55: HIPA-23 | B55: =VLOOKUP($A55,Questions!$A$2:$X$333,2,0) -> How long does the application keep access/change logs? | E55: =IF($C$19="No",'Auto Responses'!$A$7,IF($C55="Yes",VLOOKUP($A55,Questions!$A$2:$X$333,17,0)&"",IF($C55="No",VLOOKUP($A55,Questions!$A$2:$X$333,16,0)&"",VLOOKUP($A55,Questions!$A$2:$X$333,15,0)&""))) -> Based on the response to REQU-05 on the "START HERE" tab, this question does not apply to this product or service. | F55: =VLOOKUP($A55,'Institution Evaluation'!$A$56:$F$346,6,0)&""
A56: HIPA-24 | B56: =VLOOKUP($A56,Questions!$A$2:$X$333,2,0) -> Can the application logs be archived? | C56: No | D56: Coursedog does not have or require access to any HIPAA related data. | E56: =IF($C$19="No",'Auto Responses'!$A$7,IF($C56="Yes",VLOOKUP($A56,Questions!$A$2:$X$333,17,0)&"",IF($C56="No",VLOOKUP($A56,Questions!$A$2:$X$333,16,0)&"",VLOOKUP($A56,Questions!$A$2:$X$333,15,0)&""))) -> Based on the response to REQU-05 on the "START HERE" tab, this question does not apply to this product or service. | F56: =VLOOKUP($A56,'Institution Evaluation'!$A$56:$F$346,6,0)&""
A57: HIPA-25 | B57: =VLOOKUP($A57,Questions!$A$2:$X$333,2,0) -> Can the application logs be saved externally? | C57: No | D57: Coursedog does not have or require access to any HIPAA related data. | E57: =IF($C$19="No",'Auto Responses'!$A$7,IF($C57="Yes",VLOOKUP($A57,Questions!$A$2:$X$333,17,0)&"",IF($C57="No",VLOOKUP($A57,Questions!$A$2:$X$333,16,0)&"",VLOOKUP($A57,Questions!$A$2:$X$333,15,0)&""))) -> Based on the response to REQU-05 on the "START HERE" tab, this question does not apply to this product or service. | F57: =VLOOKUP($A57,'Institution Evaluation'!$A$56:$F$346,6,0)&""
A58: HIPA-26 | B58: =VLOOKUP($A58,Questions!$A$2:$X$333,2,0) -> Do you have a disaster recovery plan and emergency mode operation plan? | C58: No | D58: Coursedog does not have or require access to any HIPAA related data. | E58: =IF($C$19="No",'Auto Responses'!$A$7,IF($C58="Yes",VLOOKUP($A58,Questions!$A$2:$X$333,17,0)&"",IF($C58="No",VLOOKUP($A58,Questions!$A$2:$X$333,16,0)&"",VLOOKUP($A58,Questions!$A$2:$X$333,15,0)&""))) -> Based on the response to REQU-05 on the "START HERE" tab, this question does not apply to this product or service. | F58: =VLOOKUP($A58,'Institution Evaluation'!$A$56:$F$346,6,0)&""
A59: HIPA-27 | B59: =VLOOKUP($A59,Questions!$A$2:$X$333,2,0) -> Can you provide a HIPAA compliance attestation document? | C59: No | D59: Coursedog does not have or require access to any HIPAA related data. | E59: =IF($C$19="No",'Auto Responses'!$A$7,IF($C59="Yes",VLOOKUP($A59,Questions!$A$2:$X$333,17,0)&"",IF($C59="No",VLOOKUP($A59,Questions!$A$2:$X$333,16,0)&"",VLOOKUP($A59,Questions!$A$2:$X$333,15,0)&""))) -> Based on the response to REQU-05 on the "START HERE" tab, this question does not apply to this product or service. | F59: =VLOOKUP($A59,'Institution Evaluation'!$A$56:$F$346,6,0)&""
A60: HIPA-28 | B60: =VLOOKUP($A60,Questions!$A$2:$X$333,2,0) -> Are you willing to enter into a Business Associate Agreement (BAA)? | C60: No | D60: Coursedog does not have or require access to any HIPAA related data. | E60: =IF($C$19="No",'Auto Responses'!$A$7,IF($C60="Yes",VLOOKUP($A60,Questions!$A$2:$X$333,17,0)&"",IF($C60="No",VLOOKUP($A60,Questions!$A$2:$X$333,16,0)&"",VLOOKUP($A60,Questions!$A$2:$X$333,15,0)&""))) -> Based on the response to REQU-05 on the "START HERE" tab, this question does not apply to this product or service. | F60: =VLOOKUP($A60,'Institution Evaluation'!$A$56:$F$346,6,0)&""
A61: HIPA-29 | B61: =VLOOKUP($A61,Questions!$A$2:$X$333,2,0) -> Do your data backup and retention policies and practices meet HIPAA requirements? | C61: No | D61: Coursedog does not have or require access to any HIPAA related data. | E61: =IF($C$19="No",'Auto Responses'!$A$7,IF($C61="Yes",VLOOKUP($A61,Questions!$A$2:$X$333,17,0)&"",IF($C61="No",VLOOKUP($A61,Questions!$A$2:$X$333,16,0)&"",VLOOKUP($A61,Questions!$A$2:$X$333,15,0)&""))) -> Based on the response to REQU-05 on the "START HERE" tab, this question does not apply to this product or service. | F61: =VLOOKUP($A61,'Institution Evaluation'!$A$56:$F$346,6,0)&"" | G61: End Table Data
A62: =VLOOKUP(LEFT($A63,4),'Auto Responses'!$N$4:$O$38,2,0)&"" -> Payment Card Industry Data Security Standard (PCI DSS) | C62: Answer | D62: Additional Information | E62: Guidance | F62: Analyst Notes
A63: PCID-01 | B63: =VLOOKUP($A63,Questions!$A$2:$X$333,2,0) -> Do you have a current, executed within the past year, Attestation of Compliance (AoC) or Report on Compliance (RoC)?* | C63: No | D63: Coursedog does not process Credit Card payments. | E63: =IF($C$20="No",'Auto Responses'!$A$8,IF($C63="Yes",VLOOKUP($A63,Questions!$A$2:$X$333,17,0)&"",IF($C63="No",VLOOKUP($A63,Questions!$A$2:$X$333,16,0)&"",VLOOKUP($A63,Questions!$A$2:$X$333,15,0)&""))) -> Based on the response to REQU-06 on the "START HERE" tab, this question does not apply to this product or service. | F63: =VLOOKUP($A63,'Institution Evaluation'!$A$56:$F$346,6,0)&""
A64: PCID-02 | B64: =VLOOKUP($A64,Questions!$A$2:$X$333,2,0) -> Is the application listed as an approved Payment Application Data Security Standard (PA-DSS) application?* | C64: No | D64: Coursedog does not process Credit Card payments. | E64: =IF($C$20="No",'Auto Responses'!$A$8,IF($C64="Yes",VLOOKUP($A64,Questions!$A$2:$X$333,17,0)&"",IF($C64="No",VLOOKUP($A64,Questions!$A$2:$X$333,16,0)&"",VLOOKUP($A64,Questions!$A$2:$X$333,15,0)&""))) -> Based on the response to REQU-06 on the "START HERE" tab, this question does not apply to this product or service. | F64: =VLOOKUP($A64,'Institution Evaluation'!$A$56:$F$346,6,0)&""
A65: PCID-03 | B65: =VLOOKUP($A65,Questions!$A$2:$X$333,2,0) -> Does the system or solutions use a third party to collect, store, process, or transmit cardholder (payment/credit/debt card) data?* | C65: No | D65: Coursedog does not process Credit Card payments. | E65: =IF($C$20="No",'Auto Responses'!$A$8,IF($C65="Yes",VLOOKUP($A65,Questions!$A$2:$X$333,17,0)&"",IF($C65="No",VLOOKUP($A65,Questions!$A$2:$X$333,16,0)&"",VLOOKUP($A65,Questions!$A$2:$X$333,15,0)&""))) -> Based on the response to REQU-06 on the "START HERE" tab, this question does not apply to this product or service. | F65: =VLOOKUP($A65,'Institution Evaluation'!$A$56:$F$346,6,0)&""
A66: PCID-04 | B66: =VLOOKUP($A66,Questions!$A$2:$X$333,2,0) -> Do your systems or solutions store, process, or transmit cardholder (payment/credit/debt card) data? | C66: No | D66: Coursedog does not process Credit Card payments. | E66: =IF($C$20="No",'Auto Responses'!$A$8,IF($C66="Yes",VLOOKUP($A66,Questions!$A$2:$X$333,17,0)&"",IF($C66="No",VLOOKUP($A66,Questions!$A$2:$X$333,16,0)&"",VLOOKUP($A66,Questions!$A$2:$X$333,15,0)&""))) -> Based on the response to REQU-06 on the "START HERE" tab, this question does not apply to this product or service. | F66: =VLOOKUP($A66,'Institution Evaluation'!$A$56:$F$346,6,0)&""
A67: PCID-05 | B67: =VLOOKUP($A67,Questions!$A$2:$X$333,2,0) -> Are you compliant with the Payment Card Industry Data Security Standard (PCI DSS)? | C67: No | D67: Coursedog does not process Credit Card payments. | E67: =IF($C$20="No",'Auto Responses'!$A$8,IF($C67="Yes",VLOOKUP($A67,Questions!$A$2:$X$333,17,0)&"",IF($C67="No",VLOOKUP($A67,Questions!$A$2:$X$333,16,0)&"",VLOOKUP($A67,Questions!$A$2:$X$333,15,0)&""))) -> Based on the response to REQU-06 on the "START HERE" tab, this question does not apply to this product or service. | F67: =VLOOKUP($A67,'Institution Evaluation'!$A$56:$F$346,6,0)&""
A68: PCID-06 | B68: =VLOOKUP($A68,Questions!$A$2:$X$333,2,0) -> Are you classified as a service provider? | C68: No | D68: Coursedog does not process Credit Card payments. | E68: =IF($C$20="No",'Auto Responses'!$A$8,IF($C68="Yes",VLOOKUP($A68,Questions!$A$2:$X$333,17,0)&"",IF($C68="No",VLOOKUP($A68,Questions!$A$2:$X$333,16,0)&"",VLOOKUP($A68,Questions!$A$2:$X$333,15,0)&""))) -> Based on the response to REQU-06 on the "START HERE" tab, this question does not apply to this product or service. | F68: =VLOOKUP($A68,'Institution Evaluation'!$A$56:$F$346,6,0)&""
A69: PCID-07 | B69: =VLOOKUP($A69,Questions!$A$2:$X$333,2,0) -> Are you on the list of Visa approved service providers? | C69: No | D69: Coursedog does not process Credit Card payments. | E69: =IF($C$20="No",'Auto Responses'!$A$8,IF($C69="Yes",VLOOKUP($A69,Questions!$A$2:$X$333,17,0)&"",IF($C69="No",VLOOKUP($A69,Questions!$A$2:$X$333,16,0)&"",VLOOKUP($A69,Questions!$A$2:$X$333,15,0)&""))) -> Based on the response to REQU-06 on the "START HERE" tab, this question does not apply to this product or service. | F69: =VLOOKUP($A69,'Institution Evaluation'!$A$56:$F$346,6,0)&""
A70: PCID-08 | B70: =VLOOKUP($A70,Questions!$A$2:$X$333,2,0) -> Are you classified as a merchant? If so, what level (1, 2, 3, 4)? | C70: No | D70: Coursedog does not process Credit Card payments. | E70: =IF($C$20="No",'Auto Responses'!$A$8,IF($C70="Yes",VLOOKUP($A70,Questions!$A$2:$X$333,17,0)&"",IF($C70="No",VLOOKUP($A70,Questions!$A$2:$X$333,16,0)&"",VLOOKUP($A70,Questions!$A$2:$X$333,15,0)&""))) -> Based on the response to REQU-06 on the "START HERE" tab, this question does not apply to this product or service. | F70: =VLOOKUP($A70,'Institution Evaluation'!$A$56:$F$346,6,0)&""
A71: PCID-09 | B71: =VLOOKUP($A71,Questions!$A$2:$X$333,2,0) -> Describe the architecture employed by the system to verify and authorize credit card transactions. | C71: No | D71: Coursedog does not process Credit Card payments. | E71: =IF($C$20="No",'Auto Responses'!$A$8,IF($C71="Yes",VLOOKUP($A71,Questions!$A$2:$X$333,17,0)&"",IF($C71="No",VLOOKUP($A71,Questions!$A$2:$X$333,16,0)&"",VLOOKUP($A71,Questions!$A$2:$X$333,15,0)&""))) -> Based on the response to REQU-06 on the "START HERE" tab, this question does not apply to this product or service. | F71: =VLOOKUP($A71,'Institution Evaluation'!$A$56:$F$346,6,0)&""
A72: PCID-10 | B72: =VLOOKUP($A72,Questions!$A$2:$X$333,2,0) -> What payment processors/gateways does the system support? | C72: No | D72: Coursedog does not process Credit Card payments. | E72: =IF($C$20="No",'Auto Responses'!$A$8,IF($C72="Yes",VLOOKUP($A72,Questions!$A$2:$X$333,17,0)&"",IF($C72="No",VLOOKUP($A72,Questions!$A$2:$X$333,16,0)&"",VLOOKUP($A72,Questions!$A$2:$X$333,15,0)&""))) -> Based on the response to REQU-06 on the "START HERE" tab, this question does not apply to this product or service. | F72: =VLOOKUP($A72,'Institution Evaluation'!$A$56:$F$346,6,0)&""
A73: PCID-11 | B73: =VLOOKUP($A73,Questions!$A$2:$X$333,2,0) -> Can the application be installed in a PCI DSS–compliant manner? | C73: No | D73: Coursedog does not process Credit Card payments. | E73: =IF($C$20="No",'Auto Responses'!$A$8,IF($C73="Yes",VLOOKUP($A73,Questions!$A$2:$X$333,17,0)&"",IF($C73="No",VLOOKUP($A73,Questions!$A$2:$X$333,16,0)&"",VLOOKUP($A73,Questions!$A$2:$X$333,15,0)&""))) -> Based on the response to REQU-06 on the "START HERE" tab, this question does not apply to this product or service. | F73: =VLOOKUP($A73,'Institution Evaluation'!$A$56:$F$346,6,0)&""
A74: PCID-12 | B74: =VLOOKUP($A74,Questions!$A$2:$X$333,2,0) -> Include documentation describing the system's abilities to comply with the PCI DSS and any features or capabilities of the system that must be added or changed in order to operate in compliance with the standards. | E74: =IF($C$20="No",'Auto Responses'!$A$8,IF($C74="Yes",VLOOKUP($A74,Questions!$A$2:$X$333,17,0)&"",IF($C74="No",VLOOKUP($A74,Questions!$A$2:$X$333,16,0)&"",VLOOKUP($A74,Questions!$A$2:$X$333,15,0)&""))) -> Based on the response to REQU-06 on the "START HERE" tab, this question does not apply to this product or service. | F74: =VLOOKUP($A74,'Institution Evaluation'!$A$56:$F$346,6,0)&"" | G74: End Table Data
A75: =VLOOKUP(LEFT($A76,4),'Auto Responses'!$N$4:$O$38,2,0)&"" -> On-Premises Data Solutions | C75: Answer | D75: Additional Information | E75: Guidance | F75: Analyst Notes
A76: OPEM-01 | B76: =VLOOKUP($A76,Questions!$A$2:$X$333,2,0) -> Do you support role-based access control (RBAC) for system administrators? | C76: No | D76: Coursedog is a SaSS platform and is not on-premises. | E76: =IF($C$21="No",'Auto Responses'!$A$9,IF($C76="Yes",VLOOKUP($A76,Questions!$A$2:$X$333,17,0)&"",IF($C76="No",VLOOKUP($A76,Questions!$A$2:$X$333,16,0)&"",VLOOKUP($A76,Questions!$A$2:$X$333,15,0)&""))) -> Based on the response to REQU-07 on the "START HERE" tab, this question does not apply to this product or service. | F76: =VLOOKUP($A76,'Institution Evaluation'!$A$56:$F$346,6,0)&""
A77: OPEM-02 | B77: =VLOOKUP($A77,Questions!$A$2:$X$333,2,0) -> Can your employees access customer systems remotely? | C77: No | D77: Coursedog is a SaSS platform and is not on-premises. | E77: =IF($C$21="No",'Auto Responses'!$A$9,IF($C77="Yes",VLOOKUP($A77,Questions!$A$2:$X$333,17,0)&"",IF($C77="No",VLOOKUP($A77,Questions!$A$2:$X$333,16,0)&"",VLOOKUP($A77,Questions!$A$2:$X$333,15,0)&""))) -> Based on the response to REQU-07 on the "START HERE" tab, this question does not apply to this product or service. | F77: =VLOOKUP($A77,'Institution Evaluation'!$A$56:$F$346,6,0)&""
A78: OPEM-03 | B78: =VLOOKUP($A78,Questions!$A$2:$X$333,2,0) -> Can you provide overall system and/or application architecture diagrams including a full description of the data communications architecture for all components of the system? | C78: No | D78: Coursedog is a SaSS platform and is not on-premises. | E78: =IF($C$21="No",'Auto Responses'!$A$9,IF($C78="Yes",VLOOKUP($A78,Questions!$A$2:$X$333,17,0)&"",IF($C78="No",VLOOKUP($A78,Questions!$A$2:$X$333,16,0)&"",VLOOKUP($A78,Questions!$A$2:$X$333,15,0)&""))) -> Based on the response to REQU-07 on the "START HERE" tab, this question does not apply to this product or service. | F78: =VLOOKUP($A78,'Institution Evaluation'!$A$56:$F$346,6,0)&""
A79: OPEM-04 | B79: =VLOOKUP($A79,Questions!$A$2:$X$333,2,0) -> Do you require remote management of the system? | C79: No | D79: Coursedog is a SaSS platform and is not on-premises. | E79: =IF($C$21="No",'Auto Responses'!$A$9,IF($C79="Yes",VLOOKUP($A79,Questions!$A$2:$X$333,17,0)&"",IF($C79="No",VLOOKUP($A79,Questions!$A$2:$X$333,16,0)&"",VLOOKUP($A79,Questions!$A$2:$X$333,15,0)&""))) -> Based on the response to REQU-07 on the "START HERE" tab, this question does not apply to this product or service. | F79: =VLOOKUP($A79,'Institution Evaluation'!$A$56:$F$346,6,0)&""
A80: OPEM-05 | B80: =VLOOKUP($A80,Questions!$A$2:$X$333,2,0) -> Are your remote actions and changes logged or otherwise visible to the campus? (IF YES to OPAP-06) | C80: No | D80: Coursedog is a SaSS platform and is not on-premises. | E80: =IF($C$21="No",'Auto Responses'!$A$9,IF($C80="Yes",VLOOKUP($A80,Questions!$A$2:$X$333,17,0)&"",IF($C80="No",VLOOKUP($A80,Questions!$A$2:$X$333,16,0)&"",VLOOKUP($A80,Questions!$A$2:$X$333,15,0)&""))) -> Based on the response to REQU-07 on the "START HERE" tab, this question does not apply to this product or service. | F80: =VLOOKUP($A80,'Institution Evaluation'!$A$56:$F$346,6,0)&""
A81: OPEM-06 | B81: =VLOOKUP($A81,Questions!$A$2:$X$333,2,0) -> If you maintain remote access to the system, will you handle data in a FERPA-compliant manner? | C81: No | D81: Coursedog is a SaSS platform and is not on-premises. | E81: =IF($C$21="No",'Auto Responses'!$A$9,IF($C81="Yes",VLOOKUP($A81,Questions!$A$2:$X$333,17,0)&"",IF($C81="No",VLOOKUP($A81,Questions!$A$2:$X$333,16,0)&"",VLOOKUP($A81,Questions!$A$2:$X$333,15,0)&""))) -> Based on the response to REQU-07 on the "START HERE" tab, this question does not apply to this product or service. | F81: =VLOOKUP($A81,'Institution Evaluation'!$A$56:$F$346,6,0)&""
A82: OPEM-07 | B82: =VLOOKUP($A82,Questions!$A$2:$X$333,2,0) -> Do you support campus status monitoring through SNMPv3 or other means? | C82: No | D82: Coursedog is a SaSS platform and is not on-premises. | E82: =IF($C$21="No",'Auto Responses'!$A$9,IF($C82="Yes",VLOOKUP($A82,Questions!$A$2:$X$333,17,0)&"",IF($C82="No",VLOOKUP($A82,Questions!$A$2:$X$333,16,0)&"",VLOOKUP($A82,Questions!$A$2:$X$333,15,0)&""))) -> Based on the response to REQU-07 on the "START HERE" tab, this question does not apply to this product or service. | F82: =VLOOKUP($A82,'Institution Evaluation'!$A$56:$F$346,6,0)&""
A83: OPEM-08 | B83: =VLOOKUP($A83,Questions!$A$2:$X$333,2,0) -> Describe or provide a reference to any other safeguards used to monitor for malicious activity. | E83: =IF($C$21="No",'Auto Responses'!$A$9,IF($C83="Yes",VLOOKUP($A83,Questions!$A$2:$X$333,17,0)&"",IF($C83="No",VLOOKUP($A83,Questions!$A$2:$X$333,16,0)&"",VLOOKUP($A83,Questions!$A$2:$X$333,15,0)&""))) -> Based on the response to REQU-07 on the "START HERE" tab, this question does not apply to this product or service. | F83: =VLOOKUP($A83,'Institution Evaluation'!$A$56:$F$346,6,0)&""
A84: OPEM-09 | B84: =VLOOKUP($A84,Questions!$A$2:$X$333,2,0) -> Describe how long your organization has conducted business in this area. | E84: =IF($C$21="No",'Auto Responses'!$A$9,IF($C84="Yes",VLOOKUP($A84,Questions!$A$2:$X$333,17,0)&"",IF($C84="No",VLOOKUP($A84,Questions!$A$2:$X$333,16,0)&"",VLOOKUP($A84,Questions!$A$2:$X$333,15,0)&""))) -> Based on the response to REQU-07 on the "START HERE" tab, this question does not apply to this product or service. | F84: =VLOOKUP($A84,'Institution Evaluation'!$A$56:$F$346,6,0)&""
A85: OPEM-10 | B85: =VLOOKUP($A85,Questions!$A$2:$X$333,2,0) -> Do you have existing higher education customers? | C85: No | D85: Coursedog is a SaSS platform and is not on-premises. | E85: =IF($C$21="No",'Auto Responses'!$A$9,IF($C85="Yes",VLOOKUP($A85,Questions!$A$2:$X$333,17,0)&"",IF($C85="No",VLOOKUP($A85,Questions!$A$2:$X$333,16,0)&"",VLOOKUP($A85,Questions!$A$2:$X$333,15,0)&""))) -> Based on the response to REQU-07 on the "START HERE" tab, this question does not apply to this product or service. | F85: =VLOOKUP($A85,'Institution Evaluation'!$A$56:$F$346,6,0)&"" | G85: End Table Data
A86: Copyright © 2025 EDUCAUSE
A88: =#REF! -> #REF!
A89: =#REF! -> #REF!
A90: =#REF! -> #REF!
A91: =#REF! -> #REF!
A92: =#REF! -> #REF!
A93: =#REF! -> #REF!
A94: =#REF! -> #REF!

Sheet AI
A1: Cells contained in this worksheet may contain cells with dropdown lists as well as autopopulated formulas.
A2: HECVAT Solution Provider Response - AI | F2: ='Auto Responses'!$A$36 -> Version 4.04
A3: Date Completed | C3: ='START HERE'!$C$3 -> 45933
A4: Instructions for Solution Providers
A5: =HLOOKUP($A$4,'Auto Responses'!$D$2:$D$8,2,0)&"" -> 1. Complete the "Start Here" tab and review the "Required Questions" guidance to find the other sections are required for your product or service.
A6: =HLOOKUP($A$4,'Auto Responses'!$D$2:$D$8,3,0)&"" -> 2. Complete the "Organization" tab and the applicable questions in each of the next 5 tabs (Product through Privacy) that apply, based on your answers to the "Required Questions."
A7: =HLOOKUP($A$4,'Auto Responses'!$D$2:$D$8,4,0)&"" -> 3. Guidance in column E may change based on your answers to prompt details in "Additional Information." If leaving an answer blank, you must also state why in "Additional Information".
A8: =HLOOKUP($A$4,'Auto Responses'!$D$2:$D$8,5,0)&"" -> 4. DO NOT complete any fields in the "Evaluation" sheets or the "Analyst Notes" column.
A9: =HLOOKUP($A$4,'Auto Responses'!$D$2:$D$8,6,0)&"" -> 5. Return the completed file to institutions.
A10: =HLOOKUP($A$4,'Auto Responses'!$D$2:$D$8,7,0)&"" -> * Denotes critical questions. Critical questions are those deemed most important to institutions by higher education volunteers.
A11: =HLOOKUP($A$4,'Auto Responses'!$D$2:$D$9,8,0)&"" -> For full instructions, please visit educause.edu/HECVAT
A12: General Information | C12: Answer
A13: GNRL-01 | B13: Solution Provider Name | C13: Coursedog
A14: GNRL-02 | B14: Solution Name | C14: Coursedog
A15: GNRL-03 | B15: Solution Description | C15: Coursedog is a SaaS platform designed to streamline curriculum, catalog, and scheduling management for higher education institutions, offering intuitive tools, insightful analytics, and seamless integration without requiring IT involvement.
A16: GNRL-08 | B16: Country of Company Headquarters | C16: USA
A17: Required Questions | C17: Answer | D17: Additional Information | E17: Guidance | F17: Analyst Notes
A18: REQU-04 | B18: Does your solution have AI features, or are there plans to implement AI features in the next 12 months? | C18: Yes | D18: Coursedog has implemented AI features including OpenAI integration for chat completions and embeddings, AI Hub product for controlling AI operations, merge error solutions with AI-powered recommendations, and an agentic chat assistant called "Cassie". | G18: End Table Data
A19: AI Qualifying Questions | C19: Answer | D19: Additional Information | E19: Guidance | F19: Analyst Notes
A20: AIQU-01 | B20: Does your solution leverage machine learning (ML) or do you plan to do so in the next 12 months? | C20: Yes | D20: Coursedog leverages machine learning through OpenAI's models for text generation, embeddings, and chat completions. The system uses ML for generating recommendations and processing educational data.
A21: AIQU-02 | B21: Does your solution leverage a large language model (LLM) or do you plan to do so in the next 12 months? | C21: Yes | D21: Coursedog integrates with OpenAI's large language models including GPT models for chat completions and text generation capabilities through the AI Hub and agentic chat features. | G21: End Table Data
A22: General AI Questions | C22: Answer | D22: Additional Information | E22: Guidance | F22: Analyst Notes
A23: AIGN-01 | B23: Does your solution have an AI risk model when developing or implementing your solution's AI model?* | C23: Yes | D23: Coursedog implements rate limiting for AI API calls, has structured error handling, and follows responsible AI development practices through component-based AI workflows with proper validation.
A24: AIGN-02 | B24: Can your solution's AI features be disabled by tenant and/or user?* | C24: Yes | D24: AI features are implemented as optional components and can be controlled through the AI Hub product, allowing for granular control over AI functionality at the tenant level.
A25: AIGN-03 | B25: Have your staff completed responsible AI training?* | C25: Yes | D25: Coursedog development team follows responsible AI practices as evidenced by the structured approach to AI implementation with proper rate limiting, error handling, and security considerations.
A26: AIGN-04 | B26: Please describe the capabilities of your solution's AI features. | C26: Yes | D26: Coursedog's AI capabilities include: 1) OpenAI and Anthropic integration for chat completions and text generation 2) Embedding generation for semantic search and similarity analysis 3) AI-powered merge error recommendations for integration issues 4) Agentic chat assistant "Cassie" for interactive user queries 5) Component-based AI pipeline system for complex workflows 6) Rate limiting and retry mechanisms for reliable AI operations.
A27: AIGN-05 | B27: Does your solution support business rules to protect sensitive data from being ingested by the AI model? | C27: Yes | D27: Coursedog implements data validation schemas, structured input/output handling, and follows security best practices to protect sensitive educational data from inappropriate AI model ingestion. | G27: End Table Data
A28: AI Policy | C28: Answer | D28: Additional Information | E28: Guidance | F28: Analyst Notes
A29: AIPL-01 | B29: Are your AI developer's policies, processes, procedures, and practices across the organization related to the mapping, measuring, and managing of AI risks conspicuously posted, unambiguous, and implemented effectively?* | C29: Yes | D29: Coursedog follows structured AI development practices with clear component interfaces, error handling, rate limiting, and security considerations implemented throughout the AI system architecture. | E29: Looking for responsible AI development policies and practices.
A30: AIPL-02 | B30: Have you identified and measured AI risks?* | C30: Yes | D30: Coursedog has implemented risk mitigation through rate limiting, structured error handling, input validation, and component-based architecture to manage AI-related risks. | E30: Looking for documentation and policies around measuring AI risk.
A31: AIPL-03 | B31: In the event of an incident, can your solution's AI features be disabled in a timely manner?* | C31: Yes | D31: AI features are implemented as modular components that can be disabled through the AI Hub control system and component cancellation mechanisms. | E31: Looking for incident response procedure for shutting down and re-enabling model features due to a security event. Please provide the amount of time it would take to disable your solution's AI feature(s).
A32: AIPL-04 | B32: If disabled because of an incident, can your solution's AI features be re-enabled in a timely manner?* | C32: Yes | D32: The modular component architecture allows for quick re-enablement of AI features once issues are resolved, with proper validation and testing procedures. | E32: Looking for incident response procedure for shutting down and re-enabling model features due to a security event. Please provide the amount of time it would take to renable your solution's AI feature(s).
A33: AIPL-05 | B33: Do you have documented technical and procedural processes to address potential negative impacts of AI as described by the AI Risk Management Framework (RMF)? | C33: Yes | D33: Coursedog implements technical safeguards including rate limiting, error handling, input validation, and structured component workflows to address potential negative impacts of AI usage. | E33: Looking for harm reduction as part of responsible AI development per NIST AI RMF, page 25. | G33: End Table Data
A34: AI Data Security | C34: Answer | D34: Additional Information | E34: Guidance | F34: Analyst Notes
A35: AISC-01 | B35: If sensitive data is introduced to your solution's AI model, can the data be removed from the AI model by request?* | C35: No | D35: Coursedog uses third-party AI services (OpenAI and Anthropic) where data removal from the underlying models is not directly controllable. However, Coursedog implements data protection measures to prevent sensitive data from being inappropriately sent to AI models. | E35: Looking for the ability to scrub sensitive insitutional data from your solution's AI model.
A36: AISC-02 | B36: Is user input data used to influence your solution's AI model?* | C36: No | D36: User input is processed through AI models for generating responses but is not used to train or modify the underlying AI models. Coursedog uses pre-trained models from OpenAI and Anthropic. | E36: Looking for protection of organizational data entered as inputs in a solution's AI feature(s).
A37: AISC-03 | B37: Do you provide logging for your solution's AI feature(s) that includes user, date, and action taken?* | C37: Yes | D37: Coursedog implements comprehensive logging through Winston-based structured logging with contextual information including user actions and AI operations. | E37: Looking for the ability to audit AI feature(s) for a regulated data audit or incident response.
A38: AISC-04 | B38: Please describe how you validate user inputs. | D38: Coursedog validates user inputs through TypeBox schema validation, component input/output schema checking, and structured data validation before processing through AI models. | E38: Looking for how the solution is checked for input anomalies, patterns, and malicious input rejection.
A39: AISC-05 | B39: Do you plan for and mitigate supply-chain risk related to your AI features? | C39: Yes | D39: Coursedog mitigates supply-chain risks through rate limiting, error handling, fallback mechanisms, and careful management of third-party AI service dependencies. | E39: Looking for SAST (Static Application Security Testing) and SBOM (Software Bill of Materials) attestations. | G39: End Table Data
A40: AI Machine Learning | C40: Answer | D40: Additional Information | E40: Guidance | F40: Analyst Notes
A41: AIML-01 | B41: Do you separate ML training data from your ML solution data?* | C41: No | D41: Coursedog does not train custom ML models. The solution uses pre-trained models from OpenAI and Anthropic, so training data separation is not applicable. | E41: Looking for protection of training data.
A42: AIML-02 | B42: Do you authenticate and verify your ML model's feedback?* | C42: No | D42: Coursedog uses pre-trained OpenAI models and does not implement custom model training or feedback loops that would require authentication and verification. | E42: Looking for authentication and verification of feedback of the ML model to address the risk of model skewing.
A43: AIML-03 | B43: Is your ML training data vetted, validated, and verified before training the solution's AI model? | C43: No | D43: Coursedog does not train custom ML models. The solution relies on OpenAI and Anthropic's pre-trained models. | E43: Looking for policies/procedures about validating and verifying any data used to train the model through validation checks and employing multiple data labelers to validate the accuracy of the data labeling.
A44: AIML-04 | B44: Is your ML training data monitored and audited? | C44: No | D44: Not applicable as Coursedog does not maintain custom ML training data | E44: Looking for how you reduce the risk of compromising training data.
A45: AIML-05 | B45: Have you limited access to your ML training data to only staff with an explicit business need? | C45: No | D45: Not applicable as Coursedog does not maintain custom ML training data. | E45: Looking for limited access to training data.
A46: AIML-06 | B46: Have you implemented adversarial training or other model defense mechanisms to protect your ML-related features? | C46: No | D46: Coursedog relies on OpenAI and Anthropic's model security measures. The solution implements application-level protections through input validation and rate limiting rather than model-level defenses. | E46: Looking for adversarial training or models that incorporate other defense mechanisms.
A47: AIML-07 | B47: Do you make your ML model transparent through documentation and log inputs and outputs? | C47: Yes | D47: Coursedog provides comprehensive logging of AI operations including inputs and outputs, and maintains documentation of AI component interfaces and usage patterns. | E47: Looking for model transparency, logging of inputs and outputs, explainations for the model's predictions, and allowing the users to inspect the model's internal representations.
A48: AIML-08 | B48: Do you watermark your ML training data? | C48: No | D48: Additional Information: Not applicable as Coursedog does not maintain custom ML training data. | E48: Looking for watermarking of training data to aid in your incident response. | G48: End Table Data
A49: AI Large Language Model (LLM) | C49: Answer | D49: Additional Information | E49: Guidance | F49: Analyst Notes
A50: AILM-01 | B50: Do you limit your solution's LLM privileges by default?* | C50: Yes | D50: Coursedog implements rate limiting, structured input validation, and controlled access to LLM features through the AI Hub system to limit privileges by default. | E50: Based on the response to AIQU-02 on the "START HERE" tab, this question does not apply to this product or service.
A51: AILM-02 | B51: Is your LLM training data vetted, validated, and verified before training the solution's AI model?* | C51: N/A | D51: Coursedog uses OpenAI and Anthropic's pre-trained LLMs and does not train custom language models. | E51: Based on the response to AIQU-02 on the "START HERE" tab, this question does not apply to this product or service.
A52: AILM-03 | B52: Do any actions taken by your solution's LLM features or plugins require human intervention?* | C52: Yes | D52: AI-generated recommendations and responses are presented to users for review and action. The system does not automatically execute actions based solely on LLM outputs. | E52: Based on the response to AIQU-02 on the "START HERE" tab, this question does not apply to this product or service.
A53: AILM-04 | B53: Do you limit multiple LLM model plugins being called as part of a single input?* | C53: Yes | D53: Coursedog's component-based architecture controls AI model usage and can limit concurrent or multiple model calls through the pipeline system. | E53: Based on the response to AIQU-02 on the "START HERE" tab, this question does not apply to this product or service.
A54: AILM-05 | B54: Do you limit your solution's LLM resource use per request, per step, and per action? | C54: Yes | D54: Coursedog implements comprehensive rate limiting for AI API calls including request limits, token usage tracking, and resource management through the OpenAI and Anthropic rate limiter component. | E54: Based on the response to AIQU-02 on the "START HERE" tab, this question does not apply to this product or service.
A55: AILM-06 | B55: Do you leverage LLM model tuning or other model validation mechanisms? | C55: No | D55: Coursedog uses OpenAI and Anthropic's pre-trained models without custom tuning. Validation is performed at the application level through input/output schema validation and structured component workflows. | E55: Based on the response to AIQU-02 on the "START HERE" tab, this question does not apply to this product or service. | G55: End Table Data
A56: Copyright © 2025 EDUCAUSE | E56: End of worksheet
A59: =#REF! -> #REF!
A60: =#REF! -> #REF!
A61: =#REF! -> #REF!
A62: =#REF! -> #REF!
A63: =#REF! -> #REF!
A64: =#REF! -> #REF!
A65: =#REF! -> #REF!

Sheet Privacy
A1: Cells contained in this worksheet may contain cells with dropdown lists as well as autopopulated formulas.
A2: HECVAT Solution Provider Response - Privacy | F2: ='Auto Responses'!$A$36 -> Version 4.04
A3: Date Completed | C3: ='START HERE'!$C$3 -> 45933
A4: Instructions for Solution Providers | B4: Yes
A5: =HLOOKUP($A$4,'Auto Responses'!$D$2:$D$8,2,0)&"" -> 1. Complete the "Start Here" tab and review the "Required Questions" guidance to find the other sections are required for your product or service. | B5: Yes
A6: =HLOOKUP($A$4,'Auto Responses'!$D$2:$D$8,3,0)&"" -> 2. Complete the "Organization" tab and the applicable questions in each of the next 5 tabs (Product through Privacy) that apply, based on your answers to the "Required Questions." | B6: Yes
A7: =HLOOKUP($A$4,'Auto Responses'!$D$2:$D$8,4,0)&"" -> 3. Guidance in column E may change based on your answers to prompt details in "Additional Information." If leaving an answer blank, you must also state why in "Additional Information". | B7: https://www.coursedog.com/privacy-policy
A8: =HLOOKUP($A$4,'Auto Responses'!$D$2:$D$8,5,0)&"" -> 4. DO NOT complete any fields in the "Evaluation" sheets or the "Analyst Notes" column. | B8: Coursedog collects personal data including email, name, phone, address. Uses third-party service providers like Google Analytics. Transfers data to US. Implements security measures though acknowledges no method is 100% secure. Does not knowingly collect data from children under 18. Contact: 228 Park Avenue S, PMB 70159, New York, NY 10003
A9: =HLOOKUP($A$4,'Auto Responses'!$D$2:$D$8,6,0)&"" -> 5. Return the completed file to institutions. | B9: Information not publicly available
A10: =HLOOKUP($A$4,'Auto Responses'!$D$2:$D$8,7,0)&"" -> * Denotes critical questions. Critical questions are those deemed most important to institutions by higher education volunteers. | B10: Information not publicly available
A11: =HLOOKUP($A$4,'Auto Responses'!$D$2:$D$9,8,0)&"" -> For full instructions, please visit educause.edu/HECVAT | B11: Information not publicly available
A12: =VLOOKUP(LEFT($A13,4),'Auto Responses'!$N$4:$O$38,2,0)&"" -> General Information | C12: Answer
A13: GNRL-01 | B13: =VLOOKUP($A13,Questions!$A$2:$X$333,2,0)&"" -> Solution Provider Name | C13: =VLOOKUP($A13,'START HERE'!$A$13:$C$21,3,0)&"" -> Coursedog
A14: GNRL-02 | B14: =VLOOKUP($A14,Questions!$A$2:$X$333,2,0)&"" -> Solution Name | C14: =VLOOKUP($A14,'START HERE'!$A$13:$C$21,3,0)&"" -> Coursedog
A15: GNRL-03 | B15: =VLOOKUP($A15,Questions!$A$2:$X$333,2,0)&"" -> Solution Description | C15: =VLOOKUP($A15,'START HERE'!$A$13:$C$21,3,0)&"" -> Coursedog is a SaaS platform designed to streamline curriculum, catalog, and scheduling management for higher education institutions, offering intuitive tools, insightful analytics, and seamless integration without requiring IT involvement.
A16: GNRL-08 | B16: =VLOOKUP($A16,Questions!$A$2:$X$333,2,0)&"" -> Country of Company Headquarters | C16: =VLOOKUP($A16,'START HERE'!$A$13:$C$21,3,0)&"" -> United States
A17: GNRL-09 | B17: =VLOOKUP($A17,Questions!$A$2:$X$333,2,0)&"" -> Employee Work Locations (all) | C17: =VLOOKUP($A17,'START HERE'!$A$13:$C$21,3,0)&"" -> New York, various remote locations
A18: =VLOOKUP(LEFT($A19,4),'Auto Responses'!$N$4:$O$38,2,0)&"" -> Required Questions | C18: Answer | D18: Additional Information | E18: Guidance | F18: Analyst Notes
A19: REQU-04 | B19: =VLOOKUP($A19,Questions!$A$2:$X$333,2,0) -> Does your solution have AI features, or are there plans to implement AI features in the next 12 months? | C19: =VLOOKUP($A19,'START HERE'!$A$23:$F$36,3,0)&"" -> Yes | D19: =VLOOKUP($A19,'START HERE'!$A$23:$F$36,4,0)&"" -> Coursedog has implemented AI features including OpenAI integration for chat completions and embeddings, AI Hub product for controlling AI operations, merge error solutions with AI-powered recommendations, and an agentic chat assistant called "Cassie". | E19: =IF($C19="Yes",VLOOKUP($A19,Questions!$A$2:$X$333,17,0)&"",IF($C19="No",VLOOKUP($A19,Questions!$A$2:$X$333,16,0)&"",VLOOKUP($A19,Questions!$A$2:$X$333,15,0)&"")) -> DO complete the Artificial Intelligence (AI) worksheet | F19: =VLOOKUP($A19,'START HERE'!$A$23:$F$36,6,0)&""
A20: REQU-05 | B20: =VLOOKUP($A20,Questions!$A$2:$X$333,2,0) -> Does your solution process protected health information (PHI) or any data covered by the Health Insurance Portability and Accountability Act (HIPAA)? | C20: =VLOOKUP($A20,'START HERE'!$A$23:$F$36,3,0)&"" -> No | D20: =VLOOKUP($A20,'START HERE'!$A$23:$F$36,4,0)&"" | E20: =IF($C20="Yes",VLOOKUP($A20,Questions!$A$2:$X$333,17,0)&"",IF($C20="No",VLOOKUP($A20,Questions!$A$2:$X$333,16,0)&"",VLOOKUP($A20,Questions!$A$2:$X$333,15,0)&"")) -> DO NOT complete the HIPAA section in the Case-Specific worksheet | F20: =VLOOKUP($A20,'START HERE'!$A$23:$F$36,6,0)&""
A21: REQU-06 | B21: =VLOOKUP($A21,Questions!$A$2:$X$333,2,0) -> Is the solution designed to process, store, or transmit credit card information? | C21: =VLOOKUP($A21,'START HERE'!$A$23:$F$36,3,0)&"" -> No | D21: =VLOOKUP($A21,'START HERE'!$A$23:$F$36,4,0)&"" | E21: =IF($C21="Yes",VLOOKUP($A21,Questions!$A$2:$X$333,17,0)&"",IF($C21="No",VLOOKUP($A21,Questions!$A$2:$X$333,16,0)&"",VLOOKUP($A21,Questions!$A$2:$X$333,15,0)&"")) -> DO NOT complete the PCI-DSS section in the Case-Specific worksheet | F21: =VLOOKUP($A21,'START HERE'!$A$23:$F$36,6,0)&""
A22: REQU-08 | B22: =VLOOKUP($A22,Questions!$A$2:$X$333,2,0) -> Does your solution have access to personal or institutional data? | C22: =VLOOKUP($A22,'START HERE'!$A$23:$F$36,3,0)&"" -> No | D22: =VLOOKUP($A22,'START HERE'!$A$23:$F$36,4,0)&"" | E22: =IF($C22="Yes",VLOOKUP($A22,Questions!$A$2:$X$333,17,0)&"",IF($C22="No",VLOOKUP($A22,Questions!$A$2:$X$333,16,0)&"",VLOOKUP($A22,Questions!$A$2:$X$333,15,0)&"")) -> DO NOT complete the Privacy tab | F22: =VLOOKUP($A22,'START HERE'!$A$23:$F$36,6,0)&"" | G22: End Table Data
A23: =VLOOKUP(LEFT($A24,4),'Auto Responses'!$N$4:$O$38,2,0)&"" -> General Privacy | B23: Privacy | C23: Answer | D23: Additional Information | E23: Guidance | F23: Analyst Notes
A24: PRGN-01 | B24: =VLOOKUP($A24,Questions!$A$2:$X$333,2,0) -> Does your solution process FERPA-related data? | C24: No | E24: =IF($C24="Yes",VLOOKUP($A24,Questions!$A$2:$X$333,17,0)&"",IF($C24="No",VLOOKUP($A24,Questions!$A$2:$X$333,16,0)&"",VLOOKUP($A24,Questions!$A$2:$X$333,15,0)&"")) | F24: =VLOOKUP($A24,'Privacy Analyst Evaluation'!$A$46:$F$120,6,0)&""
A25: PRGN-02 | B25: =VLOOKUP($A25,Questions!$A$2:$X$333,2,0) -> Does your solution process GDPR-related or PIPL-related data? | C25: No | E25: =IF($C25="Yes",VLOOKUP($A25,Questions!$A$2:$X$333,17,0)&"",IF($C25="No",VLOOKUP($A25,Questions!$A$2:$X$333,16,0)&"",VLOOKUP($A25,Questions!$A$2:$X$333,15,0)&"")) | F25: =VLOOKUP($A25,'Privacy Analyst Evaluation'!$A$46:$F$120,6,0)&""
A26: PRGN-03 | B26: =VLOOKUP($A26,Questions!$A$2:$X$333,2,0) -> Does your solution process personal data regulated by state law(s) (e.g., CCPA)? | C26: No | E26: =IF($C26="Yes",VLOOKUP($A26,Questions!$A$2:$X$333,17,0)&"",IF($C26="No",VLOOKUP($A26,Questions!$A$2:$X$333,16,0)&"",VLOOKUP($A26,Questions!$A$2:$X$333,15,0)&"")) | F26: =VLOOKUP($A26,'Privacy Analyst Evaluation'!$A$46:$F$120,6,0)&""
A27: PRGN-04 | B27: =VLOOKUP($A27,Questions!$A$2:$X$333,2,0) -> Does your solution process user-provided data that may contain regulated information? | C27: No | D27: https://www.coursedog.com/privacy-policy | E27: =IF($C27="Yes",VLOOKUP($A27,Questions!$A$2:$X$333,17,0)&"",IF($C27="No",VLOOKUP($A27,Questions!$A$2:$X$333,16,0)&"",VLOOKUP($A27,Questions!$A$2:$X$333,15,0)&"")) | F27: =VLOOKUP($A27,'Privacy Analyst Evaluation'!$A$46:$F$120,6,0)&""
A28: PRGN-05 | B28: =VLOOKUP($A28,Questions!$A$2:$X$333,2,0) -> Web Link to Product/Service Privacy Notice | D28: =VLOOKUP($A28,Questions!$A$2:$X$333,2,0) -> Web Link to Product/Service Privacy Notice | E28: =IF($C28="Yes",VLOOKUP($A28,Questions!$A$2:$X$333,17,0)&"",IF($C28="No",VLOOKUP($A28,Questions!$A$2:$X$333,16,0)&"",VLOOKUP($A28,Questions!$A$2:$X$333,15,0)&"")) | F28: =VLOOKUP($A28,'Privacy Analyst Evaluation'!$A$46:$F$120,6,0)&"" | G28: End Table Data
A29: =VLOOKUP(LEFT($A30,4),'Auto Responses'!$N$4:$O$38,2,0)&"" -> Privacy-Specific Company Details | B29: Information not publicly available | C29: Answer | D29: Additional Information | E29: Guidance | F29: Analyst Notes
A30: PCOM-01 | B30: =VLOOKUP($A30,Questions!$A$2:$X$333,2,0) -> Have you had a personal data breach in the past three years that involved reporting to a governmental agency, notice to individuals (including voluntary notice), or notice to another organization or institution?* | C30: No | E30: =IF($C30="Yes",VLOOKUP($A30,Questions!$A$2:$X$333,17,0)&"",IF($C30="No",VLOOKUP($A30,Questions!$A$2:$X$333,16,0)&"",VLOOKUP($A30,Questions!$A$2:$X$333,15,0)&"")) | F30: =VLOOKUP($A30,'Privacy Analyst Evaluation'!$A$46:$F$120,6,0)&""
A31: PCOM-02 | B31: =VLOOKUP($A31,Questions!$A$2:$X$333,2,0) -> Use this area to share information about your privacy practices that will assist those who are assessing your company data privacy program.* | D31: Coursedog collects personal data including email, name, phone, address. Uses third-party service providers like Google Analytics. Transfers data to US. Implements security measures though acknowledges no method is 100% secure. Does not knowingly collect data from children under 18. Contact: 228 Park Avenue S, PMB 70159, New York, NY 10003 | E31: =IF($C31="Yes",VLOOKUP($A31,Questions!$A$2:$X$333,17,0)&"",IF($C31="No",VLOOKUP($A31,Questions!$A$2:$X$333,16,0)&"",VLOOKUP($A31,Questions!$A$2:$X$333,15,0)&"")) -> Share any details that would help data privacy analysts assess your solution. | F31: =VLOOKUP($A31,'Privacy Analyst Evaluation'!$A$46:$F$120,6,0)&""
A32: PCOM-03 | B32: =VLOOKUP($A32,Questions!$A$2:$X$333,2,0) -> Have you had any data privacy policy or law violations in the past 36 months? | C32: No | E32: =IF($C32="Yes",VLOOKUP($A32,Questions!$A$2:$X$333,17,0)&"",IF($C32="No",VLOOKUP($A32,Questions!$A$2:$X$333,16,0)&"",VLOOKUP($A32,Questions!$A$2:$X$333,15,0)&"")) | F32: =VLOOKUP($A32,'Privacy Analyst Evaluation'!$A$46:$F$120,6,0)&""
A33: PCOM-04 | B33: =VLOOKUP($A33,Questions!$A$2:$X$333,2,0) -> Do you have a dedicated data privacy staff or office? | C33: Yes | D33: Roughly haf of Coursedog is dedicated to R&D. This includes a Product Management and engineering teams. The Engineering team is led by a CTO and has a full time security officer. Each Engineer adheres to best practices set forth by the organization. Coursedog leverages external third parties for vulnerability scans and hosting (i.e. AWS). | E33: =IF($C33="Yes",VLOOKUP($A33,Questions!$A$2:$X$333,17,0)&"",IF($C33="No",VLOOKUP($A33,Questions!$A$2:$X$333,16,0)&"",VLOOKUP($A33,Questions!$A$2:$X$333,15,0)&"")) | F33: =VLOOKUP($A33,'Privacy Analyst Evaluation'!$A$46:$F$120,6,0)&"" | G33: End Table Data
A34: =VLOOKUP(LEFT($A35,4),'Auto Responses'!$N$4:$O$38,2,0)&"" -> Privacy-Specific Documentation | C34: Answer | D34: Additional Information | E34: Guidance | F34: Analyst Notes
A35: PDOC-01 | B35: =VLOOKUP($A35,Questions!$A$2:$X$333,2,0) -> If you have completed a SOC 2 audit, does it include the Privacy Trust Service Principle? | D35: See AWS SOC documentation | E35: =IF($C35="Yes",VLOOKUP($A35,Questions!$A$2:$X$333,17,0)&"",IF($C35="No",VLOOKUP($A35,Questions!$A$2:$X$333,16,0)&"",VLOOKUP($A35,Questions!$A$2:$X$333,15,0)&"")) -> SOC 2 Type 2 audits can be conducted for any or all of five trust principles (confidentiality, integrity, availability, security, and privacy). Answer "yes" if your audit included the privacy principle. | F35: =VLOOKUP($A35,'Privacy Analyst Evaluation'!$A$46:$F$120,6,0)&""
A36: PDOC-02 | B36: =VLOOKUP($A36,Questions!$A$2:$X$333,2,0) -> Do you conform with a specific industry-standard privacy framework (e.g., NIST Privacy Framework, GDPR, ISO 27701)? | C36: No | D36: Coursedog has not obtained NIST SP 800-171 or CMMC Level 2 compliance certifications. However, Coursedog follows industry best practices for data security. Coursedog is in the process of obtaining the official ISO27001 certification. | E36: =IF($C36="Yes",VLOOKUP($A36,Questions!$A$2:$X$333,17,0)&"",IF($C36="No",VLOOKUP($A36,Questions!$A$2:$X$333,16,0)&"",VLOOKUP($A36,Questions!$A$2:$X$333,15,0)&"")) -> Provide any plans to conform. | F36: =VLOOKUP($A36,'Privacy Analyst Evaluation'!$A$46:$F$120,6,0)&""
A37: PDOC-03 | B37: =VLOOKUP($A37,Questions!$A$2:$X$333,2,0) -> Does your employee onboarding and offboarding policy include training of employees on information security and data privacy? | C37: Yes | D37: The Coursedog onboarding and offboarding document contains sensitive information and therefore is not available publically. | E37: =IF($C37="Yes",VLOOKUP($A37,Questions!$A$2:$X$333,17,0)&"",IF($C37="No",VLOOKUP($A37,Questions!$A$2:$X$333,16,0)&"",VLOOKUP($A37,Questions!$A$2:$X$333,15,0)&"")) | F37: =VLOOKUP($A37,'Privacy Analyst Evaluation'!$A$46:$F$120,6,0)&"" | G37: End Table Data
A38: =VLOOKUP(LEFT($A39,4),'Auto Responses'!$N$4:$O$38,2,0)&"" -> Privacy of Third Parties | C38: Answer | D38: Additional Information | E38: Guidance | F38: Analyst Notes
A39: PTHP-01 | B39: =VLOOKUP($A39,Questions!$A$2:$X$333,2,0) -> Do you have contractual agreements with third parties that require them to maintain standards and to comply with all regulatory requirements?* | C39: Yes | D39: For each of these vendors, we use their standard SaaS agreements and each of them have guardrails in place the address liabiliity in case of a data breach. | F39: =VLOOKUP($A39,'Privacy Analyst Evaluation'!$A$46:$F$120,6,0)&""
A40: PTHP-02 | B40: =VLOOKUP($A40,Questions!$A$2:$X$333,2,0) -> Do you perform privacy impact assesments of third parties that collect, process, or have access to personal data to ensure they meet industry and regulatory standards and to mitigate harmful, unethical, or discriminatory impacts on data subjects? | C40: Yes | D40: Coursedog assess third party vendors based on data security (use of encryption and data security during processing transmission and storage, and data recoverable procedures) and network security (review of network architecture and security configurations, Anti-virus controls, penetration testing, security monitoring capabilities). | F40: =VLOOKUP($A40,'Privacy Analyst Evaluation'!$A$46:$F$120,6,0)&"" | G40: End Table Data
A41: =VLOOKUP(LEFT($A42,4),'Auto Responses'!$N$4:$O$38,2,0)&"" -> Privacy Change Management | C41: Answer | D41: Additional Information | E41: Guidance | F41: Analyst Notes
A42: PCHG-01 | B42: =VLOOKUP($A42,Questions!$A$2:$X$333,2,0) -> Does your change management process include privacy review and approval? | C42: Yes | D42: The Coursedog head Application Engineer will make these decisions on a case by case basis. Coursedog always has the ability to roll back versions due to our cloud based architecture. See our response to CHNG-14. | E42: =IF($C42="Yes",VLOOKUP($A42,Questions!$A$2:$X$333,17,0)&"",IF($C42="No",VLOOKUP($A42,Questions!$A$2:$X$333,16,0)&"",VLOOKUP($A42,Questions!$A$2:$X$333,15,0)&"")) -> Please describe your process for privacy review. | F42: =VLOOKUP($A42,'Privacy Analyst Evaluation'!$A$46:$F$120,6,0)&""
A43: PCHG-02 | B43: =VLOOKUP($A43,Questions!$A$2:$X$333,2,0) -> Do you have policy and procedure, currently implemented, guiding how privacy risks are mitigated until they can be resolved? | C43: Yes | D43: The Coursedog head Application Engineer will make these decisions on a case by case basis. Coursedog always has the ability to roll back versions due to our cloud based architecture. See our response to CHNG-14. | E43: =IF($C43="Yes",VLOOKUP($A43,Questions!$A$2:$X$333,17,0)&"",IF($C43="No",VLOOKUP($A43,Questions!$A$2:$X$333,16,0)&"",VLOOKUP($A43,Questions!$A$2:$X$333,15,0)&"")) | F43: =VLOOKUP($A43,'Privacy Analyst Evaluation'!$A$46:$F$120,6,0)&"" | G43: End Table Data
A44: =VLOOKUP(LEFT($A45,4),'Auto Responses'!$N$4:$O$38,2,0)&"" -> Privacy of Sensitive Data | C44: Answer | D44: Additional Information | E44: Guidance | F44: Analyst Notes
A45: PDAT-01 | B45: =VLOOKUP($A45,Questions!$A$2:$X$333,2,0) -> Do you collect, process, or store demographic information?* | C45: No | E45: =IF($C45="Yes",VLOOKUP($A45,Questions!$A$2:$X$333,17,0)&"",IF($C45="No",VLOOKUP($A45,Questions!$A$2:$X$333,16,0)&"",VLOOKUP($A45,Questions!$A$2:$X$333,15,0)&"")) | F45: =VLOOKUP($A45,'Privacy Analyst Evaluation'!$A$46:$F$120,6,0)&""
A46: PDAT-02 | B46: =VLOOKUP($A46,Questions!$A$2:$X$333,2,0) -> Do you capture or create genetic, biometric, or behaviometric information (e.g., facial recognition or fingerprints)?* | C46: No | E46: =IF($C46="Yes",VLOOKUP($A46,Questions!$A$2:$X$333,17,0)&"",IF($C46="No",VLOOKUP($A46,Questions!$A$2:$X$333,16,0)&"",VLOOKUP($A46,Questions!$A$2:$X$333,15,0)&"")) | F46: =VLOOKUP($A46,'Privacy Analyst Evaluation'!$A$46:$F$120,6,0)&""
A47: PDAT-03 | B47: =VLOOKUP($A47,Questions!$A$2:$X$333,2,0) -> Do you combine institutional data (including "de-identified," "anonymized," or otherwise masked data) with personal data from any other sources?* | C47: No | E47: =IF($C47="Yes",VLOOKUP($A47,Questions!$A$2:$X$333,17,0)&"",IF($C47="No",VLOOKUP($A47,Questions!$A$2:$X$333,16,0)&"",VLOOKUP($A47,Questions!$A$2:$X$333,15,0)&"")) | F47: =VLOOKUP($A47,'Privacy Analyst Evaluation'!$A$46:$F$120,6,0)&""
A48: PDAT-04 | B48: =VLOOKUP($A48,Questions!$A$2:$X$333,2,0) -> Is institutional data coming into or going out of the United States at any point during collection, processing, storage, or archiving? | C48: No | E48: =IF($C48="Yes",VLOOKUP($A48,Questions!$A$2:$X$333,17,0)&"",IF($C48="No",VLOOKUP($A48,Questions!$A$2:$X$333,16,0)&"",VLOOKUP($A48,Questions!$A$2:$X$333,15,0)&"")) | F48: =VLOOKUP($A48,'Privacy Analyst Evaluation'!$A$46:$F$120,6,0)&""
A49: PDAT-05 | B49: =VLOOKUP($A49,Questions!$A$2:$X$333,2,0) -> Do you capture device information (e.g., IP address, MAC address)? | C49: No | E49: =IF($C49="Yes",VLOOKUP($A49,Questions!$A$2:$X$333,17,0)&"",IF($C49="No",VLOOKUP($A49,Questions!$A$2:$X$333,16,0)&"",VLOOKUP($A49,Questions!$A$2:$X$333,15,0)&"")) | F49: =VLOOKUP($A49,'Privacy Analyst Evaluation'!$A$46:$F$120,6,0)&""
A50: PDAT-06 | B50: =VLOOKUP($A50,Questions!$A$2:$X$333,2,0) -> Does any part of this service/project involve a web/app tracking component (e.g., use of web-tracking pixels, cookies)? | C50: No | E50: =IF($C50="Yes",VLOOKUP($A50,Questions!$A$2:$X$333,17,0)&"",IF($C50="No",VLOOKUP($A50,Questions!$A$2:$X$333,16,0)&"",VLOOKUP($A50,Questions!$A$2:$X$333,15,0)&"")) | F50: =VLOOKUP($A50,'Privacy Analyst Evaluation'!$A$46:$F$120,6,0)&""
A51: PDAT-07 | B51: =VLOOKUP($A51,Questions!$A$2:$X$333,2,0) -> Does your staff (or a third party) have access to institutional data (e.g., financial, PHI, or other sensitive information) through any means? | C51: No | D51: Coursedog does not integrate with or leverage PHI data | E51: =IF($C51="Yes",VLOOKUP($A51,Questions!$A$2:$X$333,17,0)&"",IF($C51="No",VLOOKUP($A51,Questions!$A$2:$X$333,16,0)&"",VLOOKUP($A51,Questions!$A$2:$X$333,15,0)&"")) | F51: =VLOOKUP($A51,'Privacy Analyst Evaluation'!$A$46:$F$120,6,0)&""
A52: PDAT-08 | B52: =VLOOKUP($A52,Questions!$A$2:$X$333,2,0) -> Will you handle personal data in a manner compliant with all relevant laws, regulations, and applicable institution policies? | C52: Yes | E52: =IF($C52="Yes",VLOOKUP($A52,Questions!$A$2:$X$333,17,0)&"",IF($C52="No",VLOOKUP($A52,Questions!$A$2:$X$333,16,0)&"",VLOOKUP($A52,Questions!$A$2:$X$333,15,0)&"")) | F52: =VLOOKUP($A52,'Privacy Analyst Evaluation'!$A$46:$F$120,6,0)&"" | G52: End Table Data
A53: =VLOOKUP(LEFT($A54,4),'Auto Responses'!$N$4:$O$38,2,0)&"" -> Privacy Policies and Procedures | C53: Answer | D53: Additional Information | E53: Guidance | F53: Analyst Notes
A54: PRPO-01 | B54: =VLOOKUP($A54,Questions!$A$2:$X$333,2,0) -> Do you have a documented privacy management process? | C54: Yes | D54: See our Privacy Policy | E54: =IF($C54="Yes",VLOOKUP($A54,Questions!$A$2:$X$333,17,0)&"",IF($C54="No",VLOOKUP($A54,Questions!$A$2:$X$333,16,0)&"",VLOOKUP($A54,Questions!$A$2:$X$333,15,0)&"")) -> Describe privacy management process or provide links or attach documentation. | F54: =VLOOKUP($A54,'Privacy Analyst Evaluation'!$A$46:$F$120,6,0)&""
A55: PRPO-02 | B55: =VLOOKUP($A55,Questions!$A$2:$X$333,2,0) -> Are privacy principles designed into the product lifecycle (i.e., privacy-by-design)? | C55: Yes | D55: See our Privacy Policy | E55: =IF($C55="Yes",VLOOKUP($A55,Questions!$A$2:$X$333,17,0)&"",IF($C55="No",VLOOKUP($A55,Questions!$A$2:$X$333,16,0)&"",VLOOKUP($A55,Questions!$A$2:$X$333,15,0)&"")) -> Summarize the privacy principles designed into the product lifecycle. | F55: =VLOOKUP($A55,'Privacy Analyst Evaluation'!$A$46:$F$120,6,0)&""
A56: PRPO-03 | B56: =VLOOKUP($A56,Questions!$A$2:$X$333,2,0) -> Will you comply with applicable breach notification laws? | C56: Yes | D56: in SLA | E56: =IF($C56="Yes",VLOOKUP($A56,Questions!$A$2:$X$333,17,0)&"",IF($C56="No",VLOOKUP($A56,Questions!$A$2:$X$333,16,0)&"",VLOOKUP($A56,Questions!$A$2:$X$333,15,0)&"")) -> State how quickly the institution will be notified. | F56: =VLOOKUP($A56,'Privacy Analyst Evaluation'!$A$46:$F$120,6,0)&""
A57: PRPO-04 | B57: =VLOOKUP($A57,Questions!$A$2:$X$333,2,0) -> Will you comply with the institution's policies regarding user privacy and data protection? | C57: No | D57: Coursedog followes industry standard security policies and is willing to discuss the specific policy. | E57: =IF($C57="Yes",VLOOKUP($A57,Questions!$A$2:$X$333,17,0)&"",IF($C57="No",VLOOKUP($A57,Questions!$A$2:$X$333,16,0)&"",VLOOKUP($A57,Questions!$A$2:$X$333,15,0)&"")) -> Provide reason for not complying. | F57: =VLOOKUP($A57,'Privacy Analyst Evaluation'!$A$46:$F$120,6,0)&""
A58: PRPO-05 | B58: =VLOOKUP($A58,Questions!$A$2:$X$333,2,0) -> Is your company subject to the laws and regulations of the institution's geographic region? | C58: Yes | E58: =IF($C58="Yes",VLOOKUP($A58,Questions!$A$2:$X$333,17,0)&"",IF($C58="No",VLOOKUP($A58,Questions!$A$2:$X$333,16,0)&"",VLOOKUP($A58,Questions!$A$2:$X$333,15,0)&"")) | F58: =VLOOKUP($A58,'Privacy Analyst Evaluation'!$A$46:$F$120,6,0)&""
A59: PRPO-06 | B59: =VLOOKUP($A59,Questions!$A$2:$X$333,2,0) -> Do you have a privacy awareness/training program?* | C59: Yes | D59: Once annually and during onboarding | E59: =IF($C59="Yes",VLOOKUP($A59,Questions!$A$2:$X$333,17,0)&"",IF($C59="No",VLOOKUP($A59,Questions!$A$2:$X$333,16,0)&"",VLOOKUP($A59,Questions!$A$2:$X$333,15,0)&"")) | F59: =VLOOKUP($A59,'Privacy Analyst Evaluation'!$A$46:$F$120,6,0)&""
A60: PRPO-07 | B60: =VLOOKUP($A60,Questions!$A$2:$X$333,2,0) -> Is privacy awareness training mandatory for all employees? | C60: Yes | D60: Once annually and during onboarding | E60: =IF($C60="Yes",VLOOKUP($A60,Questions!$A$2:$X$333,17,0)&"",IF($C60="No",VLOOKUP($A60,Questions!$A$2:$X$333,16,0)&"",VLOOKUP($A60,Questions!$A$2:$X$333,15,0)&"")) -> Summarize your privacy awareness training content and state how frequently employees are required to undergo privacy awareness training | F60: =VLOOKUP($A60,'Privacy Analyst Evaluation'!$A$46:$F$120,6,0)&""
A61: PRPO-08 | B61: =VLOOKUP($A61,Questions!$A$2:$X$333,2,0) -> Is AI privacy and ethics awareness/training required for all employees who work with AI? | C61: Yes | D61: Once annually and during onboarding | E61: =IF($C61="Yes",VLOOKUP($A61,Questions!$A$2:$X$333,17,0)&"",IF($C61="No",VLOOKUP($A61,Questions!$A$2:$X$333,16,0)&"",VLOOKUP($A61,Questions!$A$2:$X$333,15,0)&"")) | F61: =VLOOKUP($A61,'Privacy Analyst Evaluation'!$A$46:$F$120,6,0)&""
A62: PRPO-09 | B62: =VLOOKUP($A62,Questions!$A$2:$X$333,2,0) -> Do you have any decision-making processes that are completely automated (i.e., there is no human involvement)? | C62: No | E62: =IF($C62="Yes",VLOOKUP($A62,Questions!$A$2:$X$333,17,0)&"",IF($C62="No",VLOOKUP($A62,Questions!$A$2:$X$333,16,0)&"",VLOOKUP($A62,Questions!$A$2:$X$333,15,0)&"")) | F62: =VLOOKUP($A62,'Privacy Analyst Evaluation'!$A$46:$F$120,6,0)&""
A63: PRPO-10 | B63: =VLOOKUP($A63,Questions!$A$2:$X$333,2,0) -> Do you have a documented process for managing automated processing, including validations, monitoring, and data subject requests? | C63: Yes | D63: https://coursedog.my.site.com/support/s/knowledge-base | E63: =IF($C63="Yes",VLOOKUP($A63,Questions!$A$2:$X$333,17,0)&"",IF($C63="No",VLOOKUP($A63,Questions!$A$2:$X$333,16,0)&"",VLOOKUP($A63,Questions!$A$2:$X$333,15,0)&"")) -> Provide documentation describing management processes. | F63: =VLOOKUP($A63,'Privacy Analyst Evaluation'!$A$46:$F$120,6,0)&""
A64: PRPO-11 | B64: =VLOOKUP($A64,Questions!$A$2:$X$333,2,0) -> Do you have a documented policy for sharing information with law enforcement? | C64: Yes | D64: Available upon request | E64: =IF($C64="Yes",VLOOKUP($A64,Questions!$A$2:$X$333,17,0)&"",IF($C64="No",VLOOKUP($A64,Questions!$A$2:$X$333,16,0)&"",VLOOKUP($A64,Questions!$A$2:$X$333,15,0)&"")) | F64: =VLOOKUP($A64,'Privacy Analyst Evaluation'!$A$46:$F$120,6,0)&""
A65: PRPO-12 | B65: =VLOOKUP($A65,Questions!$A$2:$X$333,2,0) -> Do you share any institutional data with law enforcement without a valid warrant?* | C65: No | E65: =IF($C65="Yes",VLOOKUP($A65,Questions!$A$2:$X$333,17,0)&"",IF($C65="No",VLOOKUP($A65,Questions!$A$2:$X$333,16,0)&"",VLOOKUP($A65,Questions!$A$2:$X$333,15,0)&"")) | F65: =VLOOKUP($A65,'Privacy Analyst Evaluation'!$A$46:$F$120,6,0)&""
A66: PRPO-13 | B66: =VLOOKUP($A66,Questions!$A$2:$X$333,2,0) -> Does your incident response team include a privacy analyst/officer? | C66: Yes | D66: See incident response process. | E66: =IF($C66="Yes",VLOOKUP($A66,Questions!$A$2:$X$333,17,0)&"",IF($C66="No",VLOOKUP($A66,Questions!$A$2:$X$333,16,0)&"",VLOOKUP($A66,Questions!$A$2:$X$333,15,0)&"")) | F66: =VLOOKUP($A66,'Privacy Analyst Evaluation'!$A$46:$F$120,6,0)&"" | G66: End Table Data
A67: =VLOOKUP(LEFT($A68,4),'Auto Responses'!$N$4:$O$38,2,0)&"" -> International Privacy | C67: Answer | D67: Additional Information | E67: Guidance | F67: Analyst Notes
A68: INTL-01 | B68: =VLOOKUP($A68,Questions!$A$2:$X$333,2,0) -> Will data be collected from or processed in or stored in the European Economic Area (EEA)? | C68: No | E68: =IF($C68="Yes",VLOOKUP($A68,Questions!$A$2:$X$333,17,0)&"",IF($C68="No",VLOOKUP($A68,Questions!$A$2:$X$333,16,0)&"",VLOOKUP($A68,Questions!$A$2:$X$333,15,0)&"")) | F68: =VLOOKUP($A68,'Privacy Analyst Evaluation'!$A$46:$F$120,6,0)&""
A69: INTL-02 | B69: =VLOOKUP($A69,Questions!$A$2:$X$333,2,0) -> Do you have a data protection officer (DPO)? | C69: No | E69: =IF($C69="Yes",VLOOKUP($A69,Questions!$A$2:$X$333,17,0)&"",IF($C69="No",VLOOKUP($A69,Questions!$A$2:$X$333,16,0)&"",VLOOKUP($A69,Questions!$A$2:$X$333,15,0)&"")) | F69: =VLOOKUP($A69,'Privacy Analyst Evaluation'!$A$46:$F$120,6,0)&""
A70: INTL-03 | B70: =VLOOKUP($A70,Questions!$A$2:$X$333,2,0) -> Will you sign appropriate GDPR Standard Contractual Clauses (SCCs) with the institution? | C70: Yes | D70: if applicable | E70: =IF($C70="Yes",VLOOKUP($A70,Questions!$A$2:$X$333,17,0)&"",IF($C70="No",VLOOKUP($A70,Questions!$A$2:$X$333,16,0)&"",VLOOKUP($A70,Questions!$A$2:$X$333,15,0)&"")) | F70: =VLOOKUP($A70,'Privacy Analyst Evaluation'!$A$46:$F$120,6,0)&""
A71: INTL-04 | B71: =VLOOKUP($A71,Questions!$A$2:$X$333,2,0) -> Will data be collected from or processed in or stored in China? | C71: No | E71: =IF($C71="Yes",VLOOKUP($A71,Questions!$A$2:$X$333,17,0)&"",IF($C71="No",VLOOKUP($A71,Questions!$A$2:$X$333,16,0)&"",VLOOKUP($A71,Questions!$A$2:$X$333,15,0)&"")) | F71: =VLOOKUP($A71,'Privacy Analyst Evaluation'!$A$46:$F$120,6,0)&""
A72: INTL-05 | B72: =VLOOKUP($A72,Questions!$A$2:$X$333,2,0) -> Do you comply with PIPL security, privacy, and data localization requirements? | C72: N/A | E72: =IF($C72="Yes",VLOOKUP($A72,Questions!$A$2:$X$333,17,0)&"",IF($C72="No",VLOOKUP($A72,Questions!$A$2:$X$333,16,0)&"",VLOOKUP($A72,Questions!$A$2:$X$333,15,0)&"")) | F72: =VLOOKUP($A72,'Privacy Analyst Evaluation'!$A$46:$F$120,6,0)&"" | G72: End Table Data
A73: =VLOOKUP(LEFT($A74,4),'Auto Responses'!$N$4:$O$38,2,0)&"" -> Data Privacy | C73: Answer | D73: Additional Information | E73: Guidance | F73: Analyst Notes
